Workbook
Name ___Area_de_impresión: Cotización!$B$1:$L$119
Name ___Area_de_impresión: 'OP TELAS'!$B$1:$L$132
Name __Area_de_impresión: 'NV CAJAS (BL)'!$C$13:$S$52
Name _Area_de_impresión: Cotización!$B$1:$L$119
Name _Area_de_impresión: hoja1!$A$1:$H$47
Name _Area_de_impresión: 'NV CAJAS (BL)'!$C$13:$O$60

Sheet Valores
C1: Venta Directa | F1: RC Ferias | I1: Inser
A2: Tela | B2: Valor Mínimo | C2: 3-50 m2 | D2: 51-100 m2 | E2: 101-200 m2 | F2: 3-50 m2 | G2: 51-100 m2 | H2: 101-200 m2 | I2: 3-100 m2 | J2: 101-300 m2
A3: 1104 - Bandera | B3: 35000 | C3: 14000 | D3: 12500 | E3: 10500 | F3: 11000 | G3: 9500 | H3: 8000 | I3: 9500 | J3: 8000
A4: 1106 - Mesh Mate | B4: 36000 | C4: 15000 | D4: 13000 | E4: 11500 | F4: 11500 | G4: 10000 | H4: 9000 | I4: 10000 | J4: 9000
A5: 1107 - Mesh Brillante | B5: 36000 | C5: 15000 | D5: 13000 | E5: 11500 | F5: 11500 | G5: 10000 | H5: 9000 | I5: 10000 | J5: 9000
A6: 1102 - Satín | B6: 40000 | C6: 15500 | D6: 13500 | E6: 12000 | F6: 12000 | G6: 11000 | H6: 10000 | I6: 11000 | J6: 10000
A7: 1108 - Perforado | B7: 40000 | C7: 16000 | D7: 14000 | E7: 12500 | F7: 12500 | G7: 11500 | H7: 10500 | I7: 11500 | J7: 10500
A8: 1109 - Canvas | B8: 40000 | C8: 16500 | D8: 14500 | E8: 13000 | F8: 13000 | G8: 12000 | H8: 11000 | I8: 12000 | J8: 11000
A9: 1140 - Popelina | B9: 45000 | C9: 17000 | D9: 15000 | E9: 14000 | F9: 14000 | G9: 13000 | H9: 12000 | I9: 13000 | J9: 12000
A11: Item de Ingreso | B11: si/no | C11: Fuente | D11: Soporte | E11: Costura
A12: E-Mail | B12: Sí | C12: Directo | D12: Pop Up | E12: Simple
A13: CD/DVD | B13: No | C13: RC Ferias | D13: Roller | E13: Doble
A14: Laser | C14: Inser | D14: Pendón
A15: Otros | D15: Bandera
D16: Panel
D17: Otros

Sheet Nota de venta
B2: Fecha: | G2: COTIZACIÓN Nº- | Z2: CONFIGURACION
B4: DATOS CLIENTE | Z4: Productos: | AC4: Textil | AD4: Ancho | AE4: Valor/M2 | AG4: METROS IMPRESOS EXTRA: | AH4: 0.1 | AJ4: Producto | AK4: Valor unit | AQ4: Productos
B5: Contacto: | H5: Razon Social | Z5: accesorios para colgar | AC5: Popelina 155 | AD5: 1.53 | AE5: 27000 | AJ5: accesorios para colgar | AK5: 7500 | AQ5: Asta fibra de vidrio vela 2 mts
B6: Empresa: | H6: Rut: | Z6: asta vela 3m | AC6: Popelina 310 | AD6: 3.08 | AE6: 31000 | AJ6: asta vela 3m | AK6: 17000 | AQ6: Asta fibra de vidrio vela 3 mts
B7: Email: | H7: Fuente: | Z7: asta vela 4m | AC7: Pearl 155 | AD7: 1.53 | AE7: 23000 | AJ7: asta vela 4m | AK7: 19000 | AQ7: Bandera 2,3x1,5
Z8: banderas | AC8: Pearl 310 | AD8: 3.08 | AE8: 31000 | AJ8: banderas | AK8: 5000 | AQ8: Bandera 3x2
B9: Producto | C9: Textil | D9: Ancho Tela | E9: Ancho | F9: Alto | G9: Cantidad | H9: unid x ancho | I9: ratio | J9: ML impresos | K9: valor x ML | L9: Tema | Z9: base auto | AC9: Pearl 160 HP | AD9: 1.6 | AE9: 23000 | AJ9: base auto | AK9: 11000 | AQ9: Bandera 1,5x1
A10: 1 | D10: =IF(ISTEXT(C10),VLOOKUP(C10,$AC$5:$AE$234,2,FALSE),"") | H10: =IF(ISNUMBER(E10),IF(ROUNDDOWN(D10/E10,0)<1,NotaDeVenta[[#This Row],[Ancho Tela]]/NotaDeVenta[[#This Row],[Ancho]],ROUND(NotaDeVenta[[#This Row],[Ancho Tela]]/NotaDeVenta[[#This Row],[Ancho]],0)),"") | I10: =IF(ISNUMBER(H10),G10/H10,"") | J10: =IF(ISNUMBER(G10),IF(OR(B10="Textil Backlight",B10="Caja + Backlight"),E10*F10*G10,F10*I10),0) -> 0 | K10: =IF(ISTEXT(C10),VLOOKUP(C10,$AC$5:$AE$234,3,FALSE),"") | L10: Tema | Z10: base suelo metal más accesorio | AC10: Bistretch | AD10: 1.48 | AE10: 11000 | AJ10: base suelo metal más accesorio | AK10: 15000 | AQ10: Base auto
A11: 2 | D11: =IF(ISTEXT(C11),VLOOKUP(C11,$AC$5:$AE$234,2,FALSE),"") | H11: =IF(ISNUMBER(E11),IF(ROUNDDOWN(D11/E11,0)<1,NotaDeVenta[[#This Row],[Ancho Tela]]/NotaDeVenta[[#This Row],[Ancho]],ROUND(NotaDeVenta[[#This Row],[Ancho Tela]]/NotaDeVenta[[#This Row],[Ancho]],0)),"") | I11: =IF(ISNUMBER(H11),G11/H11,"") | J11: =IF(ISNUMBER(G11),IF(OR(B11="Textil Backlight",B11="Caja + Backlight"),E11*F11*G11,F11*I11),0) -> 0 | K11: =IF(ISTEXT(C11),VLOOKUP(C11,$AC$5:$AE$234,3,FALSE),"")
A12: 3 | D12: =IF(ISTEXT(C12),VLOOKUP(C12,$AC$5:$AE$234,2,FALSE),"") | H12: =IF(ISNUMBER(E12),IF(ROUNDDOWN(D12/E12,0)<1,NotaDeVenta[[#This Row],[Ancho Tela]]/NotaDeVenta[[#This Row],[Ancho]],ROUND(NotaDeVenta[[#This Row],[Ancho Tela]]/NotaDeVenta[[#This Row],[Ancho]],0)),"") | I12: =IF(ISNUMBER(H12),G12/H12,"") | J12: =IF(ISNUMBER(G12),IF(OR(B12="Textil Backlight",B12="Caja + Backlight"),E12*F12*G12,F12*I12),0) -> 0 | K12: =IF(ISTEXT(C12),VLOOKUP(C12,$AC$5:$AE$234,3,FALSE),"")
A13: 4 | D13: =IF(ISTEXT(C13),VLOOKUP(C13,$AC$5:$AE$234,2,FALSE),"") | H13: =IF(ISNUMBER(E13),IF(ROUNDDOWN(D13/E13,0)<1,NotaDeVenta[[#This Row],[Ancho Tela]]/NotaDeVenta[[#This Row],[Ancho]],ROUND(NotaDeVenta[[#This Row],[Ancho Tela]]/NotaDeVenta[[#This Row],[Ancho]],0)),"") | I13: =IF(ISNUMBER(H13),G13/H13,"") | J13: =IF(ISNUMBER(G13),IF(OR(B13="Textil Backlight",B13="Caja + Backlight"),E13*F13*G13,F13*I13),0) -> 0 | K13: =IF(ISTEXT(C13),VLOOKUP(C13,$AC$5:$AE$234,3,FALSE),"")
A14: 5 | D14: =IF(ISTEXT(C14),VLOOKUP(C14,$AC$5:$AE$234,2,FALSE),"") | H14: =IF(ISNUMBER(E14),IF(ROUNDDOWN(D14/E14,0)<1,NotaDeVenta[[#This Row],[Ancho Tela]]/NotaDeVenta[[#This Row],[Ancho]],ROUND(NotaDeVenta[[#This Row],[Ancho Tela]]/NotaDeVenta[[#This Row],[Ancho]],0)),"") | I14: =IF(ISNUMBER(H14),G14/H14,"") | J14: =IF(ISNUMBER(G14),IF(OR(B14="Textil Backlight",B14="Caja + Backlight"),E14*F14*G14,F14*I14),0) -> 0 | K14: =IF(ISTEXT(C14),VLOOKUP(C14,$AC$5:$AE$234,3,FALSE),"")
A15: 6 | D15: =IF(ISTEXT(C15),VLOOKUP(C15,$AC$5:$AE$234,2,FALSE),"") | H15: =IF(ISNUMBER(E15),IF(ROUNDDOWN(D15/E15,0)<1,NotaDeVenta[[#This Row],[Ancho Tela]]/NotaDeVenta[[#This Row],[Ancho]],ROUND(NotaDeVenta[[#This Row],[Ancho Tela]]/NotaDeVenta[[#This Row],[Ancho]],0)),"") | I15: =IF(ISNUMBER(H15),G15/H15,"") | J15: =IF(ISNUMBER(G15),IF(OR(B15="Textil Backlight",B15="Caja + Backlight"),E15*F15*G15,F15*I15),0) -> 0 | K15: =IF(ISTEXT(C15),VLOOKUP(C15,$AC$5:$AE$234,3,FALSE),"")
A16: 7 | D16: =IF(ISTEXT(C16),VLOOKUP(C16,$AC$5:$AE$234,2,FALSE),"") | H16: =IF(ISNUMBER(E16),IF(ROUNDDOWN(D16/E16,0)<1,NotaDeVenta[[#This Row],[Ancho Tela]]/NotaDeVenta[[#This Row],[Ancho]],ROUND(NotaDeVenta[[#This Row],[Ancho Tela]]/NotaDeVenta[[#This Row],[Ancho]],0)),"") | I16: =IF(ISNUMBER(H16),G16/H16,"") | J16: =IF(ISNUMBER(G16),IF(OR(B16="Textil Backlight",B16="Caja + Backlight"),E16*F16*G16,F16*I16),0) -> 0 | K16: =IF(ISTEXT(C16),VLOOKUP(C16,$AC$5:$AE$234,3,FALSE),"")
A17: 8 | D17: =IF(ISTEXT(C17),VLOOKUP(C17,$AC$5:$AE$234,2,FALSE),"") | H17: =IF(ISNUMBER(E17),IF(ROUNDDOWN(D17/E17,0)<1,NotaDeVenta[[#This Row],[Ancho Tela]]/NotaDeVenta[[#This Row],[Ancho]],ROUND(NotaDeVenta[[#This Row],[Ancho Tela]]/NotaDeVenta[[#This Row],[Ancho]],0)),"") | I17: =IF(ISNUMBER(H17),G17/H17,"") | J17: =IF(ISNUMBER(G17),IF(OR(B17="Textil Backlight",B17="Caja + Backlight"),E17*F17*G17,F17*I17),0) -> 0 | K17: =IF(ISTEXT(C17),VLOOKUP(C17,$AC$5:$AE$234,3,FALSE),"")
A18: 9 | D18: =IF(ISTEXT(C18),VLOOKUP(C18,$AC$5:$AE$234,2,FALSE),"") | H18: =IF(ISNUMBER(E18),IF(ROUNDDOWN(D18/E18,0)<1,NotaDeVenta[[#This Row],[Ancho Tela]]/NotaDeVenta[[#This Row],[Ancho]],ROUND(NotaDeVenta[[#This Row],[Ancho Tela]]/NotaDeVenta[[#This Row],[Ancho]],0)),"") | I18: =IF(ISNUMBER(H18),G18/H18,"") | J18: =IF(ISNUMBER(G18),IF(OR(B18="Textil Backlight",B18="Caja + Backlight"),E18*F18*G18,F18*I18),0) -> 0 | K18: =IF(ISTEXT(C18),VLOOKUP(C18,$AC$5:$AE$234,3,FALSE),"")
A19: 10 | D19: =IF(ISTEXT(C19),VLOOKUP(C19,$AC$5:$AE$234,2,FALSE),"") | H19: =IF(ISNUMBER(E19),IF(ROUNDDOWN(D19/E19,0)<1,NotaDeVenta[[#This Row],[Ancho Tela]]/NotaDeVenta[[#This Row],[Ancho]],ROUND(NotaDeVenta[[#This Row],[Ancho Tela]]/NotaDeVenta[[#This Row],[Ancho]],0)),"") | I19: =IF(ISNUMBER(H19),G19/H19,"") | J19: =IF(ISNUMBER(G19),IF(OR(B19="Textil Backlight",B19="Caja + Backlight"),E19*F19*G19,F19*I19),0) -> 0 | K19: =IF(ISTEXT(C19),VLOOKUP(C19,$AC$5:$AE$234,3,FALSE),"")
A20: 11 | D20: =IF(ISTEXT(C20),VLOOKUP(C20,$AC$5:$AE$234,2,FALSE),"") | H20: =IF(ISNUMBER(E20),IF(ROUNDDOWN(D20/E20,0)<1,NotaDeVenta[[#This Row],[Ancho Tela]]/NotaDeVenta[[#This Row],[Ancho]],ROUND(NotaDeVenta[[#This Row],[Ancho Tela]]/NotaDeVenta[[#This Row],[Ancho]],0)),"") | I20: =IF(ISNUMBER(H20),G20/H20,"") | J20: =IF(ISNUMBER(G20),IF(OR(B20="Textil Backlight",B20="Caja + Backlight"),E20*F20*G20,F20*I20),0) -> 0 | K20: =IF(ISTEXT(C20),VLOOKUP(C20,$AC$5:$AE$234,3,FALSE),"")
A21: 12 | D21: =IF(ISTEXT(C21),VLOOKUP(C21,$AC$5:$AE$234,2,FALSE),"") | H21: =IF(ISNUMBER(E21),IF(ROUNDDOWN(D21/E21,0)<1,NotaDeVenta[[#This Row],[Ancho Tela]]/NotaDeVenta[[#This Row],[Ancho]],ROUND(NotaDeVenta[[#This Row],[Ancho Tela]]/NotaDeVenta[[#This Row],[Ancho]],0)),"") | I21: =IF(ISNUMBER(H21),G21/H21,"") | J21: =IF(ISNUMBER(G21),IF(OR(B21="Textil Backlight",B21="Caja + Backlight"),E21*F21*G21,F21*I21),0) -> 0 | K21: =IF(ISTEXT(C21),VLOOKUP(C21,$AC$5:$AE$234,3,FALSE),"")
A22: 13 | D22: =IF(ISTEXT(C22),VLOOKUP(C22,$AC$5:$AE$234,2,FALSE),"") | H22: =IF(ISNUMBER(E22),IF(ROUNDDOWN(D22/E22,0)<1,NotaDeVenta[[#This Row],[Ancho Tela]]/NotaDeVenta[[#This Row],[Ancho]],ROUND(NotaDeVenta[[#This Row],[Ancho Tela]]/NotaDeVenta[[#This Row],[Ancho]],0)),"") | I22: =IF(ISNUMBER(H22),G22/H22,"") | J22: =IF(ISNUMBER(G22),IF(OR(B22="Textil Backlight",B22="Caja + Backlight"),E22*F22*G22,F22*I22),0) -> 0 | K22: =IF(ISTEXT(C22),VLOOKUP(C22,$AC$5:$AE$234,3,FALSE),"")
... A102: 93 | D102: =IF(ISTEXT(C102),VLOOKUP(C102,$AC$5:$AE$234,2,FALSE),"") | H102: =IF(ISNUMBER(E102),IF(ROUNDDOWN(D102/E102,0)<1,NotaDeVenta[[#This Row],[Ancho Tela]]/NotaDeVenta[[#This Row],[Ancho]],ROUND(NotaDeVenta[[#This Row],[Ancho Tela]]/NotaDeVenta[[#This Row],[Ancho]],0)),"") | I102: =IF(ISNUMBER(H102),G102/H102,"") | J102: =IF(ISNUMBER(G102),IF(OR(B102="Textil Backlight",B102="Caja + Backlight"),E102*F102*G102,F102*I102),0) -> 0 | K102: =IF(ISTEXT(C102),VLOOKUP(C102,$AC$5:$AE$234,3,FALSE),"")
A103: 94 | D103: =IF(ISTEXT(C103),VLOOKUP(C103,$AC$5:$AE$234,2,FALSE),"") | H103: =IF(ISNUMBER(E103),IF(ROUNDDOWN(D103/E103,0)<1,NotaDeVenta[[#This Row],[Ancho Tela]]/NotaDeVenta[[#This Row],[Ancho]],ROUND(NotaDeVenta[[#This Row],[Ancho Tela]]/NotaDeVenta[[#This Row],[Ancho]],0)),"") | I103: =IF(ISNUMBER(H103),G103/H103,"") | J103: =IF(ISNUMBER(G103),IF(OR(B103="Textil Backlight",B103="Caja + Backlight"),E103*F103*G103,F103*I103),0) -> 0 | K103: =IF(ISTEXT(C103),VLOOKUP(C103,$AC$5:$AE$234,3,FALSE),"") | Z103: base suelo plástico | AC103: Blackout | AD103: 1.48 | AE103: 12000 | AJ103: base suelo plástico | AK103: 25000 | AQ103: Base suelo metal más accesorio para rellenar
A104: 95 | D104: =IF(ISTEXT(C104),VLOOKUP(C104,$AC$5:$AE$234,2,FALSE),"") | H104: =IF(ISNUMBER(E104),IF(ROUNDDOWN(D104/E104,0)<1,NotaDeVenta[[#This Row],[Ancho Tela]]/NotaDeVenta[[#This Row],[Ancho]],ROUND(NotaDeVenta[[#This Row],[Ancho Tela]]/NotaDeVenta[[#This Row],[Ancho]],0)),"") | I104: =IF(ISNUMBER(H104),G104/H104,"") | J104: =IF(ISNUMBER(G104),IF(OR(B104="Textil Backlight",B104="Caja + Backlight"),E104*F104*G104,F104*I104),0) -> 0 | K104: =IF(ISTEXT(C104),VLOOKUP(C104,$AC$5:$AE$234,3,FALSE),"") | Z104: Camino de mesa | AC104: Canvas tarpaulin | AD104: 1.48 | AE104: 11000 | AJ104: Camino de mesa | AK104: 5000 | AQ104: Base suelo plástico para rellenar
A105: 96 | D105: =IF(ISTEXT(C105),VLOOKUP(C105,$AC$5:$AE$234,2,FALSE),"") | H105: =IF(ISNUMBER(E105),IF(ROUNDDOWN(D105/E105,0)<1,NotaDeVenta[[#This Row],[Ancho Tela]]/NotaDeVenta[[#This Row],[Ancho]],ROUND(NotaDeVenta[[#This Row],[Ancho Tela]]/NotaDeVenta[[#This Row],[Ancho]],0)),"") | I105: =IF(ISNUMBER(H105),G105/H105,"") | J105: =IF(ISNUMBER(G105),IF(OR(B105="Textil Backlight",B105="Caja + Backlight"),E105*F105*G105,F105*I105),0) -> 0 | K105: =IF(ISTEXT(C105),VLOOKUP(C105,$AC$5:$AE$234,3,FALSE),"") | Z105: cubre sensor | AC105: Crea sábana algodón | AD105: 1.48 | AE105: 11000 | AJ105: cubre sensor | AK105: 3500 | AQ105: Bolso de transporte con ruedas 1 estructura panel araña
A106: 97 | D106: =IF(ISTEXT(C106),VLOOKUP(C106,$AC$5:$AE$234,2,FALSE),"") | H106: =IF(ISNUMBER(E106),IF(ROUNDDOWN(D106/E106,0)<1,NotaDeVenta[[#This Row],[Ancho Tela]]/NotaDeVenta[[#This Row],[Ancho]],ROUND(NotaDeVenta[[#This Row],[Ancho Tela]]/NotaDeVenta[[#This Row],[Ancho]],0)),"") | I106: =IF(ISNUMBER(H106),G106/H106,"") | J106: =IF(ISNUMBER(G106),IF(OR(B106="Textil Backlight",B106="Caja + Backlight"),E106*F106*G106,F106*I106),0) -> 0 | K106: =IF(ISTEXT(C106),VLOOKUP(C106,$AC$5:$AE$234,3,FALSE),"") | Z106: estaca | AC106: Crea sábana poliester | AD106: 1.38 | AE106: 10000 | AJ106: estaca | AK106: 10000 | AQ106: Bolso de transporte con ruedas 2 estructuras panel araña
A107: 98 | D107: =IF(ISTEXT(C107),VLOOKUP(C107,$AC$5:$AE$234,2,FALSE),"") | H107: =IF(ISNUMBER(E107),IF(ROUNDDOWN(D107/E107,0)<1,NotaDeVenta[[#This Row],[Ancho Tela]]/NotaDeVenta[[#This Row],[Ancho]],ROUND(NotaDeVenta[[#This Row],[Ancho Tela]]/NotaDeVenta[[#This Row],[Ancho]],0)),"") | I107: =IF(ISNUMBER(H107),G107/H107,"") | J107: =IF(ISNUMBER(G107),IF(OR(B107="Textil Backlight",B107="Caja + Backlight"),E107*F107*G107,F107*I107),0) -> 0 | K107: =IF(ISTEXT(C107),VLOOKUP(C107,$AC$5:$AE$234,3,FALSE),"") | Z107: estampado textil sin terminaciones | AC107: Cuerina | AD107: 1.38 | AE107: 12000 | AJ107: estampado textil sin terminaciones | AK107: 2000 | AQ107: Cosmetiquero 20x30 cms 1 cara
A108: 99 | D108: =IF(ISTEXT(C108),VLOOKUP(C108,$AC$5:$AE$234,2,FALSE),"") | H108: =IF(ISNUMBER(E108),IF(ROUNDDOWN(D108/E108,0)<1,NotaDeVenta[[#This Row],[Ancho Tela]]/NotaDeVenta[[#This Row],[Ancho]],ROUND(NotaDeVenta[[#This Row],[Ancho Tela]]/NotaDeVenta[[#This Row],[Ancho]],0)),"") | I108: =IF(ISNUMBER(H108),G108/H108,"") | J108: =IF(ISNUMBER(G108),IF(OR(B108="Textil Backlight",B108="Caja + Backlight"),E108*F108*G108,F108*I108),0) -> 0 | K108: =IF(ISTEXT(C108),VLOOKUP(C108,$AC$5:$AE$234,3,FALSE),"")
A109: 100 | D109: =IF(ISTEXT(C109),VLOOKUP(C109,$AC$5:$AE$234,2,FALSE),"") | H109: =IF(ISNUMBER(E109),IF(ROUNDDOWN(D109/E109,0)<1,NotaDeVenta[[#This Row],[Ancho Tela]]/NotaDeVenta[[#This Row],[Ancho]],ROUND(NotaDeVenta[[#This Row],[Ancho Tela]]/NotaDeVenta[[#This Row],[Ancho]],0)),"") | I109: =IF(ISNUMBER(H109),G109/H109,"") | J109: =IF(ISNUMBER(G109),IF(OR(B109="Textil Backlight",B109="Caja + Backlight"),E109*F109*G109,F109*I109),0) -> 0 | K109: =IF(ISTEXT(C109),VLOOKUP(C109,$AC$5:$AE$234,3,FALSE),"")
A110: 101 | D110: =IF(ISTEXT(C110),VLOOKUP(C110,$AC$5:$AE$234,2,FALSE),"") | H110: =IF(ISNUMBER(E110),IF(ROUNDDOWN(D110/E110,0)<1,NotaDeVenta[[#This Row],[Ancho Tela]]/NotaDeVenta[[#This Row],[Ancho]],ROUND(NotaDeVenta[[#This Row],[Ancho Tela]]/NotaDeVenta[[#This Row],[Ancho]],0)),"") | I110: =IF(ISNUMBER(H110),G110/H110,"") | J110: =IF(ISNUMBER(G110),IF(OR(B110="Textil Backlight",B110="Caja + Backlight"),E110*F110*G110,F110*I110),0) -> 0 | K110: =IF(ISTEXT(C110),VLOOKUP(C110,$AC$5:$AE$234,3,FALSE),"") | Z110: Estuches | AC110: Felpa gruesa | AD110: 1.38 | AE110: 12000 | AJ110: Estuches | AK110: 3000 | AQ110: Cubre alarma
G111: =IF(ISNUMBER(G10),SUM(G10:G110),"") | J111: =IF(ISNUMBER(J10),SUM(J10:J110),"") -> 0 | Z111: fleje arriba y abajo | AC111: Franela | AD111: 1.48 | AE111: 12000 | AJ111: fleje arriba y abajo | AK111: 10500 | AQ111: Estaca
B112: Nombre del Trabajo
B113: Descripcion del producto | Z113: Funda Almohada | AC113: Gabardina antiflu | AD113: 1.48 | AE113: 12000 | AJ113: Funda Almohada | AK113: 6000 | AQ113: Estuche 18x23 cms 1 cara
B114: observaciones produccion | Z114: Funda Cojín | AC114: Gasa | AD114: 1.46 | AE114: 12000 | AJ114: Funda Cojín | AK114: 4000 | AQ114: Estuche 18x23 cms tiro y retiro
Z115: lienzo simple con bolsillo SIN estructuras | AC115: Gasa rustica | AD115: 1.38 | AE115: 12800 | AJ115: lienzo simple con bolsillo SIN estructuras | AK115: 7000 | AQ115: Estuche lapicero 5x20 cms
B116: Producto | C116: Valor impresion total | D116: Estructura | E116: Terminaciones | F116: Otros x1 | G116: Valor unitario prod | H116: Total neto | I116: Valor Impresión Unit | Z116: lienzo simple con bolsillos, estructutras, accesorios para colgar | AC116: Hole | AD116: 1.58 | AE116: 8000 | AJ116: lienzo simple con bolsillos, estructutras, accesorios para colgar | AK116: 10000 | AQ116: Estuches lentes 22x12 cms tiro y retiro
A117: 1 | B117: =B10 -> 0 | C117: =IF(ISNUMBER(K10),J10*K10,0) -> 0 | D117: =IF(ISNUMBER(C117),VLOOKUP(B117,Productos!$A$2:$G$111,7,FALSE),0) -> #N/A | E117: =IF(B117<>"",VLOOKUP(B117,Productos!$A$2:$G$116,6,FALSE),0) -> #N/A | G117: =IF(B117="Caja + Backlight",'NV CAJAS (BL)'!L27+TablaValoresProducto[[#This Row],[Valor Impresión Unit]]+TablaValoresProducto[[#This Row],[Estructura]]+TablaValoresProducto[[#This Row],[Terminaciones]]+TablaValoresProducto[[#This Row],[Otros x1]],IF(ISNUMBER(TablaValoresProducto[[#This Row],[Valor impresion total]]),TablaValoresProducto[[#This Row],[Valor impresion total]]/G10+TablaValoresProducto[[#This Row],[Estructura]]+TablaValoresProducto[[#This Row],[Terminaciones]]+TablaValoresProducto[[#This Row],[Otros x1]],0)) -> #DIV/0! | H117: =IF(ISNUMBER(G117),G117*G10,0) -> 0 | I117: =TablaValoresProducto[[#This Row],[Valor impresion total]]/G10 -> #DIV/0! | Z117: lienzo tiro y retiro con bolsillos SIN estructuras | AC117: Jersey | AD117: 1.48 | AE117: 10500 | AJ117: lienzo tiro y retiro con bolsillos SIN estructuras | AK117: 15000 | AQ117: Forro textil soporte muro 2,3x2,3 mts tiro y retiro
A118: 2 | B118: =B11 -> 0 | C118: =IF(ISNUMBER(K11),J11*K11,0) -> 0 | D118: =IF(ISNUMBER(C118),VLOOKUP(B118,Productos!$A$2:$G$111,7,FALSE),0) -> #N/A | E118: =IF(B118<>"",VLOOKUP(B118,Productos!$A$2:$G$116,6,FALSE),0) -> #N/A | G118: =IF(B118="Caja + Backlight",'NV CAJAS (BL)'!L28+TablaValoresProducto[[#This Row],[Valor Impresión Unit]]+TablaValoresProducto[[#This Row],[Estructura]]+TablaValoresProducto[[#This Row],[Terminaciones]]+TablaValoresProducto[[#This Row],[Otros x1]],IF(ISNUMBER(TablaValoresProducto[[#This Row],[Valor impresion total]]),TablaValoresProducto[[#This Row],[Valor impresion total]]/G11+TablaValoresProducto[[#This Row],[Estructura]]+TablaValoresProducto[[#This Row],[Terminaciones]]+TablaValoresProducto[[#This Row],[Otros x1]],0)) -> #DIV/0! | H118: =IF(ISNUMBER(G118),G118*G11,0) -> 0 | I118: =TablaValoresProducto[[#This Row],[Valor impresion total]]/G11 -> #DIV/0!
A119: 3 | B119: =B12 -> 0 | C119: =IF(ISNUMBER(K12),J12*K12,0) -> 0 | D119: =IF(ISNUMBER(C119),VLOOKUP(B119,Productos!$A$2:$G$111,7,FALSE),0) -> #N/A | E119: =IF(B119<>"",VLOOKUP(B119,Productos!$A$2:$G$116,6,FALSE),0) -> #N/A | G119: =IF(B119="Caja + Backlight",'NV CAJAS (BL)'!L29+TablaValoresProducto[[#This Row],[Valor Impresión Unit]]+TablaValoresProducto[[#This Row],[Estructura]]+TablaValoresProducto[[#This Row],[Terminaciones]]+TablaValoresProducto[[#This Row],[Otros x1]],IF(ISNUMBER(TablaValoresProducto[[#This Row],[Valor impresion total]]),TablaValoresProducto[[#This Row],[Valor impresion total]]/G12+TablaValoresProducto[[#This Row],[Estructura]]+TablaValoresProducto[[#This Row],[Terminaciones]]+TablaValoresProducto[[#This Row],[Otros x1]],0)) -> #DIV/0! | H119: =IF(ISNUMBER(G119),G119*G12,0) -> 0 | I119: =TablaValoresProducto[[#This Row],[Valor impresion total]]/G12 -> #DIV/0!
A120: 4 | B120: =B13 -> 0 | C120: =IF(ISNUMBER(K13),J13*K13,0) -> 0 | D120: =IF(ISNUMBER(C120),VLOOKUP(B120,Productos!$A$2:$G$111,7,FALSE),0) -> #N/A | E120: =IF(B120<>"",VLOOKUP(B120,Productos!$A$2:$G$116,6,FALSE),0) -> #N/A | G120: =IF(B120="Caja + Backlight",'NV CAJAS (BL)'!L30+TablaValoresProducto[[#This Row],[Valor Impresión Unit]]+TablaValoresProducto[[#This Row],[Estructura]]+TablaValoresProducto[[#This Row],[Terminaciones]]+TablaValoresProducto[[#This Row],[Otros x1]],IF(ISNUMBER(TablaValoresProducto[[#This Row],[Valor impresion total]]),TablaValoresProducto[[#This Row],[Valor impresion total]]/G13+TablaValoresProducto[[#This Row],[Estructura]]+TablaValoresProducto[[#This Row],[Terminaciones]]+TablaValoresProducto[[#This Row],[Otros x1]],0)) -> #DIV/0! | H120: =IF(ISNUMBER(G120),G120*G13,0) -> 0 | I120: =TablaValoresProducto[[#This Row],[Valor impresion total]]/G13 -> #DIV/0!
A121: 5 | B121: =B14 -> 0 | C121: =IF(ISNUMBER(K14),J14*K14,0) -> 0 | D121: =IF(ISNUMBER(C121),VLOOKUP(B121,Productos!$A$2:$G$111,7,FALSE),0) -> #N/A | E121: =IF(B121<>"",VLOOKUP(B121,Productos!$A$2:$G$116,6,FALSE),0) -> #N/A | G121: =IF(B121="Caja + Backlight",'NV CAJAS (BL)'!L31+TablaValoresProducto[[#This Row],[Valor Impresión Unit]]+TablaValoresProducto[[#This Row],[Estructura]]+TablaValoresProducto[[#This Row],[Terminaciones]]+TablaValoresProducto[[#This Row],[Otros x1]],IF(ISNUMBER(TablaValoresProducto[[#This Row],[Valor impresion total]]),TablaValoresProducto[[#This Row],[Valor impresion total]]/G14+TablaValoresProducto[[#This Row],[Estructura]]+TablaValoresProducto[[#This Row],[Terminaciones]]+TablaValoresProducto[[#This Row],[Otros x1]],0)) -> #DIV/0! | H121: =IF(ISNUMBER(G121),G121*G14,0) -> 0 | I121: =TablaValoresProducto[[#This Row],[Valor impresion total]]/G14 -> #DIV/0!
A122: 6 | B122: =B15 -> 0 | C122: =IF(ISNUMBER(K15),J15*K15,0) -> 0 | D122: =IF(ISNUMBER(C122),VLOOKUP(B122,Productos!$A$2:$G$111,7,FALSE),0) -> #N/A | E122: =IF(B122<>"",VLOOKUP(B122,Productos!$A$2:$G$116,6,FALSE),0) -> #N/A | G122: =IF(B122="Caja + Backlight",'NV CAJAS (BL)'!L32+TablaValoresProducto[[#This Row],[Valor Impresión Unit]]+TablaValoresProducto[[#This Row],[Estructura]]+TablaValoresProducto[[#This Row],[Terminaciones]]+TablaValoresProducto[[#This Row],[Otros x1]],IF(ISNUMBER(TablaValoresProducto[[#This Row],[Valor impresion total]]),TablaValoresProducto[[#This Row],[Valor impresion total]]/G15+TablaValoresProducto[[#This Row],[Estructura]]+TablaValoresProducto[[#This Row],[Terminaciones]]+TablaValoresProducto[[#This Row],[Otros x1]],0)) -> #DIV/0! | H122: =IF(ISNUMBER(G122),G122*G15,0) -> 0 | I122: =TablaValoresProducto[[#This Row],[Valor impresion total]]/G15 -> #DIV/0!
A123: 7 | B123: =B16 -> 0 | C123: =IF(ISNUMBER(K16),J16*K16,0) -> 0 | D123: =IF(ISNUMBER(C123),VLOOKUP(B123,Productos!$A$2:$G$111,7,FALSE),0) -> #N/A | E123: =IF(B123<>"",VLOOKUP(B123,Productos!$A$2:$G$116,6,FALSE),0) -> #N/A | G123: =IF(B123="Caja + Backlight",'NV CAJAS (BL)'!L33+TablaValoresProducto[[#This Row],[Valor Impresión Unit]]+TablaValoresProducto[[#This Row],[Estructura]]+TablaValoresProducto[[#This Row],[Terminaciones]]+TablaValoresProducto[[#This Row],[Otros x1]],IF(ISNUMBER(TablaValoresProducto[[#This Row],[Valor impresion total]]),TablaValoresProducto[[#This Row],[Valor impresion total]]/G16+TablaValoresProducto[[#This Row],[Estructura]]+TablaValoresProducto[[#This Row],[Terminaciones]]+TablaValoresProducto[[#This Row],[Otros x1]],0)) -> #DIV/0! | H123: =IF(ISNUMBER(G123),G123*G16,0) -> 0 | I123: =TablaValoresProducto[[#This Row],[Valor impresion total]]/G16 -> #DIV/0!
A124: 8 | B124: =B17 -> 0 | C124: =IF(ISNUMBER(K17),J17*K17,0) -> 0 | D124: =IF(ISNUMBER(C124),VLOOKUP(B124,Productos!$A$2:$G$111,7,FALSE),0) -> #N/A | E124: =IF(B124<>"",VLOOKUP(B124,Productos!$A$2:$G$116,6,FALSE),0) -> #N/A | G124: =IF(B124="Caja + Backlight",'NV CAJAS (BL)'!L34+TablaValoresProducto[[#This Row],[Valor Impresión Unit]]+TablaValoresProducto[[#This Row],[Estructura]]+TablaValoresProducto[[#This Row],[Terminaciones]]+TablaValoresProducto[[#This Row],[Otros x1]],IF(ISNUMBER(TablaValoresProducto[[#This Row],[Valor impresion total]]),TablaValoresProducto[[#This Row],[Valor impresion total]]/G17+TablaValoresProducto[[#This Row],[Estructura]]+TablaValoresProducto[[#This Row],[Terminaciones]]+TablaValoresProducto[[#This Row],[Otros x1]],0)) -> #DIV/0! | H124: =IF(ISNUMBER(G124),G124*G17,0) -> 0 | I124: =TablaValoresProducto[[#This Row],[Valor impresion total]]/G17 -> #DIV/0!
A125: 9 | B125: =B18 -> 0 | C125: =IF(ISNUMBER(K18),J18*K18,0) -> 0 | D125: =IF(ISNUMBER(C125),VLOOKUP(B125,Productos!$A$2:$G$111,7,FALSE),0) -> #N/A | E125: =IF(B125<>"",VLOOKUP(B125,Productos!$A$2:$G$116,6,FALSE),0) -> #N/A | G125: =IF(B125="Caja + Backlight",'NV CAJAS (BL)'!L35+TablaValoresProducto[[#This Row],[Valor Impresión Unit]]+TablaValoresProducto[[#This Row],[Estructura]]+TablaValoresProducto[[#This Row],[Terminaciones]]+TablaValoresProducto[[#This Row],[Otros x1]],IF(ISNUMBER(TablaValoresProducto[[#This Row],[Valor impresion total]]),TablaValoresProducto[[#This Row],[Valor impresion total]]/G18+TablaValoresProducto[[#This Row],[Estructura]]+TablaValoresProducto[[#This Row],[Terminaciones]]+TablaValoresProducto[[#This Row],[Otros x1]],0)) -> #DIV/0! | H125: =IF(ISNUMBER(G125),G125*G18,0) -> 0 | I125: =TablaValoresProducto[[#This Row],[Valor impresion total]]/G18 -> #DIV/0!
A126: 10 | B126: =B19 -> 0 | C126: =IF(ISNUMBER(K19),J19*K19,0) -> 0 | D126: =IF(ISNUMBER(C126),VLOOKUP(B126,Productos!$A$2:$G$111,7,FALSE),0) -> #N/A | E126: =IF(B126<>"",VLOOKUP(B126,Productos!$A$2:$G$116,6,FALSE),0) -> #N/A | G126: =IF(B126="Caja + Backlight",'NV CAJAS (BL)'!L36+TablaValoresProducto[[#This Row],[Valor Impresión Unit]]+TablaValoresProducto[[#This Row],[Estructura]]+TablaValoresProducto[[#This Row],[Terminaciones]]+TablaValoresProducto[[#This Row],[Otros x1]],IF(ISNUMBER(TablaValoresProducto[[#This Row],[Valor impresion total]]),TablaValoresProducto[[#This Row],[Valor impresion total]]/G19+TablaValoresProducto[[#This Row],[Estructura]]+TablaValoresProducto[[#This Row],[Terminaciones]]+TablaValoresProducto[[#This Row],[Otros x1]],0)) -> #DIV/0! | H126: =IF(ISNUMBER(G126),G126*G19,0) -> 0 | I126: =TablaValoresProducto[[#This Row],[Valor impresion total]]/G19 -> #DIV/0!
A127: 11 | B127: =B20 -> 0 | C127: =IF(ISNUMBER(K20),J20*K20,0) -> 0 | D127: =IF(ISNUMBER(C127),VLOOKUP(B127,Productos!$A$2:$G$111,7,FALSE),0) -> #N/A | E127: =IF(B127<>"",VLOOKUP(B127,Productos!$A$2:$G$116,6,FALSE),0) -> #N/A | G127: =IF(B127="Caja + Backlight",'NV CAJAS (BL)'!L37+TablaValoresProducto[[#This Row],[Valor Impresión Unit]]+TablaValoresProducto[[#This Row],[Estructura]]+TablaValoresProducto[[#This Row],[Terminaciones]]+TablaValoresProducto[[#This Row],[Otros x1]],IF(ISNUMBER(TablaValoresProducto[[#This Row],[Valor impresion total]]),TablaValoresProducto[[#This Row],[Valor impresion total]]/G20+TablaValoresProducto[[#This Row],[Estructura]]+TablaValoresProducto[[#This Row],[Terminaciones]]+TablaValoresProducto[[#This Row],[Otros x1]],0)) -> #DIV/0! | H127: =IF(ISNUMBER(G127),G127*G20,0) -> 0 | I127: =TablaValoresProducto[[#This Row],[Valor impresion total]]/G20 -> #DIV/0!
A128: 12 | B128: =B21 -> 0 | C128: =IF(ISNUMBER(K21),J21*K21,0) -> 0 | D128: =IF(ISNUMBER(C128),VLOOKUP(B128,Productos!$A$2:$G$111,7,FALSE),0) -> #N/A | E128: =IF(B128<>"",VLOOKUP(B128,Productos!$A$2:$G$116,6,FALSE),0) -> #N/A | G128: =IF(B128="Caja + Backlight",'NV CAJAS (BL)'!L38+TablaValoresProducto[[#This Row],[Valor Impresión Unit]]+TablaValoresProducto[[#This Row],[Estructura]]+TablaValoresProducto[[#This Row],[Terminaciones]]+TablaValoresProducto[[#This Row],[Otros x1]],IF(ISNUMBER(TablaValoresProducto[[#This Row],[Valor impresion total]]),TablaValoresProducto[[#This Row],[Valor impresion total]]/G21+TablaValoresProducto[[#This Row],[Estructura]]+TablaValoresProducto[[#This Row],[Terminaciones]]+TablaValoresProducto[[#This Row],[Otros x1]],0)) -> #DIV/0! | H128: =IF(ISNUMBER(G128),G128*G21,0) -> 0 | I128: =TablaValoresProducto[[#This Row],[Valor impresion total]]/G21 -> #DIV/0!
A129: 13 | B129: =B22 -> 0 | C129: =IF(ISNUMBER(K22),J22*K22,0) -> 0 | D129: =IF(ISNUMBER(C129),VLOOKUP(B129,Productos!$A$2:$G$111,7,FALSE),0) -> #N/A | E129: =IF(B129<>"",VLOOKUP(B129,Productos!$A$2:$G$116,6,FALSE),0) -> #N/A | G129: =IF(B129="Caja + Backlight",'NV CAJAS (BL)'!L39+TablaValoresProducto[[#This Row],[Valor Impresión Unit]]+TablaValoresProducto[[#This Row],[Estructura]]+TablaValoresProducto[[#This Row],[Terminaciones]]+TablaValoresProducto[[#This Row],[Otros x1]],IF(ISNUMBER(TablaValoresProducto[[#This Row],[Valor impresion total]]),TablaValoresProducto[[#This Row],[Valor impresion total]]/G22+TablaValoresProducto[[#This Row],[Estructura]]+TablaValoresProducto[[#This Row],[Terminaciones]]+TablaValoresProducto[[#This Row],[Otros x1]],0)) -> #DIV/0! | H129: =IF(ISNUMBER(G129),G129*G22,0) -> 0 | I129: =TablaValoresProducto[[#This Row],[Valor impresion total]]/G22 -> #DIV/0!
... A209: 93 | B209: =B102 -> 0 | C209: =IF(ISNUMBER(K102),J102*K102,0) -> 0 | D209: =IF(ISNUMBER(C209),VLOOKUP(B209,Productos!$A$2:$G$111,7,FALSE),0) -> #N/A | E209: =IF(B209<>"",VLOOKUP(B209,Productos!$A$2:$G$116,6,FALSE),0) -> #N/A | G209: =IF(B209="Caja + Backlight",'NV CAJAS (BL)'!L119+TablaValoresProducto[[#This Row],[Valor Impresión Unit]]+TablaValoresProducto[[#This Row],[Estructura]]+TablaValoresProducto[[#This Row],[Terminaciones]]+TablaValoresProducto[[#This Row],[Otros x1]],IF(ISNUMBER(TablaValoresProducto[[#This Row],[Valor impresion total]]),TablaValoresProducto[[#This Row],[Valor impresion total]]/G102+TablaValoresProducto[[#This Row],[Estructura]]+TablaValoresProducto[[#This Row],[Terminaciones]]+TablaValoresProducto[[#This Row],[Otros x1]],0)) -> #DIV/0! | H209: =IF(ISNUMBER(G209),G209*G102,0) -> 0 | I209: =TablaValoresProducto[[#This Row],[Valor impresion total]]/G102 -> #DIV/0!
A210: 94 | B210: =B103 -> 0 | C210: =IF(ISNUMBER(K103),J103*K103,0) -> 0 | D210: =IF(ISNUMBER(C210),VLOOKUP(B210,Productos!$A$2:$G$111,7,FALSE),0) -> #N/A | E210: =IF(B210<>"",VLOOKUP(B210,Productos!$A$2:$G$116,6,FALSE),0) -> #N/A | F210: 0 | G210: =IF(B210="Caja + Backlight",'NV CAJAS (BL)'!L120+TablaValoresProducto[[#This Row],[Valor Impresión Unit]]+TablaValoresProducto[[#This Row],[Estructura]]+TablaValoresProducto[[#This Row],[Terminaciones]]+TablaValoresProducto[[#This Row],[Otros x1]],IF(ISNUMBER(TablaValoresProducto[[#This Row],[Valor impresion total]]),TablaValoresProducto[[#This Row],[Valor impresion total]]/G103+TablaValoresProducto[[#This Row],[Estructura]]+TablaValoresProducto[[#This Row],[Terminaciones]]+TablaValoresProducto[[#This Row],[Otros x1]],0)) -> #DIV/0! | H210: =IF(ISNUMBER(G210),G210*G103,0) -> 0 | I210: =TablaValoresProducto[[#This Row],[Valor impresion total]]/G103 -> #DIV/0! | Z210: lienzo tiro y retiro con bolsillos , estructuras y accesorios para colgar | AC210: Lanilla | AD210: 1.4 | AE210: 11000 | AJ210: lienzo tiro y retiro con bolsillos , estructuras y accesorios para colgar | AK210: 18000 | AQ210: Funda Almohada 50x70 cms 1 cara , reverso con cruce
A211: 95 | B211: =B104 -> 0 | C211: =IF(ISNUMBER(K104),J104*K104,0) -> 0 | D211: =IF(ISNUMBER(C211),VLOOKUP(B211,Productos!$A$2:$G$111,7,FALSE),0) -> #N/A | E211: =IF(B211<>"",VLOOKUP(B211,Productos!$A$2:$G$116,6,FALSE),0) -> #N/A | F211: 0 | G211: =IF(B211="Caja + Backlight",'NV CAJAS (BL)'!L121+TablaValoresProducto[[#This Row],[Valor Impresión Unit]]+TablaValoresProducto[[#This Row],[Estructura]]+TablaValoresProducto[[#This Row],[Terminaciones]]+TablaValoresProducto[[#This Row],[Otros x1]],IF(ISNUMBER(TablaValoresProducto[[#This Row],[Valor impresion total]]),TablaValoresProducto[[#This Row],[Valor impresion total]]/G104+TablaValoresProducto[[#This Row],[Estructura]]+TablaValoresProducto[[#This Row],[Terminaciones]]+TablaValoresProducto[[#This Row],[Otros x1]],0)) -> #DIV/0! | H211: =IF(ISNUMBER(G211),G211*G104,0) -> 0 | I211: =TablaValoresProducto[[#This Row],[Valor impresion total]]/G104 -> #DIV/0! | Z211: mantel basta perimetral 150x150 | AC211: Lino 100% | AD211: 1.38 | AE211: 15000 | AJ211: mantel basta perimetral 150x150 | AK211: 4000 | AQ211: Funda Almohada 50x70 cms tiro y retiro cierre lateral
A212: 96 | B212: =B105 -> 0 | C212: =IF(ISNUMBER(K105),J105*K105,0) -> 0 | D212: =IF(ISNUMBER(C212),VLOOKUP(B212,Productos!$A$2:$G$111,7,FALSE),0) -> #N/A | E212: =IF(B212<>"",VLOOKUP(B212,Productos!$A$2:$G$116,6,FALSE),0) -> #N/A | F212: 0 | G212: =IF(B212="Caja + Backlight",'NV CAJAS (BL)'!L122+TablaValoresProducto[[#This Row],[Valor Impresión Unit]]+TablaValoresProducto[[#This Row],[Estructura]]+TablaValoresProducto[[#This Row],[Terminaciones]]+TablaValoresProducto[[#This Row],[Otros x1]],IF(ISNUMBER(TablaValoresProducto[[#This Row],[Valor impresion total]]),TablaValoresProducto[[#This Row],[Valor impresion total]]/G105+TablaValoresProducto[[#This Row],[Estructura]]+TablaValoresProducto[[#This Row],[Terminaciones]]+TablaValoresProducto[[#This Row],[Otros x1]],0)) -> #DIV/0! | H212: =IF(ISNUMBER(G212),G212*G105,0) -> 0 | I212: =TablaValoresProducto[[#This Row],[Valor impresion total]]/G105 -> #DIV/0! | Z212: mantel con calce y basta 210x300 | AC212: Lino arena | AD212: 1.58 | AE212: 12000 | AJ212: mantel con calce y basta 210x300 | AK212: 7000 | AN212: valor mínimo 1 m2 | AO212: 0 | AQ212: Funda Almohada 50x90 cms 1 cara , reverso con cruce
A213: 97 | B213: =B106 -> 0 | C213: =IF(ISNUMBER(K106),J106*K106,0) -> 0 | D213: =IF(ISNUMBER(C213),VLOOKUP(B213,Productos!$A$2:$G$111,7,FALSE),0) -> #N/A | E213: =IF(B213<>"",VLOOKUP(B213,Productos!$A$2:$G$116,6,FALSE),0) -> #N/A | F213: 0 | G213: =IF(B213="Caja + Backlight",'NV CAJAS (BL)'!L123+TablaValoresProducto[[#This Row],[Valor Impresión Unit]]+TablaValoresProducto[[#This Row],[Estructura]]+TablaValoresProducto[[#This Row],[Terminaciones]]+TablaValoresProducto[[#This Row],[Otros x1]],IF(ISNUMBER(TablaValoresProducto[[#This Row],[Valor impresion total]]),TablaValoresProducto[[#This Row],[Valor impresion total]]/G106+TablaValoresProducto[[#This Row],[Estructura]]+TablaValoresProducto[[#This Row],[Terminaciones]]+TablaValoresProducto[[#This Row],[Otros x1]],0)) -> #DIV/0! | H213: =IF(ISNUMBER(G213),G213*G106,0) -> 0 | I213: =TablaValoresProducto[[#This Row],[Valor impresion total]]/G106 -> #DIV/0! | Z213: muro textil tubo aluminio 2.3x2.3 | AC213: Lona algodón blanca | AD213: 1.44 | AE213: 13000 | AJ213: muro textil tubo aluminio 2.3x2.3 | AK213: 96000 | AN213: productor 1<10 M2 | AO213: 0 | AQ213: Funda Almohada 50x90 cms tiro y retiro cierre lateral
A214: 98 | B214: =B107 -> 0 | C214: =IF(ISNUMBER(K107),J107*K107,0) -> 0 | D214: =IF(ISNUMBER(C214),VLOOKUP(B214,Productos!$A$2:$G$111,7,FALSE),0) -> #N/A | E214: =IF(B214<>"",VLOOKUP(B214,Productos!$A$2:$G$116,6,FALSE),0) -> #N/A | F214: 0 | G214: =IF(B214="Caja + Backlight",'NV CAJAS (BL)'!L124+TablaValoresProducto[[#This Row],[Valor Impresión Unit]]+TablaValoresProducto[[#This Row],[Estructura]]+TablaValoresProducto[[#This Row],[Terminaciones]]+TablaValoresProducto[[#This Row],[Otros x1]],IF(ISNUMBER(TablaValoresProducto[[#This Row],[Valor impresion total]]),TablaValoresProducto[[#This Row],[Valor impresion total]]/G107+TablaValoresProducto[[#This Row],[Estructura]]+TablaValoresProducto[[#This Row],[Terminaciones]]+TablaValoresProducto[[#This Row],[Otros x1]],0)) -> #DIV/0! | H214: =IF(ISNUMBER(G214),G214*G107,0) -> 0 | I214: =TablaValoresProducto[[#This Row],[Valor impresion total]]/G107 -> #DIV/0! | Z214: Panel pop 1c | AC214: Lona cruda algodón | AD214: 1.44 | AE214: 12500 | AJ214: Panel pop 1c | AK214: 85000 | AN214: productor 10<20m2 | AO214: 0.05 | AQ214: Funda Cojín 40x40 cms 1 cara, cierre abajo
A215: 99 | B215: =B108 -> 0 | C215: =IF(ISNUMBER(K108),J108*K108,0) -> 0 | D215: =IF(ISNUMBER(C215),VLOOKUP(B215,Productos!$A$2:$G$111,7,FALSE),0) -> #N/A | E215: =IF(B215<>"",VLOOKUP(B215,Productos!$A$2:$G$116,6,FALSE),0) -> #N/A | F215: 0 | G215: =IF(B215="Caja + Backlight",'NV CAJAS (BL)'!L125+TablaValoresProducto[[#This Row],[Valor Impresión Unit]]+TablaValoresProducto[[#This Row],[Estructura]]+TablaValoresProducto[[#This Row],[Terminaciones]]+TablaValoresProducto[[#This Row],[Otros x1]],IF(ISNUMBER(TablaValoresProducto[[#This Row],[Valor impresion total]]),TablaValoresProducto[[#This Row],[Valor impresion total]]/G108+TablaValoresProducto[[#This Row],[Estructura]]+TablaValoresProducto[[#This Row],[Terminaciones]]+TablaValoresProducto[[#This Row],[Otros x1]],0)) -> #DIV/0! | H215: =IF(ISNUMBER(G215),G215*G108,0) -> 0 | I215: =TablaValoresProducto[[#This Row],[Valor impresion total]]/G108 -> #DIV/0! | Z215: Panel pop 2c | AC215: Lona impermeable | AD215: 1.48 | AE215: 12000 | AJ215: Panel pop 2c | AK215: 120000 | AN215: productor 21 <50m2 | AO215: 0.1 | AQ215: Funda Cojín 40x40 cms tiro y retiro, cierre abajo
A216: 100 | B216: =B110 -> 0 | C216: =IF(ISNUMBER(K110),J110*K110,0) -> 0 | D216: =IF(ISNUMBER(C216),VLOOKUP(B216,Productos!$A$2:$G$111,7,FALSE),0) -> #N/A | E216: =IF(B216<>"",VLOOKUP(B216,Productos!$A$2:$G$116,6,FALSE),0) -> #N/A | F216: 0 | G216: =IF(B216="Caja + Backlight",'NV CAJAS (BL)'!L126+TablaValoresProducto[[#This Row],[Valor Impresión Unit]]+TablaValoresProducto[[#This Row],[Estructura]]+TablaValoresProducto[[#This Row],[Terminaciones]]+TablaValoresProducto[[#This Row],[Otros x1]],IF(ISNUMBER(TablaValoresProducto[[#This Row],[Valor impresion total]]),TablaValoresProducto[[#This Row],[Valor impresion total]]/G109+TablaValoresProducto[[#This Row],[Estructura]]+TablaValoresProducto[[#This Row],[Terminaciones]]+TablaValoresProducto[[#This Row],[Otros x1]],0)) -> #DIV/0! | H216: =IF(ISNUMBER(G216),G216*G110,0) -> 0 | I216: =TablaValoresProducto[[#This Row],[Valor impresion total]]/G109 -> #DIV/0! | Z216: Panel pop 3c | AC216: Lona rústica | AD216: 1.44 | AE216: 12600 | AJ216: Panel pop 3c | AK216: 140000 | AN216: prouctor > 50 m2 | AO216: 0.2 | AQ216: Funda Cojín 50x50 cms 1 cara, cierre abajo
Z217: Panel pop 4c | AC217: Loneta cruda algodón | AD217: 1.48 | AE217: 12500 | AJ217: Panel pop 4c | AK217: 170000 | AO217: =IF(OR(B117="Textil Backlight",B117="Caja + Backlight"), IF(J111>50,SUM(H117:H216)*0.2, IF(J111>21,SUM(H117:H216)*0.1, IF(J111>10,SUM(H117:H216)*0.05,0))),0) -> 0 | AQ217: Funda Cojín 50x50 cms tiro y retiro, cierre abajo
Z218: Panel pop 5c | AC218: Lycra | AD218: 1.48 | AE218: 12300 | AJ218: Panel pop 5c | AK218: 205000 | AQ218: Lienzo con uniones con calce con basta
Z219: Panel pop 6c | AC219: Mesh mate con traspaso | AD219: 1.58 | AE219: 16320 | AJ219: Panel pop 6c | AK219: 245000 | AQ219: Lienzo con uniones con calce con ojetillos perimetrales
Z220: Pañuelos | AC220: Mesh mate con traspaso | AD220: 2.8 | AE220: 30000 | AJ220: Pañuelos | AK220: 8000 | AQ220: Lienzo con uniones con calce, bolsillos, fleje plástico arriba y abajo con hilos para colgar transparente
Z221: pecheras con bolsillo | AC221: Mirror | AD221: 1.58 | AE221: 9600 | AJ221: pecheras con bolsillo | AK221: 5000 | AQ221: Lienzo con uniones con calce, basta o bolsillo SIN estructuras
Z222: pecheras simples | AC222: Papel mural liso | AD222: 1.1 | AE222: 12000 | AJ222: pecheras simples | AK222: 4000 | AQ222: Lienzo con uniones con calce, bolsillos, madera exterior ambas caras arriba y abajo con cáncamos y cable para colgar
Z223: Pieceras con basta | AC223: Papel mural textura | AD223: 1.1 | AE223: 12000 | AJ223: Pieceras con basta | AK223: 8000 | AQ223: Lienzo con uniones con calce, bolsillos, tubo metálico arriba y pletina metálica abajo con cable y candados
Z224: Pieceras con forro | AC224: Polar | AD224: 1.38 | AE224: 11100 | AJ224: Pieceras con forro | AK224: 10000 | AQ224: Lienzo simple con basta o bolsillo SIN estructuras hasta 150cms de ancho
Z225: pletina fierro arriba ya abjo | AC225: Popelina anti agua | AD225: 1.48 | AE225: 11300 | AJ225: pletina fierro arriba ya abjo | AK225: 15000 | AQ225: Lienzo simple con bolsillos hasta 150 cms de ancho, fleje plástico arriba y abajo con hilos para colgar transparente
Z226: sin estructura | AC226: Popelina glossy 280 | AD226: 1.48 | AE226: 10800 | AJ226: sin estructura | AK226: 0 | AQ226: Lienzo simple con bolsillos hasta 150 cms de ancho, madera exterior ambas caras arriba y abajo con cáncamos y cable para colgar
Z227: textil panel araña | AC227: Popelina panel | AD227: 2.28 | AE227: 27400 | AJ227: textil panel araña | AK227: 10000 | AQ227: Lienzo simple con bolsillos hasta 150 cms de ancho, tubo metálico arriba y pletina metálica abajo con cable y candados
Z228: Totebag | AC228: Satin delgado | AD228: 1.48 | AE228: 11000 | AJ228: Totebag | AK228: 3000 | AQ228: Lienzo simple con ojetillos perimetrales reforzados cada 30 cms
Z229: tubo aluminio arriba y abajo | AC229: Satin grueso | AD229: 1.48 | AE229: 10000 | AJ229: tubo aluminio arriba y abajo | AK229: 13000 | AQ229: Lienzo simple con ojetillos perimetrales reforzados cada 50 cms
Z230: Velas banderas | AC230: Seda sintética | AD230: 1.48 | AE230: 12500 | AJ230: Velas banderas | AK230: 6000 | AQ230: Lienzo simple con ojetillos reforzados 4 esquinas
Y231: BACKLIGHT | Z231: caja frameless 12 doble | AC231: Stretch | AD231: 1.58 | AE231: 12000 | AQ231: Lienzo tiro y retiro con basta o bolsillos SIN estructuras
Z232: caja frameless 10 doble | AC232: Sun out | AD232: 1.58 | AE232: 11000 | AQ232: Lienzo tiro y retiro con uniones con calce sin estructutas
Z233: caja frameless 10 simple | AC233: Taslan | AD233: 1.48 | AE233: 11500 | AQ233: Lienzo tiro y retiro con uniones con calce, bolsillo tubo metálico arriba y pletina metálica abajo con cable y candados
Z234: caja frameless 8 simple | AC234: Velo liso | AD234: 1.38 | AE234: 10000 | AQ234: Lienzo tiro y retiro, madera exterior ambas caras arriba y abajo con cáncamos y cable para colgar
Z235: caja frameless 6 simple | AQ235: Lienzo tiro y retiro, tubo metálico arriba y pletina metálica abajo con cable y candados
Z236: fuente de poder | AQ236: Mantel basta perimetral 150x150
Z237: iluminación | AQ237: Mantel con calce y basta 210x300
Z238: instalación | AQ238: Panel araña 1 cuerpo (228 cms alto x 75 cms de ancho) con textil
Z239: perfil 6 | AQ239: Panel araña 1 cuerpo (228 cms alto x 75 cms de ancho) solo estructura
Z240: perfil 8 | AQ240: Panel araña 2 cuerpos (228 cms alto x 150 cms de ancho) con textil
Z241: Perfil 10 | AQ241: Panel araña 2 cuerpos (228 cms alto x 150 cms de ancho) solo estructura
Z242: perfil 12 | AQ242: Panel araña 3 cuerpos (228 cms alto x 230 cms de ancho) con textil
Z243: pernos | AQ243: Panel araña 3 cuerpos (228 cms alto x 230 cms de ancho) solo estructura
Z244: esquineros | AQ244: Panel araña 4 cuerpos (228 cms alto x 300 cms de ancho) con textil
Z245: caja frameless 10 exhibidor | AQ245: Panel araña 4 cuerpos (228 cms alto x 300 cms de ancho) solo estructura
Z246: textil backlight | AQ246: Panel araña 5 cuerpos (228 cms alto x 375 cms de ancho) con textil
AQ247: Panel araña 5 cuerpos (228 cms alto x 375 cms de ancho) solo estructura
AQ248: Panel araña 6 cuerpos (228 cms alto x 450 cms de ancho) con textil
AQ249: Panel araña 6 cuerpos (228 cms alto x 450 cms de ancho) solo estructura
AQ250: Pañuelo 100x100 cms
AQ251: Pañuelo 50x50 cms
AQ252: Pañuelo 70x70 cms
AQ253: Pañuelo 90x90 cms
AQ254: Pareo 140x140 cms
AQ255: Pechera adulto con boslillo
AQ256: Pechera adulto simple
AQ257: Pechera niño con bolsillo
AQ258: Pechera niño simple
... AQ287: Vela 90x300 solo con asta de fibra de vidrio

Sheet Cotización
H1: COTIZACIÓN Nº: | I1: ='Nota de venta'!H1 -> 0 | AD1: Venta Directa | AG1: RC Ferias | AJ1: Inser
Y2: E-Mail | Z2: Sí | AA2: Directo | AB2: Tela | AC2: Valor Mínimo | AD2: 3-50 m2 | AE2: 51-100 m2 | AF2: 101-200 m2 | AG2: 3-50 m2 | AH2: 51-100 m2 | AI2: 101-200 m2 | AJ2: 3-100 m2 | AK2: 101-300 m2 | AL2: Pop Up
B3: fecha | C3: ='Nota de venta'!C2 -> 0 | Y3: CD/DVD | Z3: No | AA3: RC Ferias | AB3: 3304 - Bandera | AC3: 35000 | AD3: 14000 | AE3: 12500 | AF3: 10500 | AG3: 11000 | AH3: 9500 | AI3: 8000 | AJ3: 9500 | AK3: 8000 | AL3: Roller
B4: DATOS CLIENTE | Y4: Laser | AA4: Inser | AB4: 3306 - Mesh Mate | AC4: 36000 | AD4: 15000 | AE4: 13000 | AF4: 11500 | AG4: 11500 | AH4: 10000 | AI4: 9000 | AJ4: 10000 | AK4: 9000 | AL4: Pendón
B5: Estimado(a): | C5: ='Nota de venta'!C5 -> 0 | F5: Rut: | H5: ='Nota de venta'!I6 -> 0 | Y5: Otros | AB5: 3307 - Mesh Brillante | AC5: 36000 | AD5: 15000 | AE5: 13000 | AF5: 11500 | AG5: 11500 | AH5: 10000 | AI5: 9000 | AJ5: 10000 | AK5: 9000 | AL5: Bandera
B6: Empresa: | C6: ='Nota de venta'!C6 -> 0 | F6: Razon Social: | H6: ='Nota de venta'!I5 -> 0 | AB6: 3302 - Satín | AC6: 40000 | AD6: 15500 | AE6: 13500 | AF6: 12000 | AG6: 12000 | AH6: 11000 | AI6: 10000 | AJ6: 11000 | AK6: 10000 | AL6: Panel
B7: Nombre: | C7: ='Nota de venta'!C112 -> 0 | F7: Condiciones de pago: | AB7: 3308 - Perforado | AC7: 40000 | AD7: 16000 | AE7: 14000 | AF7: 12500 | AG7: 12500 | AH7: 11500 | AI7: 10500 | AJ7: 11500 | AK7: 10500 | AL7: Otros
B8: Descripción: | C8: ='Nota de venta'!C113 -> 0
B10: REQUERIMIENTO TEXTIL | N10: =#REF! -> #REF! | AB10: 3309 - Canvas | AC10: 40000 | AD10: 16500 | AE10: 14500 | AF10: 13000 | AG10: 13000 | AH10: 12000 | AI10: 11000 | AJ10: 12000 | AK10: 11000
B11: Tema | C11: # | D11: Producto | E11: Ancho | F11: Alto | G11: ML | H11: valor unitario | I11: Valor Total | X11: 3340 - Popelina | Y11: 45000 | Z11: 17000 | AA11: 15000 | AB11: 14000 | AC11: 14000 | AD11: 13000 | AE11: 12000 | AF11: 13000 | AG11: 12000
A12: 1 | B12: ='Nota de venta'!L10 -> Tema | C12: ='Nota de venta'!G10 -> 0 | D12: ='Nota de venta'!B10 -> 0 | E12: ='Nota de venta'!E10 -> 0 | F12: ='Nota de venta'!F10 -> 0 | G12: ='Nota de venta'!J10 -> 0 | H12: ='Nota de venta'!G117 -> #DIV/0! | I12: =IF(ISNUMBER(COTIZACION[[#This Row],[valor unitario]]),COTIZACION[[#This Row],[valor unitario]]*COTIZACION[[#This Row],['#]],0) -> 0
A13: 2 | B13: ='Nota de venta'!L11 -> 0 | C13: ='Nota de venta'!G11 -> 0 | D13: ='Nota de venta'!B11 -> 0 | E13: ='Nota de venta'!E11 -> 0 | F13: ='Nota de venta'!F11 -> 0 | G13: ='Nota de venta'!J11 -> 0 | H13: ='Nota de venta'!G118 -> #DIV/0! | I13: =IF(ISNUMBER(COTIZACION[[#This Row],[valor unitario]]),COTIZACION[[#This Row],[valor unitario]]*COTIZACION[[#This Row],['#]],0) -> 0
A14: 3 | B14: ='Nota de venta'!L12 -> 0 | C14: ='Nota de venta'!G12 -> 0 | D14: ='Nota de venta'!B12 -> 0 | E14: ='Nota de venta'!E12 -> 0 | F14: ='Nota de venta'!F12 -> 0 | G14: ='Nota de venta'!J12 -> 0 | H14: ='Nota de venta'!G119 -> #DIV/0! | I14: =IF(ISNUMBER(COTIZACION[[#This Row],[valor unitario]]),COTIZACION[[#This Row],[valor unitario]]*COTIZACION[[#This Row],['#]],0) -> 0
A15: 4 | B15: ='Nota de venta'!L13 -> 0 | C15: ='Nota de venta'!G13 -> 0 | D15: ='Nota de venta'!B13 -> 0 | E15: ='Nota de venta'!E13 -> 0 | F15: ='Nota de venta'!F13 -> 0 | G15: ='Nota de venta'!J13 -> 0 | H15: ='Nota de venta'!G120 -> #DIV/0! | I15: =IF(ISNUMBER(COTIZACION[[#This Row],[valor unitario]]),COTIZACION[[#This Row],[valor unitario]]*COTIZACION[[#This Row],['#]],0) -> 0
A16: 5 | B16: ='Nota de venta'!L14 -> 0 | C16: ='Nota de venta'!G14 -> 0 | D16: ='Nota de venta'!B14 -> 0 | E16: ='Nota de venta'!E14 -> 0 | F16: ='Nota de venta'!F14 -> 0 | G16: ='Nota de venta'!J14 -> 0 | H16: ='Nota de venta'!G121 -> #DIV/0! | I16: =IF(ISNUMBER(COTIZACION[[#This Row],[valor unitario]]),COTIZACION[[#This Row],[valor unitario]]*COTIZACION[[#This Row],['#]],0) -> 0
A17: 6 | B17: ='Nota de venta'!L15 -> 0 | C17: ='Nota de venta'!G15 -> 0 | D17: ='Nota de venta'!B15 -> 0 | E17: ='Nota de venta'!E15 -> 0 | F17: ='Nota de venta'!F15 -> 0 | G17: ='Nota de venta'!J15 -> 0 | H17: ='Nota de venta'!G122 -> #DIV/0! | I17: =IF(ISNUMBER(COTIZACION[[#This Row],[valor unitario]]),COTIZACION[[#This Row],[valor unitario]]*COTIZACION[[#This Row],['#]],0) -> 0
A18: 7 | B18: ='Nota de venta'!L16 -> 0 | C18: ='Nota de venta'!G16 -> 0 | D18: ='Nota de venta'!B16 -> 0 | E18: ='Nota de venta'!E16 -> 0 | F18: ='Nota de venta'!F16 -> 0 | G18: ='Nota de venta'!J16 -> 0 | H18: ='Nota de venta'!G123 -> #DIV/0! | I18: =IF(ISNUMBER(COTIZACION[[#This Row],[valor unitario]]),COTIZACION[[#This Row],[valor unitario]]*COTIZACION[[#This Row],['#]],0) -> 0
A19: 8 | B19: ='Nota de venta'!L17 -> 0 | C19: ='Nota de venta'!G17 -> 0 | D19: ='Nota de venta'!B17 -> 0 | E19: ='Nota de venta'!E17 -> 0 | F19: ='Nota de venta'!F17 -> 0 | G19: ='Nota de venta'!J17 -> 0 | H19: ='Nota de venta'!G124 -> #DIV/0! | I19: =IF(ISNUMBER(COTIZACION[[#This Row],[valor unitario]]),COTIZACION[[#This Row],[valor unitario]]*COTIZACION[[#This Row],['#]],0) -> 0
A20: 9 | B20: ='Nota de venta'!L18 -> 0 | C20: ='Nota de venta'!G18 -> 0 | D20: ='Nota de venta'!B18 -> 0 | E20: ='Nota de venta'!E18 -> 0 | F20: ='Nota de venta'!F18 -> 0 | G20: ='Nota de venta'!J18 -> 0 | H20: ='Nota de venta'!G125 -> #DIV/0! | I20: =IF(ISNUMBER(COTIZACION[[#This Row],[valor unitario]]),COTIZACION[[#This Row],[valor unitario]]*COTIZACION[[#This Row],['#]],0) -> 0
A21: 10 | B21: ='Nota de venta'!L19 -> 0 | C21: ='Nota de venta'!G19 -> 0 | D21: ='Nota de venta'!B19 -> 0 | E21: ='Nota de venta'!E19 -> 0 | F21: ='Nota de venta'!F19 -> 0 | G21: ='Nota de venta'!J19 -> 0 | H21: ='Nota de venta'!G126 -> #DIV/0! | I21: =IF(ISNUMBER(COTIZACION[[#This Row],[valor unitario]]),COTIZACION[[#This Row],[valor unitario]]*COTIZACION[[#This Row],['#]],0) -> 0
A22: 11 | B22: ='Nota de venta'!L20 -> 0 | C22: ='Nota de venta'!G20 -> 0 | D22: ='Nota de venta'!B20 -> 0 | E22: ='Nota de venta'!E20 -> 0 | F22: ='Nota de venta'!F20 -> 0 | G22: ='Nota de venta'!J20 -> 0 | H22: ='Nota de venta'!G127 -> #DIV/0! | I22: =IF(ISNUMBER(COTIZACION[[#This Row],[valor unitario]]),COTIZACION[[#This Row],[valor unitario]]*COTIZACION[[#This Row],['#]],0) -> 0
A23: 12 | B23: ='Nota de venta'!L21 -> 0 | C23: ='Nota de venta'!G21 -> 0 | D23: ='Nota de venta'!B21 -> 0 | E23: ='Nota de venta'!E21 -> 0 | F23: ='Nota de venta'!F21 -> 0 | G23: ='Nota de venta'!J21 -> 0 | H23: ='Nota de venta'!G128 -> #DIV/0! | I23: =IF(ISNUMBER(COTIZACION[[#This Row],[valor unitario]]),COTIZACION[[#This Row],[valor unitario]]*COTIZACION[[#This Row],['#]],0) -> 0
... A110: 99 | B110: ='Nota de venta'!L108 -> 0 | C110: ='Nota de venta'!G108 -> 0 | D110: ='Nota de venta'!B108 -> 0 | E110: ='Nota de venta'!E108 -> 0 | F110: ='Nota de venta'!F108 -> 0 | G110: ='Nota de venta'!J108 -> 0 | H110: ='Nota de venta'!G215 -> #DIV/0! | I110: =IF(ISNUMBER(COTIZACION[[#This Row],[valor unitario]]),COTIZACION[[#This Row],[valor unitario]]*COTIZACION[[#This Row],['#]],0) -> 0
A111: 100 | B111: ='Nota de venta'!L109 -> 0 | C111: ='Nota de venta'!G109 -> 0 | D111: ='Nota de venta'!B109 -> 0 | E111: ='Nota de venta'!E110 -> 0 | F111: ='Nota de venta'!F110 -> 0 | G111: ='Nota de venta'!J110 -> 0 | H111: ='Nota de venta'!G216 -> #DIV/0! | I111: =IF(ISNUMBER(COTIZACION[[#This Row],[valor unitario]]),COTIZACION[[#This Row],[valor unitario]]*COTIZACION[[#This Row],['#]],0) -> 0
C112: =SUM(COTIZACION['#]) -> 0 | H112: neto | I112: =SUM(I12:I111) -> 0
B113: Dias hábiles de producción con VºBº aprobado: | H113: descto aplicado | I113: {=IF('Nota de venta'!I7:J7*SUM('Nota de venta'!H117:H216)>'Nota de venta'!AO217,'Nota de venta'!I7:J7*SUM('Nota de venta'!H117:H216),'Nota de venta'!AO217)} -> 0 | J113: 0
H114: neto total | I114: =+I112-I113 -> 0
H115: iva | I115: =+I114*0.19 -> 0
H116: total | I116: =+I114+I115 -> 0
B117: Los valores dados en esta cotización son válidos para las cantidades aquí mencionadas. Cambios en cantidades deben ser recotizados.
B120: Si esta cotización es aprobada, devuélvala firmada por E-Mail o adjunte su Orden de Compra a: admin@texdigital.cl
B122: Datos para OC: | C122: Textiles Digitales Ltda./ 76.144.885-4/Ss. De Publicidad/ San Isidro 1927/ Santiago/Chile
B124: Datos bancarios: | D124: BANCO SANTANDER.CTA CTE: 0-000-8759710-5

Sheet OP
I1: Nº OP | J1: ='Nota de venta'!H1 -> 0
D2: ='Nota de venta'!C112 -> 0
I3: Ingreso
I4: Entrega
A5: cliente | B5: ='Nota de venta'!C6 -> 0 | I5: contacto | J5: ='Nota de venta'!C5 -> 0
A7: OBSERVACION | B7: ='Nota de venta'!C114 -> 0
AM8: Inser
A9: TEMA | B9: Producto | C9: Textil | D9: Ancho | E9: Alto | F9: # | G9: ML | H9: obs
A10: =NotaDeVenta[[#This Row],[Tema]] -> Tema | B10: =NotaDeVenta[[#This Row],[Producto]] -> 0 | C10: =NotaDeVenta[[#This Row],[Textil]] -> 0 | D10: =NotaDeVenta[[#This Row],[Ancho]] -> 0 | E10: =NotaDeVenta[[#This Row],[Alto]] -> 0 | F10: =NotaDeVenta[[#This Row],[Cantidad]] -> 0 | G10: =NotaDeVenta[[#This Row],[ML impresos]] -> 0
A11: =NotaDeVenta[[#This Row],[Tema]] -> 0 | B11: =NotaDeVenta[[#This Row],[Producto]] -> 0 | C11: =NotaDeVenta[[#This Row],[Textil]] -> 0 | D11: =NotaDeVenta[[#This Row],[Ancho]] -> 0 | E11: =NotaDeVenta[[#This Row],[Alto]] -> 0 | F11: =NotaDeVenta[[#This Row],[Cantidad]] -> 0 | G11: =NotaDeVenta[[#This Row],[ML impresos]] -> 0
A12: =NotaDeVenta[[#This Row],[Tema]] -> 0 | B12: =NotaDeVenta[[#This Row],[Producto]] -> 0 | C12: =NotaDeVenta[[#This Row],[Textil]] -> 0 | D12: =NotaDeVenta[[#This Row],[Ancho]] -> 0 | E12: =NotaDeVenta[[#This Row],[Alto]] -> 0 | F12: =NotaDeVenta[[#This Row],[Cantidad]] -> 0 | G12: =NotaDeVenta[[#This Row],[ML impresos]] -> 0
A13: =NotaDeVenta[[#This Row],[Tema]] -> 0 | B13: =NotaDeVenta[[#This Row],[Producto]] -> 0 | C13: =NotaDeVenta[[#This Row],[Textil]] -> 0 | D13: =NotaDeVenta[[#This Row],[Ancho]] -> 0 | E13: =NotaDeVenta[[#This Row],[Alto]] -> 0 | F13: =NotaDeVenta[[#This Row],[Cantidad]] -> 0 | G13: =NotaDeVenta[[#This Row],[ML impresos]] -> 0
A14: =NotaDeVenta[[#This Row],[Tema]] -> 0 | B14: =NotaDeVenta[[#This Row],[Producto]] -> 0 | C14: =NotaDeVenta[[#This Row],[Textil]] -> 0 | D14: =NotaDeVenta[[#This Row],[Ancho]] -> 0 | E14: =NotaDeVenta[[#This Row],[Alto]] -> 0 | F14: =NotaDeVenta[[#This Row],[Cantidad]] -> 0 | G14: =NotaDeVenta[[#This Row],[ML impresos]] -> 0
A15: =NotaDeVenta[[#This Row],[Tema]] -> 0 | B15: =NotaDeVenta[[#This Row],[Producto]] -> 0 | C15: =NotaDeVenta[[#This Row],[Textil]] -> 0 | D15: =NotaDeVenta[[#This Row],[Ancho]] -> 0 | E15: =NotaDeVenta[[#This Row],[Alto]] -> 0 | F15: =NotaDeVenta[[#This Row],[Cantidad]] -> 0 | G15: =NotaDeVenta[[#This Row],[ML impresos]] -> 0
A16: =NotaDeVenta[[#This Row],[Tema]] -> 0 | B16: =NotaDeVenta[[#This Row],[Producto]] -> 0 | C16: =NotaDeVenta[[#This Row],[Textil]] -> 0 | D16: =NotaDeVenta[[#This Row],[Ancho]] -> 0 | E16: =NotaDeVenta[[#This Row],[Alto]] -> 0 | F16: =NotaDeVenta[[#This Row],[Cantidad]] -> 0 | G16: =NotaDeVenta[[#This Row],[ML impresos]] -> 0
A17: =NotaDeVenta[[#This Row],[Tema]] -> 0 | B17: =NotaDeVenta[[#This Row],[Producto]] -> 0 | C17: =NotaDeVenta[[#This Row],[Textil]] -> 0 | D17: =NotaDeVenta[[#This Row],[Ancho]] -> 0 | E17: =NotaDeVenta[[#This Row],[Alto]] -> 0 | F17: =NotaDeVenta[[#This Row],[Cantidad]] -> 0 | G17: =NotaDeVenta[[#This Row],[ML impresos]] -> 0
A18: =NotaDeVenta[[#This Row],[Tema]] -> 0 | B18: =NotaDeVenta[[#This Row],[Producto]] -> 0 | C18: =NotaDeVenta[[#This Row],[Textil]] -> 0 | D18: =NotaDeVenta[[#This Row],[Ancho]] -> 0 | E18: =NotaDeVenta[[#This Row],[Alto]] -> 0 | F18: =NotaDeVenta[[#This Row],[Cantidad]] -> 0 | G18: =NotaDeVenta[[#This Row],[ML impresos]] -> 0
A19: =NotaDeVenta[[#This Row],[Tema]] -> 0 | B19: =NotaDeVenta[[#This Row],[Producto]] -> 0 | C19: =NotaDeVenta[[#This Row],[Textil]] -> 0 | D19: =NotaDeVenta[[#This Row],[Ancho]] -> 0 | E19: =NotaDeVenta[[#This Row],[Alto]] -> 0 | F19: =NotaDeVenta[[#This Row],[Cantidad]] -> 0 | G19: =NotaDeVenta[[#This Row],[ML impresos]] -> 0
A20: =NotaDeVenta[[#This Row],[Tema]] -> 0 | B20: =NotaDeVenta[[#This Row],[Producto]] -> 0 | C20: =NotaDeVenta[[#This Row],[Textil]] -> 0 | D20: =NotaDeVenta[[#This Row],[Ancho]] -> 0 | E20: =NotaDeVenta[[#This Row],[Alto]] -> 0 | F20: =NotaDeVenta[[#This Row],[Cantidad]] -> 0 | G20: =NotaDeVenta[[#This Row],[ML impresos]] -> 0
A21: =NotaDeVenta[[#This Row],[Tema]] -> 0 | B21: =NotaDeVenta[[#This Row],[Producto]] -> 0 | C21: =NotaDeVenta[[#This Row],[Textil]] -> 0 | D21: =NotaDeVenta[[#This Row],[Ancho]] -> 0 | E21: =NotaDeVenta[[#This Row],[Alto]] -> 0 | F21: =NotaDeVenta[[#This Row],[Cantidad]] -> 0 | G21: =NotaDeVenta[[#This Row],[ML impresos]] -> 0
... A110: =NotaDeVenta[[#This Row],[Tema]] -> 0 | B110: =NotaDeVenta[[#This Row],[Producto]] -> 0 | C110: =NotaDeVenta[[#This Row],[Textil]] -> 0 | D110: =NotaDeVenta[[#This Row],[Ancho]] -> 0 | E110: =NotaDeVenta[[#This Row],[Alto]] -> 0 | F110: =NotaDeVenta[[#This Row],[Cantidad]] -> 0 | G110: =NotaDeVenta[[#This Row],[ML impresos]] -> 0
F111: =SUM(F10:F110) -> 0 | G111: =SUM(G10:G110) -> 0 | AM111: vehículo propio
A113: MTS TOTALES PAPEL | H113: PRENSA:
A114: MTS TOTALES TELA | E114: Nº ROLLO
A115: CONFECCIÓN:
A116: DESPACHO

Sheet OP TELAS
I1: Nº OP | J1: ='Nota de venta'!H1 -> 0 | Z1: CAJA TERMINADA | AA1: Tela
D2: ='Nota de venta'!C112 -> 0 | Z2: AREA VISUAL | AA2: popelina backlight 155
I3: Ingreso | AA3: popelina backlight 310
I4: Entrega | AA4: pearl 155
B5: cliente | C5: ='Nota de venta'!C6 -> 0 | AA5: pearl 310
B6: obs: | C6: ='Nota de venta'!C114 -> 0 | I6: valor impresión | AA6: pearl 160 hp
J7: CAJA TERMINADA
B8: textil | C8: # | D8: ANCHO | E8: ALTO | F8: exc cms x lado | G8: ancho final | H8: alto final | I8: m2 unit | J8: m2 total | K8: valor unit | L8: corte ancho | M8: corte alto | N8: tema
A9: 1 | B9: ='Nota de venta'!C10 -> 0 | C9: ='Nota de venta'!G10 -> 0 | D9: ='Nota de venta'!E10 -> 0 | E9: ='Nota de venta'!F10 -> 0 | F9: 1.5 | G9: =TablaOpTelas[[#This Row],[ANCHO]]+(TablaOpTelas[[#This Row],[exc cms x lado]]/100)*2 -> 0.03 | H9: =TablaOpTelas[[#This Row],[ALTO]]+(TablaOpTelas[[#This Row],[exc cms x lado]]/100)*2 -> 0.03 | I9: =TablaOpTelas[[#This Row],[ancho final]]*TablaOpTelas[[#This Row],[alto final]] -> 0.0009 | J9: =TablaOpTelas[[#This Row],[m2 unit]]*TablaOpTelas[[#This Row],['#]] -> 0 | K9: =TablaOpTelas[[#This Row],[ANCHO]]*TablaOpTelas[[#This Row],[ALTO]]*$J$6 -> 0 | L9: =IF($J$7="CAJA TERMINADA",TablaOpTelas[[#This Row],[ANCHO]]+0.013,TablaOpTelas[[#This Row],[ANCHO]]+0.023) -> 0.013 | M9: =IF($J$7="CAJA TERMINADA",TablaOpTelas[[#This Row],[ALTO]]+0.013,TablaOpTelas[[#This Row],[ALTO]]+0.023) -> 0.013 | N9: ='Nota de venta'!L10 -> Tema
A10: 2 | B10: ='Nota de venta'!C11 -> 0 | C10: ='Nota de venta'!G11 -> 0 | D10: ='Nota de venta'!E11 -> 0 | E10: ='Nota de venta'!F11 -> 0 | F10: 1.5 | G10: =TablaOpTelas[[#This Row],[ANCHO]]+(TablaOpTelas[[#This Row],[exc cms x lado]]/100)*2 -> 0.03 | H10: =TablaOpTelas[[#This Row],[ALTO]]+(TablaOpTelas[[#This Row],[exc cms x lado]]/100)*2 -> 0.03 | I10: =TablaOpTelas[[#This Row],[ancho final]]*TablaOpTelas[[#This Row],[alto final]] -> 0.0009 | J10: =TablaOpTelas[[#This Row],[m2 unit]]*TablaOpTelas[[#This Row],['#]] -> 0 | K10: =TablaOpTelas[[#This Row],[ANCHO]]*TablaOpTelas[[#This Row],[ALTO]]*$J$6 -> 0 | L10: =IF($J$7="CAJA TERMINADA",TablaOpTelas[[#This Row],[ANCHO]]+0.013,TablaOpTelas[[#This Row],[ANCHO]]+0.023) -> 0.013 | M10: =IF($J$7="CAJA TERMINADA",TablaOpTelas[[#This Row],[ALTO]]+0.013,TablaOpTelas[[#This Row],[ALTO]]+0.023) -> 0.013 | N10: ='Nota de venta'!L11 -> 0
A11: 3 | B11: ='Nota de venta'!C12 -> 0 | C11: ='Nota de venta'!G12 -> 0 | D11: ='Nota de venta'!E12 -> 0 | E11: ='Nota de venta'!F12 -> 0 | F11: 1.5 | G11: =TablaOpTelas[[#This Row],[ANCHO]]+(TablaOpTelas[[#This Row],[exc cms x lado]]/100)*2 -> 0.03 | H11: =TablaOpTelas[[#This Row],[ALTO]]+(TablaOpTelas[[#This Row],[exc cms x lado]]/100)*2 -> 0.03 | I11: =TablaOpTelas[[#This Row],[ancho final]]*TablaOpTelas[[#This Row],[alto final]] -> 0.0009 | J11: =TablaOpTelas[[#This Row],[m2 unit]]*TablaOpTelas[[#This Row],['#]] -> 0 | K11: =TablaOpTelas[[#This Row],[ANCHO]]*TablaOpTelas[[#This Row],[ALTO]]*$J$6 -> 0 | L11: =IF($J$7="CAJA TERMINADA",TablaOpTelas[[#This Row],[ANCHO]]+0.013,TablaOpTelas[[#This Row],[ANCHO]]+0.023) -> 0.013 | M11: =IF($J$7="CAJA TERMINADA",TablaOpTelas[[#This Row],[ALTO]]+0.013,TablaOpTelas[[#This Row],[ALTO]]+0.023) -> 0.013 | N11: ='Nota de venta'!L12 -> 0
A12: 4 | B12: ='Nota de venta'!C13 -> 0 | C12: ='Nota de venta'!G13 -> 0 | D12: ='Nota de venta'!E13 -> 0 | E12: ='Nota de venta'!F13 -> 0 | F12: 1.5 | G12: =TablaOpTelas[[#This Row],[ANCHO]]+(TablaOpTelas[[#This Row],[exc cms x lado]]/100)*2 -> 0.03 | H12: =TablaOpTelas[[#This Row],[ALTO]]+(TablaOpTelas[[#This Row],[exc cms x lado]]/100)*2 -> 0.03 | I12: =TablaOpTelas[[#This Row],[ancho final]]*TablaOpTelas[[#This Row],[alto final]] -> 0.0009 | J12: =TablaOpTelas[[#This Row],[m2 unit]]*TablaOpTelas[[#This Row],['#]] -> 0 | K12: =TablaOpTelas[[#This Row],[ANCHO]]*TablaOpTelas[[#This Row],[ALTO]]*$J$6 -> 0 | L12: =IF($J$7="CAJA TERMINADA",TablaOpTelas[[#This Row],[ANCHO]]+0.013,TablaOpTelas[[#This Row],[ANCHO]]+0.023) -> 0.013 | M12: =IF($J$7="CAJA TERMINADA",TablaOpTelas[[#This Row],[ALTO]]+0.013,TablaOpTelas[[#This Row],[ALTO]]+0.023) -> 0.013 | N12: ='Nota de venta'!L13 -> 0
A13: 5 | B13: ='Nota de venta'!C14 -> 0 | C13: ='Nota de venta'!G14 -> 0 | D13: ='Nota de venta'!E14 -> 0 | E13: ='Nota de venta'!F14 -> 0 | F13: 1.5 | G13: =TablaOpTelas[[#This Row],[ANCHO]]+(TablaOpTelas[[#This Row],[exc cms x lado]]/100)*2 -> 0.03 | H13: =TablaOpTelas[[#This Row],[ALTO]]+(TablaOpTelas[[#This Row],[exc cms x lado]]/100)*2 -> 0.03 | I13: =TablaOpTelas[[#This Row],[ancho final]]*TablaOpTelas[[#This Row],[alto final]] -> 0.0009 | J13: =TablaOpTelas[[#This Row],[m2 unit]]*TablaOpTelas[[#This Row],['#]] -> 0 | K13: =TablaOpTelas[[#This Row],[ANCHO]]*TablaOpTelas[[#This Row],[ALTO]]*$J$6 -> 0 | L13: =IF($J$7="CAJA TERMINADA",TablaOpTelas[[#This Row],[ANCHO]]+0.013,TablaOpTelas[[#This Row],[ANCHO]]+0.023) -> 0.013 | M13: =IF($J$7="CAJA TERMINADA",TablaOpTelas[[#This Row],[ALTO]]+0.013,TablaOpTelas[[#This Row],[ALTO]]+0.023) -> 0.013 | N13: ='Nota de venta'!L14 -> 0
A14: 6 | B14: ='Nota de venta'!C15 -> 0 | C14: ='Nota de venta'!G15 -> 0 | D14: ='Nota de venta'!E15 -> 0 | E14: ='Nota de venta'!F15 -> 0 | F14: 1.5 | G14: =TablaOpTelas[[#This Row],[ANCHO]]+(TablaOpTelas[[#This Row],[exc cms x lado]]/100)*2 -> 0.03 | H14: =TablaOpTelas[[#This Row],[ALTO]]+(TablaOpTelas[[#This Row],[exc cms x lado]]/100)*2 -> 0.03 | I14: =TablaOpTelas[[#This Row],[ancho final]]*TablaOpTelas[[#This Row],[alto final]] -> 0.0009 | J14: =TablaOpTelas[[#This Row],[m2 unit]]*TablaOpTelas[[#This Row],['#]] -> 0 | K14: =TablaOpTelas[[#This Row],[ANCHO]]*TablaOpTelas[[#This Row],[ALTO]]*$J$6 -> 0 | L14: =IF($J$7="CAJA TERMINADA",TablaOpTelas[[#This Row],[ANCHO]]+0.013,TablaOpTelas[[#This Row],[ANCHO]]+0.023) -> 0.013 | M14: =IF($J$7="CAJA TERMINADA",TablaOpTelas[[#This Row],[ALTO]]+0.013,TablaOpTelas[[#This Row],[ALTO]]+0.023) -> 0.013 | N14: ='Nota de venta'!L15 -> 0
A15: 7 | B15: ='Nota de venta'!C16 -> 0 | C15: ='Nota de venta'!G16 -> 0 | D15: ='Nota de venta'!E16 -> 0 | E15: ='Nota de venta'!F16 -> 0 | F15: 1.5 | G15: =TablaOpTelas[[#This Row],[ANCHO]]+(TablaOpTelas[[#This Row],[exc cms x lado]]/100)*2 -> 0.03 | H15: =TablaOpTelas[[#This Row],[ALTO]]+(TablaOpTelas[[#This Row],[exc cms x lado]]/100)*2 -> 0.03 | I15: =TablaOpTelas[[#This Row],[ancho final]]*TablaOpTelas[[#This Row],[alto final]] -> 0.0009 | J15: =TablaOpTelas[[#This Row],[m2 unit]]*TablaOpTelas[[#This Row],['#]] -> 0 | K15: =TablaOpTelas[[#This Row],[ANCHO]]*TablaOpTelas[[#This Row],[ALTO]]*$J$6 -> 0 | L15: =IF($J$7="CAJA TERMINADA",TablaOpTelas[[#This Row],[ANCHO]]+0.013,TablaOpTelas[[#This Row],[ANCHO]]+0.023) -> 0.013 | M15: =IF($J$7="CAJA TERMINADA",TablaOpTelas[[#This Row],[ALTO]]+0.013,TablaOpTelas[[#This Row],[ALTO]]+0.023) -> 0.013 | N15: ='Nota de venta'!L16 -> 0
A16: 8 | B16: ='Nota de venta'!C17 -> 0 | C16: ='Nota de venta'!G17 -> 0 | D16: ='Nota de venta'!E17 -> 0 | E16: ='Nota de venta'!F17 -> 0 | F16: 1.5 | G16: =TablaOpTelas[[#This Row],[ANCHO]]+(TablaOpTelas[[#This Row],[exc cms x lado]]/100)*2 -> 0.03 | H16: =TablaOpTelas[[#This Row],[ALTO]]+(TablaOpTelas[[#This Row],[exc cms x lado]]/100)*2 -> 0.03 | I16: =TablaOpTelas[[#This Row],[ancho final]]*TablaOpTelas[[#This Row],[alto final]] -> 0.0009 | J16: =TablaOpTelas[[#This Row],[m2 unit]]*TablaOpTelas[[#This Row],['#]] -> 0 | K16: =TablaOpTelas[[#This Row],[ANCHO]]*TablaOpTelas[[#This Row],[ALTO]]*$J$6 -> 0 | L16: =IF($J$7="CAJA TERMINADA",TablaOpTelas[[#This Row],[ANCHO]]+0.013,TablaOpTelas[[#This Row],[ANCHO]]+0.023) -> 0.013 | M16: =IF($J$7="CAJA TERMINADA",TablaOpTelas[[#This Row],[ALTO]]+0.013,TablaOpTelas[[#This Row],[ALTO]]+0.023) -> 0.013 | N16: ='Nota de venta'!L17 -> 0
A17: 9 | B17: ='Nota de venta'!C18 -> 0 | C17: ='Nota de venta'!G18 -> 0 | D17: ='Nota de venta'!E18 -> 0 | E17: ='Nota de venta'!F18 -> 0 | F17: 1.5 | G17: =TablaOpTelas[[#This Row],[ANCHO]]+(TablaOpTelas[[#This Row],[exc cms x lado]]/100)*2 -> 0.03 | H17: =TablaOpTelas[[#This Row],[ALTO]]+(TablaOpTelas[[#This Row],[exc cms x lado]]/100)*2 -> 0.03 | I17: =TablaOpTelas[[#This Row],[ancho final]]*TablaOpTelas[[#This Row],[alto final]] -> 0.0009 | J17: =TablaOpTelas[[#This Row],[m2 unit]]*TablaOpTelas[[#This Row],['#]] -> 0 | K17: =TablaOpTelas[[#This Row],[ANCHO]]*TablaOpTelas[[#This Row],[ALTO]]*$J$6 -> 0 | L17: =IF($J$7="CAJA TERMINADA",TablaOpTelas[[#This Row],[ANCHO]]+0.013,TablaOpTelas[[#This Row],[ANCHO]]+0.023) -> 0.013 | M17: =IF($J$7="CAJA TERMINADA",TablaOpTelas[[#This Row],[ALTO]]+0.013,TablaOpTelas[[#This Row],[ALTO]]+0.023) -> 0.013 | N17: ='Nota de venta'!L18 -> 0
A18: 10 | B18: ='Nota de venta'!C19 -> 0 | C18: ='Nota de venta'!G19 -> 0 | D18: ='Nota de venta'!E19 -> 0 | E18: ='Nota de venta'!F19 -> 0 | F18: 1.5 | G18: =TablaOpTelas[[#This Row],[ANCHO]]+(TablaOpTelas[[#This Row],[exc cms x lado]]/100)*2 -> 0.03 | H18: =TablaOpTelas[[#This Row],[ALTO]]+(TablaOpTelas[[#This Row],[exc cms x lado]]/100)*2 -> 0.03 | I18: =TablaOpTelas[[#This Row],[ancho final]]*TablaOpTelas[[#This Row],[alto final]] -> 0.0009 | J18: =TablaOpTelas[[#This Row],[m2 unit]]*TablaOpTelas[[#This Row],['#]] -> 0 | K18: =TablaOpTelas[[#This Row],[ANCHO]]*TablaOpTelas[[#This Row],[ALTO]]*$J$6 -> 0 | L18: =IF($J$7="CAJA TERMINADA",TablaOpTelas[[#This Row],[ANCHO]]+0.013,TablaOpTelas[[#This Row],[ANCHO]]+0.023) -> 0.013 | M18: =IF($J$7="CAJA TERMINADA",TablaOpTelas[[#This Row],[ALTO]]+0.013,TablaOpTelas[[#This Row],[ALTO]]+0.023) -> 0.013 | N18: ='Nota de venta'!L19 -> 0
A19: 11 | B19: ='Nota de venta'!C20 -> 0 | C19: ='Nota de venta'!G20 -> 0 | D19: ='Nota de venta'!E20 -> 0 | E19: ='Nota de venta'!F20 -> 0 | F19: 1.5 | G19: =TablaOpTelas[[#This Row],[ANCHO]]+(TablaOpTelas[[#This Row],[exc cms x lado]]/100)*2 -> 0.03 | H19: =TablaOpTelas[[#This Row],[ALTO]]+(TablaOpTelas[[#This Row],[exc cms x lado]]/100)*2 -> 0.03 | I19: =TablaOpTelas[[#This Row],[ancho final]]*TablaOpTelas[[#This Row],[alto final]] -> 0.0009 | J19: =TablaOpTelas[[#This Row],[m2 unit]]*TablaOpTelas[[#This Row],['#]] -> 0 | K19: =TablaOpTelas[[#This Row],[ANCHO]]*TablaOpTelas[[#This Row],[ALTO]]*$J$6 -> 0 | L19: =IF($J$7="CAJA TERMINADA",TablaOpTelas[[#This Row],[ANCHO]]+0.013,TablaOpTelas[[#This Row],[ANCHO]]+0.023) -> 0.013 | M19: =IF($J$7="CAJA TERMINADA",TablaOpTelas[[#This Row],[ALTO]]+0.013,TablaOpTelas[[#This Row],[ALTO]]+0.023) -> 0.013 | N19: ='Nota de venta'!L20 -> 0
A20: 12 | B20: ='Nota de venta'!C21 -> 0 | C20: ='Nota de venta'!G21 -> 0 | D20: ='Nota de venta'!E21 -> 0 | E20: ='Nota de venta'!F21 -> 0 | F20: 1.5 | G20: =TablaOpTelas[[#This Row],[ANCHO]]+(TablaOpTelas[[#This Row],[exc cms x lado]]/100)*2 -> 0.03 | H20: =TablaOpTelas[[#This Row],[ALTO]]+(TablaOpTelas[[#This Row],[exc cms x lado]]/100)*2 -> 0.03 | I20: =TablaOpTelas[[#This Row],[ancho final]]*TablaOpTelas[[#This Row],[alto final]] -> 0.0009 | J20: =TablaOpTelas[[#This Row],[m2 unit]]*TablaOpTelas[[#This Row],['#]] -> 0 | K20: =TablaOpTelas[[#This Row],[ANCHO]]*TablaOpTelas[[#This Row],[ALTO]]*$J$6 -> 0 | L20: =IF($J$7="CAJA TERMINADA",TablaOpTelas[[#This Row],[ANCHO]]+0.013,TablaOpTelas[[#This Row],[ANCHO]]+0.023) -> 0.013 | M20: =IF($J$7="CAJA TERMINADA",TablaOpTelas[[#This Row],[ALTO]]+0.013,TablaOpTelas[[#This Row],[ALTO]]+0.023) -> 0.013 | N20: ='Nota de venta'!L21 -> 0
... A107: 99 | B107: ='Nota de venta'!C108 -> 0 | C107: ='Nota de venta'!G108 -> 0 | D107: ='Nota de venta'!E108 -> 0 | E107: ='Nota de venta'!F108 -> 0 | F107: 1.5 | G107: =TablaOpTelas[[#This Row],[ANCHO]]+(TablaOpTelas[[#This Row],[exc cms x lado]]/100)*2 -> 0.03 | H107: =TablaOpTelas[[#This Row],[ALTO]]+(TablaOpTelas[[#This Row],[exc cms x lado]]/100)*2 -> 0.03 | I107: =TablaOpTelas[[#This Row],[ancho final]]*TablaOpTelas[[#This Row],[alto final]] -> 0.0009 | J107: =TablaOpTelas[[#This Row],[m2 unit]]*TablaOpTelas[[#This Row],['#]] -> 0 | K107: =TablaOpTelas[[#This Row],[ANCHO]]*TablaOpTelas[[#This Row],[ALTO]]*$J$6 -> 0 | L107: =IF($J$7="CAJA TERMINADA",TablaOpTelas[[#This Row],[ANCHO]]+0.013,TablaOpTelas[[#This Row],[ANCHO]]+0.023) -> 0.013 | M107: =IF($J$7="CAJA TERMINADA",TablaOpTelas[[#This Row],[ALTO]]+0.013,TablaOpTelas[[#This Row],[ALTO]]+0.023) -> 0.013 | N107: ='Nota de venta'!L108 -> 0
A108: 100 | B108: ='Nota de venta'!C110 -> 0 | C108: ='Nota de venta'!G109 -> 0 | D108: ='Nota de venta'!E110 -> 0 | E108: ='Nota de venta'!F110 -> 0 | F108: 1.5 | G108: =TablaOpTelas[[#This Row],[ANCHO]]+(TablaOpTelas[[#This Row],[exc cms x lado]]/100)*2 -> 0.03 | H108: =TablaOpTelas[[#This Row],[ALTO]]+(TablaOpTelas[[#This Row],[exc cms x lado]]/100)*2 -> 0.03 | I108: =TablaOpTelas[[#This Row],[ancho final]]*TablaOpTelas[[#This Row],[alto final]] -> 0.0009 | J108: =TablaOpTelas[[#This Row],[m2 unit]]*TablaOpTelas[[#This Row],['#]] -> 0 | K108: =TablaOpTelas[[#This Row],[ANCHO]]*TablaOpTelas[[#This Row],[ALTO]]*$J$6 -> 0 | L108: =IF($J$7="CAJA TERMINADA",TablaOpTelas[[#This Row],[ANCHO]]+0.013,TablaOpTelas[[#This Row],[ANCHO]]+0.023) -> 0.013 | M108: =IF($J$7="CAJA TERMINADA",TablaOpTelas[[#This Row],[ALTO]]+0.013,TablaOpTelas[[#This Row],[ALTO]]+0.023) -> 0.013 | N108: ='Nota de venta'!L110 -> 0
C109: =SUM(TablaOpTelas['#]) -> 0 | J109: =SUM(TablaOpTelas[m2 total]) -> 0
B110: Nº INGRESO:
B112: PLOTTER:
B114: ML REQUERIDOS | C114: =J109/'Nota de venta'!D10 -> #VALUE!

Sheet hoja1
C1: ORDEN DE PRODUCCIÓN | G1: Nº: | Z1: Venta Directa | AC1: RC Ferias | AF1: Inser
U2: E-Mail | V2: Sí | W2: Directo | X2: Tela | Y2: Valor Mínimo | Z2: 3-50 m2 | AA2: 51-100 m2 | AB2: 101-200 m2 | AC2: 3-50 m2 | AD2: 51-100 m2 | AE2: 101-200 m2 | AF2: 3-100 m2 | AG2: 101-300 m2 | AH2: Pop Up | AI2: Simple | AJ2: Manual
A3: Fecha: | C3: Fecha de Entrega: | G3: Hora Entrega: | U3: CD/DVD | V3: No | W3: RC Ferias | X3: 3304 - Bandera | Y3: 35000 | Z3: 14000 | AA3: 12500 | AB3: 10500 | AC3: 11000 | AD3: 9500 | AE3: 8000 | AF3: 9500 | AG3: 8000 | AH3: Roller | AI3: Doble | AJ3: Sellado
U4: Laser | W4: Inser | X4: 3306 - Mesh Mate | Y4: 36000 | Z4: 15000 | AA4: 13000 | AB4: 11500 | AC4: 11500 | AD4: 10000 | AE4: 9000 | AF4: 10000 | AG4: 9000 | AH4: Pendón
A5: DATOS CLIENTE | U5: Otros | X5: 3307 - Mesh Brillante | Y5: 36000 | Z5: 15000 | AA5: 13000 | AB5: 11500 | AC5: 11500 | AD5: 10000 | AE5: 9000 | AF5: 10000 | AG5: 9000 | AH5: Bandera
A6: Agencia: | C6: Cliente: | G6: Tema: | X6: 3302 - Satín | Y6: 40000 | Z6: 15500 | AA6: 13500 | AB6: 12000 | AC6: 12000 | AD6: 11000 | AE6: 10000 | AF6: 11000 | AG6: 10000 | AH6: Panel
A7: O. Compra: | C7: Contacto: | G7: Fono: | X7: 3308 - Perforado | Y7: 40000 | Z7: 16000 | AA7: 14000 | AB7: 12500 | AC7: 12500 | AD7: 11500 | AE7: 10500 | AF7: 11500 | AG7: 10500 | AH7: Otros
A8: Cotización: | C8: RUT: | G8: E-Mail: | X8: 3309 - Canvas | Y8: 40000 | Z8: 16500 | AA8: 14500 | AB8: 13000 | AC8: 13000 | AD8: 12000 | AE8: 11000 | AF8: 12000 | AG8: 11000
A9: Vendedor: | C9: Guías: | G9: Fuente: | X9: 3340 - Popelina | Y9: 45000 | Z9: 17000 | AA9: 15000 | AB9: 14000 | AC9: 14000 | AD9: 13000 | AE9: 12000 | AF9: 13000 | AG9: 12000
A11: ITEM DE INGRESO
B12: Observaciones:
A14: PRE-PRENSA
A15: Operador: | C15: Pantones:
A16: Observaciones:
A18: IMPRESIÓN
A19: Máquina: | C19: VºBº | E19: Fecha VºBº | G19: Hora VºBº
A21: REQUERIMIENTO
A22: Nº | B22: Tela | C22: Largo | D22: Alto | E22: Cantidad | F22: Total | G22: Valor Unitario | H22: Valor Total
A23: 1 | F23: =IF(LEN(C23)=0,"",ROUNDUP(E23*D23*C23,0)) | G23: =IF(LEN(B23)=0,"",IF($H$9=$W$2,IF(B23=$X$3,IF(F23<51,$Z$3,IF(F23>100,$AB$3,$AA$3)),IF(B23=$X$4,IF(F23<51,$Z$4,IF(F23>100,$AB$4,$AA$4)),IF(B23=$X$5,IF(F23<51,$Z$5,IF(F23>100,$AB$5,$AA$5)),IF(B23=$X$6,IF(F23<51,$Z$6,IF(F23>100,$AB$6,$AA$6)),IF(B23=$X$7,IF(F23<51,$Z$7,IF(F23>100,$AB$7,$AA$7)),IF(B23=$X$8,IF(F23<51,$Z$8,IF(F23>100,$AB$8,$AA$8)),IF(B23=$X$9,IF(F23<51,$Z$9,IF(F23>100,$AB$9,$AA$9))))))))),IF($H$9=$W$3,IF(B23=$X$3,IF(F23<51,$AC$3,IF(F23>100,$AE$3,$AD$3)),IF(B23=$X$4,IF(F23<51,$AC$4,IF(F23>100,$AE$4,$AD$4)),IF(B23=$X$5,IF(F23<51,$AC$5,IF(F23>100,$AE$5,$AD$5)),IF(B23=$X$6,IF(F23<51,$AC$6,IF(F23>100,$AE$6,$AD$6)),IF(B23=$X$7,IF(F23<51,$AC$7,IF(F23>100,$AE$7,$AD$7)),IF(B23=$X$8,IF(F23<51,$AC$8,IF(F23>100,$AE$8,$AD$8)),IF(B23=$X$9,IF(F23<51,$AC$9,IF(F23>100,$AE$9,$AD$9))))))))),IF($H$9=$W$4,IF(B23=$X$3,IF(F23<101,$AF$3,$AG$3),IF(B23=$X$4,IF(F23<101,$AF$4,$AG$4),IF(B23=$X$5,IF(F23<101,$AF$5,$AG$5),IF(B23=$X$6,IF(F23<101,$AF$6,$AG$6),IF(B23=$X$7,IF(F23<101,$AF$7,$AG$7),IF(B23=$X$8,IF(F23<101,$AF$8,$AG$8),IF(B23=$X$9,IF(F23<101,$AF$9,$AG$9)))))))))))) | H23: =IF(LEN(D23)=0,"",IF(B23=$X$3,IF(F23*G23<$Y$3,$Y$3,F23*G23),IF(B23=$X$4,IF(F23*G23<$Y$4,$Y$4,F23*G23),IF(B23=$X$5,IF(F23*G23<$Y$5,$Y$5,F23*G23),IF(B23=$X$6,IF(F23*G23<$Y$6,$Y$6,F23*G23),IF(B23=$X$7,IF(F23*G23<$Y$7,$Y$7,F23*G23),IF(B23=$X$8,IF(F23*G23<$Y$8,$Y$8,F23*G23),IF(B23=$X$9,IF(F23*G23<$Y$9,$Y$9,F23*G23)))))))))
A24: 2 | F24: =IF(LEN(C24)=0,"",ROUNDUP(E24*D24*C24,0)) | G24: =IF(LEN(B24)=0,"",IF($H$9=$W$2,IF(B24=$X$3,IF(F24<51,$Z$3,IF(F24>100,$AB$3,$AA$3)),IF(B24=$X$4,IF(F24<51,$Z$4,IF(F24>100,$AB$4,$AA$4)),IF(B24=$X$5,IF(F24<51,$Z$5,IF(F24>100,$AB$5,$AA$5)),IF(B24=$X$6,IF(F24<51,$Z$6,IF(F24>100,$AB$6,$AA$6)),IF(B24=$X$7,IF(F24<51,$Z$7,IF(F24>100,$AB$7,$AA$7)),IF(B24=$X$8,IF(F24<51,$Z$8,IF(F24>100,$AB$8,$AA$8)),IF(B24=$X$9,IF(F24<51,$Z$9,IF(F24>100,$AB$9,$AA$9))))))))),IF($H$9=$W$3,IF(B24=$X$3,IF(F24<51,$AC$3,IF(F24>100,$AE$3,$AD$3)),IF(B24=$X$4,IF(F24<51,$AC$4,IF(F24>100,$AE$4,$AD$4)),IF(B24=$X$5,IF(F24<51,$AC$5,IF(F24>100,$AE$5,$AD$5)),IF(B24=$X$6,IF(F24<51,$AC$6,IF(F24>100,$AE$6,$AD$6)),IF(B24=$X$7,IF(F24<51,$AC$7,IF(F24>100,$AE$7,$AD$7)),IF(B24=$X$8,IF(F24<51,$AC$8,IF(F24>100,$AE$8,$AD$8)),IF(B24=$X$9,IF(F24<51,$AC$9,IF(F24>100,$AE$9,$AD$9))))))))),IF($H$9=$W$4,IF(B24=$X$3,IF(F24<101,$AF$3,$AG$3),IF(B24=$X$4,IF(F24<101,$AF$4,$AG$4),IF(B24=$X$5,IF(F24<101,$AF$5,$AG$5),IF(B24=$X$6,IF(F24<101,$AF$6,$AG$6),IF(B24=$X$7,IF(F24<101,$AF$7,$AG$7),IF(B24=$X$8,IF(F24<101,$AF$8,$AG$8),IF(B24=$X$9,IF(F24<101,$AF$9,$AG$9)))))))))))) | H24: =IF(LEN(D24)=0,"",IF(B24=$X$3,IF(F24*G24<$Y$3,$Y$3,F24*G24),IF(B24=$X$4,IF(F24*G24<$Y$4,$Y$4,F24*G24),IF(B24=$X$5,IF(F24*G24<$Y$5,$Y$5,F24*G24),IF(B24=$X$6,IF(F24*G24<$Y$6,$Y$6,F24*G24),IF(B24=$X$7,IF(F24*G24<$Y$7,$Y$7,F24*G24),IF(B24=$X$8,IF(F24*G24<$Y$8,$Y$8,F24*G24),IF(B24=$X$9,IF(F24*G24<$Y$9,$Y$9,F24*G24)))))))))
A25: 3 | F25: =IF(LEN(C25)=0,"",ROUNDUP(E25*D25*C25,0)) | G25: =IF(LEN(B25)=0,"",IF($H$9=$W$2,IF(B25=$X$3,IF(F25<51,$Z$3,IF(F25>100,$AB$3,$AA$3)),IF(B25=$X$4,IF(F25<51,$Z$4,IF(F25>100,$AB$4,$AA$4)),IF(B25=$X$5,IF(F25<51,$Z$5,IF(F25>100,$AB$5,$AA$5)),IF(B25=$X$6,IF(F25<51,$Z$6,IF(F25>100,$AB$6,$AA$6)),IF(B25=$X$7,IF(F25<51,$Z$7,IF(F25>100,$AB$7,$AA$7)),IF(B25=$X$8,IF(F25<51,$Z$8,IF(F25>100,$AB$8,$AA$8)),IF(B25=$X$9,IF(F25<51,$Z$9,IF(F25>100,$AB$9,$AA$9))))))))),IF($H$9=$W$3,IF(B25=$X$3,IF(F25<51,$AC$3,IF(F25>100,$AE$3,$AD$3)),IF(B25=$X$4,IF(F25<51,$AC$4,IF(F25>100,$AE$4,$AD$4)),IF(B25=$X$5,IF(F25<51,$AC$5,IF(F25>100,$AE$5,$AD$5)),IF(B25=$X$6,IF(F25<51,$AC$6,IF(F25>100,$AE$6,$AD$6)),IF(B25=$X$7,IF(F25<51,$AC$7,IF(F25>100,$AE$7,$AD$7)),IF(B25=$X$8,IF(F25<51,$AC$8,IF(F25>100,$AE$8,$AD$8)),IF(B25=$X$9,IF(F25<51,$AC$9,IF(F25>100,$AE$9,$AD$9))))))))),IF($H$9=$W$4,IF(B25=$X$3,IF(F25<101,$AF$3,$AG$3),IF(B25=$X$4,IF(F25<101,$AF$4,$AG$4),IF(B25=$X$5,IF(F25<101,$AF$5,$AG$5),IF(B25=$X$6,IF(F25<101,$AF$6,$AG$6),IF(B25=$X$7,IF(F25<101,$AF$7,$AG$7),IF(B25=$X$8,IF(F25<101,$AF$8,$AG$8),IF(B25=$X$9,IF(F25<101,$AF$9,$AG$9)))))))))))) | H25: =IF(LEN(D25)=0,"",IF(B25=$X$3,IF(F25*G25<$Y$3,$Y$3,F25*G25),IF(B25=$X$4,IF(F25*G25<$Y$4,$Y$4,F25*G25),IF(B25=$X$5,IF(F25*G25<$Y$5,$Y$5,F25*G25),IF(B25=$X$6,IF(F25*G25<$Y$6,$Y$6,F25*G25),IF(B25=$X$7,IF(F25*G25<$Y$7,$Y$7,F25*G25),IF(B25=$X$8,IF(F25*G25<$Y$8,$Y$8,F25*G25),IF(B25=$X$9,IF(F25*G25<$Y$9,$Y$9,F25*G25)))))))))
A26: 4 | F26: =IF(LEN(C26)=0,"",ROUNDUP(E26*D26*C26,0)) | G26: =IF(LEN(B26)=0,"",IF($H$9=$W$2,IF(B26=$X$3,IF(F26<51,$Z$3,IF(F26>100,$AB$3,$AA$3)),IF(B26=$X$4,IF(F26<51,$Z$4,IF(F26>100,$AB$4,$AA$4)),IF(B26=$X$5,IF(F26<51,$Z$5,IF(F26>100,$AB$5,$AA$5)),IF(B26=$X$6,IF(F26<51,$Z$6,IF(F26>100,$AB$6,$AA$6)),IF(B26=$X$7,IF(F26<51,$Z$7,IF(F26>100,$AB$7,$AA$7)),IF(B26=$X$8,IF(F26<51,$Z$8,IF(F26>100,$AB$8,$AA$8)),IF(B26=$X$9,IF(F26<51,$Z$9,IF(F26>100,$AB$9,$AA$9))))))))),IF($H$9=$W$3,IF(B26=$X$3,IF(F26<51,$AC$3,IF(F26>100,$AE$3,$AD$3)),IF(B26=$X$4,IF(F26<51,$AC$4,IF(F26>100,$AE$4,$AD$4)),IF(B26=$X$5,IF(F26<51,$AC$5,IF(F26>100,$AE$5,$AD$5)),IF(B26=$X$6,IF(F26<51,$AC$6,IF(F26>100,$AE$6,$AD$6)),IF(B26=$X$7,IF(F26<51,$AC$7,IF(F26>100,$AE$7,$AD$7)),IF(B26=$X$8,IF(F26<51,$AC$8,IF(F26>100,$AE$8,$AD$8)),IF(B26=$X$9,IF(F26<51,$AC$9,IF(F26>100,$AE$9,$AD$9))))))))),IF($H$9=$W$4,IF(B26=$X$3,IF(F26<101,$AF$3,$AG$3),IF(B26=$X$4,IF(F26<101,$AF$4,$AG$4),IF(B26=$X$5,IF(F26<101,$AF$5,$AG$5),IF(B26=$X$6,IF(F26<101,$AF$6,$AG$6),IF(B26=$X$7,IF(F26<101,$AF$7,$AG$7),IF(B26=$X$8,IF(F26<101,$AF$8,$AG$8),IF(B26=$X$9,IF(F26<101,$AF$9,$AG$9)))))))))))) | H26: =IF(LEN(D26)=0,"",IF(B26=$X$3,IF(F26*G26<$Y$3,$Y$3,F26*G26),IF(B26=$X$4,IF(F26*G26<$Y$4,$Y$4,F26*G26),IF(B26=$X$5,IF(F26*G26<$Y$5,$Y$5,F26*G26),IF(B26=$X$6,IF(F26*G26<$Y$6,$Y$6,F26*G26),IF(B26=$X$7,IF(F26*G26<$Y$7,$Y$7,F26*G26),IF(B26=$X$8,IF(F26*G26<$Y$8,$Y$8,F26*G26),IF(B26=$X$9,IF(F26*G26<$Y$9,$Y$9,F26*G26)))))))))
A27: 5 | F27: =IF(LEN(C27)=0,"",ROUNDUP(E27*D27*C27,0)) | G27: =IF(LEN(B27)=0,"",IF($H$9=$W$2,IF(B27=$X$3,IF(F27<51,$Z$3,IF(F27>100,$AB$3,$AA$3)),IF(B27=$X$4,IF(F27<51,$Z$4,IF(F27>100,$AB$4,$AA$4)),IF(B27=$X$5,IF(F27<51,$Z$5,IF(F27>100,$AB$5,$AA$5)),IF(B27=$X$6,IF(F27<51,$Z$6,IF(F27>100,$AB$6,$AA$6)),IF(B27=$X$7,IF(F27<51,$Z$7,IF(F27>100,$AB$7,$AA$7)),IF(B27=$X$8,IF(F27<51,$Z$8,IF(F27>100,$AB$8,$AA$8)),IF(B27=$X$9,IF(F27<51,$Z$9,IF(F27>100,$AB$9,$AA$9))))))))),IF($H$9=$W$3,IF(B27=$X$3,IF(F27<51,$AC$3,IF(F27>100,$AE$3,$AD$3)),IF(B27=$X$4,IF(F27<51,$AC$4,IF(F27>100,$AE$4,$AD$4)),IF(B27=$X$5,IF(F27<51,$AC$5,IF(F27>100,$AE$5,$AD$5)),IF(B27=$X$6,IF(F27<51,$AC$6,IF(F27>100,$AE$6,$AD$6)),IF(B27=$X$7,IF(F27<51,$AC$7,IF(F27>100,$AE$7,$AD$7)),IF(B27=$X$8,IF(F27<51,$AC$8,IF(F27>100,$AE$8,$AD$8)),IF(B27=$X$9,IF(F27<51,$AC$9,IF(F27>100,$AE$9,$AD$9))))))))),IF($H$9=$W$4,IF(B27=$X$3,IF(F27<101,$AF$3,$AG$3),IF(B27=$X$4,IF(F27<101,$AF$4,$AG$4),IF(B27=$X$5,IF(F27<101,$AF$5,$AG$5),IF(B27=$X$6,IF(F27<101,$AF$6,$AG$6),IF(B27=$X$7,IF(F27<101,$AF$7,$AG$7),IF(B27=$X$8,IF(F27<101,$AF$8,$AG$8),IF(B27=$X$9,IF(F27<101,$AF$9,$AG$9)))))))))))) | H27: =IF(LEN(D27)=0,"",IF(B27=$X$3,IF(F27*G27<$Y$3,$Y$3,F27*G27),IF(B27=$X$4,IF(F27*G27<$Y$4,$Y$4,F27*G27),IF(B27=$X$5,IF(F27*G27<$Y$5,$Y$5,F27*G27),IF(B27=$X$6,IF(F27*G27<$Y$6,$Y$6,F27*G27),IF(B27=$X$7,IF(F27*G27<$Y$7,$Y$7,F27*G27),IF(B27=$X$8,IF(F27*G27<$Y$8,$Y$8,F27*G27),IF(B27=$X$9,IF(F27*G27<$Y$9,$Y$9,F27*G27)))))))))
A28: 6 | F28: =IF(LEN(C28)=0,"",ROUNDUP(E28*D28*C28,0)) | G28: =IF(LEN(B28)=0,"",IF($H$9=$W$2,IF(B28=$X$3,IF(F28<51,$Z$3,IF(F28>100,$AB$3,$AA$3)),IF(B28=$X$4,IF(F28<51,$Z$4,IF(F28>100,$AB$4,$AA$4)),IF(B28=$X$5,IF(F28<51,$Z$5,IF(F28>100,$AB$5,$AA$5)),IF(B28=$X$6,IF(F28<51,$Z$6,IF(F28>100,$AB$6,$AA$6)),IF(B28=$X$7,IF(F28<51,$Z$7,IF(F28>100,$AB$7,$AA$7)),IF(B28=$X$8,IF(F28<51,$Z$8,IF(F28>100,$AB$8,$AA$8)),IF(B28=$X$9,IF(F28<51,$Z$9,IF(F28>100,$AB$9,$AA$9))))))))),IF($H$9=$W$3,IF(B28=$X$3,IF(F28<51,$AC$3,IF(F28>100,$AE$3,$AD$3)),IF(B28=$X$4,IF(F28<51,$AC$4,IF(F28>100,$AE$4,$AD$4)),IF(B28=$X$5,IF(F28<51,$AC$5,IF(F28>100,$AE$5,$AD$5)),IF(B28=$X$6,IF(F28<51,$AC$6,IF(F28>100,$AE$6,$AD$6)),IF(B28=$X$7,IF(F28<51,$AC$7,IF(F28>100,$AE$7,$AD$7)),IF(B28=$X$8,IF(F28<51,$AC$8,IF(F28>100,$AE$8,$AD$8)),IF(B28=$X$9,IF(F28<51,$AC$9,IF(F28>100,$AE$9,$AD$9))))))))),IF($H$9=$W$4,IF(B28=$X$3,IF(F28<101,$AF$3,$AG$3),IF(B28=$X$4,IF(F28<101,$AF$4,$AG$4),IF(B28=$X$5,IF(F28<101,$AF$5,$AG$5),IF(B28=$X$6,IF(F28<101,$AF$6,$AG$6),IF(B28=$X$7,IF(F28<101,$AF$7,$AG$7),IF(B28=$X$8,IF(F28<101,$AF$8,$AG$8),IF(B28=$X$9,IF(F28<101,$AF$9,$AG$9)))))))))))) | H28: =IF(LEN(D28)=0,"",IF(B28=$X$3,IF(F28*G28<$Y$3,$Y$3,F28*G28),IF(B28=$X$4,IF(F28*G28<$Y$4,$Y$4,F28*G28),IF(B28=$X$5,IF(F28*G28<$Y$5,$Y$5,F28*G28),IF(B28=$X$6,IF(F28*G28<$Y$6,$Y$6,F28*G28),IF(B28=$X$7,IF(F28*G28<$Y$7,$Y$7,F28*G28),IF(B28=$X$8,IF(F28*G28<$Y$8,$Y$8,F28*G28),IF(B28=$X$9,IF(F28*G28<$Y$9,$Y$9,F28*G28)))))))))
G29: Sub-Total | H29: =SUM(H23:H28) -> 0
A31: DESCRIPCIÓN DEL TRABAJO
A32: Soporte: | E32: Plantilla Cliente:
A34: TERMINACIONES
A35: Soporte: | C35: Observaciones:
A36: Medida Vivo:
A37: Costura:
A38: Tamaño Bolsillo:
A39: Tipo de Corte:
A40: Ojetillos
A41: Remaches
A42: Tipo Travesaño: | C42: Valor de las Terminaciones:

Sheet OP cajas
D1: Nº OP | E1: ='Nota de venta'!H1 -> 0
D4: ='Nota de venta'!C112 -> 0
D6: ='Nota de venta'!C6 -> 0
G7: Ingreso | H7: 0
G8: Entrega | H8: 0
A9: Cantidad | B9: Producto | C9: Ancho | D9: Alto | E9: materiales | F9: tipo | G9: cantidad x caja | H9: cantidad total
A10: =+'NV CAJAS (BL)'!D16 -> 0 | B10: =+'NV CAJAS (BL)'!C16 -> 0 | C10: ='Nota de venta'!E10 -> 0 | D10: ='Nota de venta'!F10 -> 0 | E10: Perfil | F10: =+'NV CAJAS (BL)'!Y16 | G10: =+'NV CAJAS (BL)'!T16/I10 -> 0 | H10: =+G10*A10 -> 0 | I10: 6 | J10: ml x perfil
E11: Traseras | F11: =+'NV CAJAS (BL)'!V16 | G11: =+(C10*D10)/I11 -> 0 | H11: =+G11*A10+0.5 -> 0.5 | I11: =1.22*2.44 -> 2.9768 | J11: m2 x trasera
E12: Luces 1 | F12: =+'NV CAJAS (BL)'!H16 | G12: =+'NV CAJAS (BL)'!P16 -> #N/A | H12: =+G12*A10 -> #N/A
A13: OBS: | E13: Luces 2 | F13: =+'NV CAJAS (BL)'!L16 -> sin luces | G13: =+'NV CAJAS (BL)'!Q16 -> 0 | H13: =+G13*A10 -> 0
E14: FP | F14: =+'NV CAJAS (BL)'!W16 -> FALSE | G14: 1 | H14: =+G14*A10 -> 0 | K14: ='NV CAJAS (BL)'!X16 -> #N/A
A15: =+'NV CAJAS (BL)'!D17 -> 0 | B15: =+'NV CAJAS (BL)'!C17 -> 0 | C15: ='Nota de venta'!E11 -> 0 | D15: ='Nota de venta'!F11 -> 0 | E15: Perfil | F15: =+'NV CAJAS (BL)'!Y17 | G15: =+'NV CAJAS (BL)'!T17/I15 -> 0 | H15: =+G15*A15 -> 0 | I15: 6 | J15: ml x perfil
E16: Traseras | F16: =+'NV CAJAS (BL)'!V17 | G16: =+(C15*D15)/I16 -> 0 | H16: =+G16*A15+0.5 -> 0.5 | I16: =1.22*2.44 -> 2.9768 | J16: m2 x trasera
E17: Luces 1 | F17: =+'NV CAJAS (BL)'!H17 | G17: =+'NV CAJAS (BL)'!P17 -> #N/A | H17: =+G17*A15 -> #N/A
A18: OBS: | E18: Luces 2 | F18: =+'NV CAJAS (BL)'!L17 -> sin luces | G18: =+'NV CAJAS (BL)'!Q17 -> 0 | H18: =+G18*A15 -> 0
E19: FP | F19: =+'NV CAJAS (BL)'!W17 -> FALSE | G19: 1 | H19: =+G19*A15 -> 0 | K19: ='NV CAJAS (BL)'!X17 -> #N/A
A20: =+'NV CAJAS (BL)'!D18 -> 0 | B20: =+'NV CAJAS (BL)'!C18 -> 0 | C20: ='Nota de venta'!E12 -> 0 | D20: ='Nota de venta'!F12 -> 0 | E20: Perfil | F20: =+'NV CAJAS (BL)'!Y18 | G20: =+'NV CAJAS (BL)'!T18/I20 -> 0 | H20: =+G20*A20 -> 0 | I20: 6 | J20: ml x perfil
E21: Traseras | F21: =+'NV CAJAS (BL)'!V18 | G21: =+(C20*D20)/I21 -> 0 | H21: =+G21*A20+0.5 -> 0.5 | I21: =1.22*2.44 -> 2.9768 | J21: m2 x trasera
E22: Luces 1 | F22: =+'NV CAJAS (BL)'!H18 | G22: =+'NV CAJAS (BL)'!P18 -> #N/A | H22: =+G22*A20 -> #N/A
A23: OBS: | E23: Luces 2 | F23: =+'NV CAJAS (BL)'!L18 -> sin luces | G23: =+'NV CAJAS (BL)'!Q18 -> 0 | H23: =+G23*A20 -> 0
E24: FP | F24: =+'NV CAJAS (BL)'!W18 -> FALSE | G24: 1 | H24: =+G24*A20 -> 0 | K24: ='NV CAJAS (BL)'!X18 -> #N/A
A25: =+'NV CAJAS (BL)'!D19 -> 0 | B25: =+'NV CAJAS (BL)'!C19 -> 0 | C25: ='Nota de venta'!E13 -> 0 | D25: ='Nota de venta'!F13 -> 0 | E25: Perfil | F25: =+'NV CAJAS (BL)'!Y19 | G25: =+'NV CAJAS (BL)'!T19/I25 -> 0 | H25: =+G25*A25 -> 0 | I25: 6 | J25: ml x perfil
E26: Traseras | F26: =+'NV CAJAS (BL)'!V19 | G26: =+(C25*D25)/I26 -> 0 | H26: =+G26*A25+0.5 -> 0.5 | I26: =1.22*2.44 -> 2.9768 | J26: m2 x trasera
E27: Luces 1 | F27: =+'NV CAJAS (BL)'!H19 | G27: =+'NV CAJAS (BL)'!P19 -> #N/A | H27: =+G27*A25 -> #N/A
A28: OBS: | E28: Luces 2 | F28: =+'NV CAJAS (BL)'!L19 -> sin luces | G28: =+'NV CAJAS (BL)'!Q19 -> 0 | H28: =+G28*A25 -> 0
E29: FP | F29: =+'NV CAJAS (BL)'!W19 -> FALSE | G29: 1 | H29: =+G29*A25 -> 0 | K29: ='NV CAJAS (BL)'!X19 -> #N/A

Sheet NV CAJAS (BL)
AG2: Fuente | AK2: Despachos e instalaciones | AV2: lista productos | AY2: Tela | AZ2: ancho | BA2: valor m2 | BC2: textil entre 0,1 y 0,5 m2 | BG2: =2.56*2000 -> 5120
AG3: valor mínimo 1 m2 | AH3: 0 | AK3: Sin despacho ni instalación | AV3: textil backlight | AY3: popelina backlight 155 | AZ3: 1.53 | BA3: 27000 | BC3: textil entre 0,51 y 1 m2 | BD3: 6500
AG4: productor 1<10 M2 | AH4: 0 | AK4: con despacho a un punto dentro de Santiago | AY4: popelina backlight 310 | AZ4: 3.08 | BA4: 31000 | BC4: textil entre 1,01 y 5 m2 | BD4: 9000
B5: Fecha: | C5: =Cotización!C3 -> 0 | AG5: productor 10<20m2 | AH5: 0.05 | AK5: con instalación | AY5: pearl 155 | AZ5: 1.53 | BA5: 22000 | BC5: textil entre 5,01 y 10 m2 | BD5: 10000
AG6: productor 21 <50m2 | AH6: 0.1 | AY6: pearl 310 | AZ6: 3.08 | BA6: 31000 | BC6: más de 10 m2 | BD6: 11000
B7: DATOS CLIENTE | AG7: prouctor > 50 m2 | AH7: 0.2 | AY7: pearl 160 hp | AZ7: 1.6 | BA7: 22000 | BC7: sin terminaciones | BD7: 0
B8: Contacto: | C8: ='Nota de venta'!C5 -> 0 | H8: ID trabajo:
B9: Empresa: | C9: ='Nota de venta'!C6 -> 0
D13: REQUERIMIENTO CAJAS LUZ LED | AQ13: Despachos e instalaciones | AR13: Estructuras | BA13: PRODUCTOS | BC13: lista productos | BD13: nick | BE13: TIPO DE LUZ | BF13: medida | BG13: precio venta | BH13: watts | BI13: max ancho | BJ13: costo s/iva | BM13: Terminaciones | BN13: ML | BP13: complementos | BQ13: valor m2 | BT13: FUENTES DE PODER | BU13: PRECIO VENTA | BV13: costos s/iva | BW13: WATSS
C14: Ç | F14: ESTRUCTURAS | AQ14: Sin despacho ni instalación | AR14: trovicel m2 | BA14: caja frameless 12 doble | BL14: ARMADO MINIMO | BM14: armado mínimo <1 | BN14: 10000 | BQ14: M2 | BS14: 600 | BT14: FP 600 watts-24v- MEAN WELL | BU14: =+BV14*1.8 -> 110102.4 | BV14: 61168 | BW14: 600
A15: item | C15: Producto nro | D15: Cantidad | E15: lado + largo | F15: lado + corto | G15: Columna1 | H15: led 1 | I15: Ancho led 1 | J15: # led 1 x lado | K15: ml x cubrir | L15: led 2 | M15: Ancho led 2 | N15: # led 2 x lado | O15: lados a cubrir | P15: luces 1 x caja | Q15: luces 2 x caja | R15: luces 1 totales | S15: luces 2 totales | T15: mts lineales x caja | U15: armado | V15: traseras | W15: FP | X15: WATTS | Y15: tipo perfil | Z15: mts lineales totales | AC15: cant traseras | AD15: cant FP | AE15: CONECTORES/ENCHUFES | AF15: CABLE MTS CABLE | AG15: tipo led 1 | AH15: tipo led 2 | AP15: con despacho a un punto dentro de Santiago | AQ15: alucobond m2 | BA15: caja frameless 10 doble | BD15: Basic 5 focos | BE15: Basic led lateral 5F 5K , 53 cms max 500mm | BF15: 0.53 | BG15: =BJ15*1.5 -> 14506.5 | BH15: 15 | BI15: 0.5 | BJ15: 9671 | BK15: 5f 5k | BL15: ARMADO SIMPLE | BM15: armado simple 1=>4 ml | BN15: 7000 | BP15: trovicel 122 | BQ15: 5000 | BS15: 450 | BT15: FP 450 watts-24v- MEAN WELL | BU15: =+BV15*1.8 -> 88471.8 | BV15: 49151 | BW15: 450
A16: A | D16: ='Nota de venta'!G10 -> 0 | E16: =IF('Nota de venta'!F10>'Nota de venta'!E10,'Nota de venta'!F10,'Nota de venta'!E10) -> 0 | F16: =IF('Nota de venta'!F10<'Nota de venta'!E10,'Nota de venta'!F10,'Nota de venta'!E10) -> 0 | H16: =IF(ISTEXT(Tabla1[[#This Row],[Producto nro]]),IF(OR(Tabla1[[#This Row],[Producto nro]]="PERFIL 60 MM",Tabla1[[#This Row],[lado + corto]]>1.4),"Malla Front Led 50x150 5k","Led Lateral Actilum M12 -6k, 90 cms max 1000mm"),"") | I16: =VLOOKUP(H16,$BE$15:$BG$29,2,FALSE) -> #N/A | J16: =TRUNC((E16-0.03)/I16) -> #N/A | K16: =E16-(J16*I16) -> #N/A | L16: =IF(Tabla1[[#This Row],[Producto nro]]="PERFIL 60 MM","sin luces","sin luces") -> sin luces | M16: =VLOOKUP(L16,$BE$15:$BG$29,$R26,FALSE) -> 0 | N16: =IF(M16=0,0,TRUNC(K16/M16)) -> 0 | O16: =IF(Tabla1[[#This Row],[Producto nro]]="PERFIL 60 MM",1, IF(Tabla1[[#This Row],[led 1]]="",0, IF(Tabla1[[#This Row],[led 1]]="Led Lateral Actilum M12 -6k, 90 cms max 1000mm", IF(Tabla1[[#This Row],[lado + corto]]<0.8,1, IF(Tabla1[[#This Row],[lado + corto]]<140,2,0)),1))) -> 0 | P16: =+$J16*$O16 -> #N/A | Q16: =+$N16*$O16 -> 0 | R16: =+P16*D16 -> #N/A | S16: =+Q16*D16 -> 0 | T16: =+E16*2+F16*2 -> 0 | U16: =IF(T16=0,"",IF(T16<1,"ARMADO MINIMO",IF(T16<=4,"ARMADO SIMPLE",IF(T16<=6,"ARMADO MEDIO",IF(T16<8,"ARMADO COMPLEJO","ARMADO JUMBO"))))) | V16: =IF(AND(Y16="",H16=""),"",IF(ISNUMBER(FIND("DOBLE",Y16)),"sin traseras",IF(OR(H16="Malla Front Led 50x150 5k",H16="malla front led 12v 6000 k"),"alucobond 122x244","trovicel 122"))) | W16: =IF(ISNUMBER(Tabla1[[#This Row],[WATTS]]), IF(Tabla1[[#This Row],[WATTS]]<35,VLOOKUP(35,$BS$14:$BT$22,2,FALSE), IF(Tabla1[[#This Row],[WATTS]]<50,VLOOKUP(50,$BS$14:$BT$22,2,FALSE), IF(Tabla1[[#This Row],[WATTS]]<75,VLOOKUP(75,$BS$14:$BT$22,2,FALSE), IF(Tabla1[[#This Row],[WATTS]]<100,VLOOKUP(100,$BS$14:$BT$22,2,FALSE), IF(Tabla1[[#This Row],[WATTS]]<150,VLOOKUP(150,$BS$14:$BT$22,2,FALSE), IF(Tabla1[[#This Row],[WATTS]]<200,VLOOKUP(200,$BS$14:$BT$22,2,FALSE), IF(Tabla1[[#This Row],[WATTS]]<350,VLOOKUP(350,$BS$14:$BT$22,2,FALSE), IF(Tabla1[[#This Row],[WATTS]]<=400,VLOOKUP(450,$BS$14:$BT$22,2,FALSE), "2 FP 350 watts - 24v MEAN WELL"))))))))) -> FALSE | X16: =+VLOOKUP(Tabla1[[#This Row],[led 1]],$BE$15:$BI$26,AA16,FALSE)*Tabla1[[#This Row],[luces 1 x caja]]+VLOOKUP(Tabla1[[#This Row],[led 2]],$BE$15:$BI$26,AA16,FALSE)*Tabla1[[#This Row],[luces 2 x caja]] -> #N/A | Y16: =IF(C16="","",IF(ISNUMBER(FIND("6",C16)),"PERFIL 60 MM",IF(ISNUMBER(FIND("8",C16)),"PERFIL 80 MM", IF(ISNUMBER(FIND("10",C16)),IF(ISNUMBER(FIND("doble",C16)), "PERFIL 100 MM DOBLE", "PERFIL 100 MM SIMPLE"), "PERFIL 120 MM SIMPLE")))) | Z16: =Tabla1[[#This Row],[mts lineales x caja]]*Tabla1[[#This Row],[Cantidad]] -> 0 | AA16: 4 | AB16: 7 | AC16: =+E16*F16/2 -> 0 | AD16: =VLOOKUP(W16,$BT$14:$BW$22,$T26,FALSE)/X16 -> #N/A | AE16: =+D16*1 -> 0 | AF16: =1.5*D16 -> 0 | AG16: =VLOOKUP(H16,$BE$15:$BK$23,AB16,FALSE) -> #N/A | AH16: =VLOOKUP(L16,$BE$15:$BK$23,AB16,FALSE) -> 0 | AP16: con instalación | AQ16: fuente 24v 75 watts | BA16: caja frameless 10 simple | BD16: Basic 3 focos | BE16: Basic led lateral 3F 5K, 33 cms max 500mm | BF16: 0.33 | BG16: =+BJ16*1.5 -> 11196 | BH16: 9 | BI16: 0.5 | BJ16: 7464 | BK16: 3f 5k | BL16: ARMADO MEDIO | BM16: armado medio 4 > 6 ml | BN16: 6000 | BP16: alucobond 122x244 | BQ16: =10400*1.35 -> 14040 | BS16: 350 | BT16: FP 350 watts - 24v MEAN WELL | BU16: =+BV16*1.8 -> 40374 | BV16: 22430 | BW16: 350
A17: B | D17: ='Nota de venta'!G11 -> 0 | E17: =IF('Nota de venta'!F11>'Nota de venta'!E11,'Nota de venta'!F11,'Nota de venta'!E11) -> 0 | F17: =IF('Nota de venta'!F11<'Nota de venta'!E11,'Nota de venta'!F11,'Nota de venta'!E11) -> 0 | H17: =IF(ISTEXT(Tabla1[[#This Row],[Producto nro]]),IF(OR(Tabla1[[#This Row],[Producto nro]]="PERFIL 60 MM",Tabla1[[#This Row],[lado + corto]]>1.4),"Malla Front Led 50x150 5k","Led Lateral Actilum M12 -6k, 90 cms max 1000mm"),"") | I17: =VLOOKUP(H17,$BE$15:$BG$29,$R27,FALSE) -> #N/A | J17: =TRUNC((E17-0.03)/I17) -> #N/A | K17: =E17-(J17*I17) -> #N/A | L17: =IF(Tabla1[[#This Row],[Producto nro]]="PERFIL 60 MM","sin luces","sin luces") -> sin luces | M17: =VLOOKUP(L17,$BE$15:$BG$29,$R27,FALSE) -> 0 | N17: =IF(M17=0,0,TRUNC(K17/M17)) -> 0 | O17: =IF(Tabla1[[#This Row],[Producto nro]]="PERFIL 60 MM",1, IF(Tabla1[[#This Row],[led 1]]="",0, IF(Tabla1[[#This Row],[led 1]]="Led Lateral Actilum M12 -6k, 90 cms max 1000mm", IF(Tabla1[[#This Row],[lado + corto]]<0.8,1, IF(Tabla1[[#This Row],[lado + corto]]<140,2,0)),1))) -> 0 | P17: =+$J17*$O17 -> #N/A | Q17: =+$N17*$O17 -> 0 | R17: =+P17*D17 -> #N/A | S17: =+Q17*D17 -> 0 | T17: =+E17*2+F17*2 -> 0 | U17: =IF(T17=0,"",IF(T17<1,"ARMADO MINIMO",IF(T17<=4,"ARMADO SIMPLE",IF(T17<=6,"ARMADO MEDIO",IF(T17<8,"ARMADO COMPLEJO","ARMADO JUMBO"))))) | V17: =IF(AND(Y17="",H17=""),"",IF(ISNUMBER(FIND("DOBLE",Y17)),"sin traseras",IF(OR(H17="Malla Front Led 50x150 5k",H17="malla front led 12v 6000 k"),"alucobond 122x244","trovicel 122"))) | W17: =IF(ISNUMBER(Tabla1[[#This Row],[WATTS]]), IF(Tabla1[[#This Row],[WATTS]]<35,VLOOKUP(35,$BS$14:$BT$22,2,FALSE), IF(Tabla1[[#This Row],[WATTS]]<50,VLOOKUP(50,$BS$14:$BT$22,2,FALSE), IF(Tabla1[[#This Row],[WATTS]]<75,VLOOKUP(75,$BS$14:$BT$22,2,FALSE), IF(Tabla1[[#This Row],[WATTS]]<100,VLOOKUP(100,$BS$14:$BT$22,2,FALSE), IF(Tabla1[[#This Row],[WATTS]]<150,VLOOKUP(150,$BS$14:$BT$22,2,FALSE), IF(Tabla1[[#This Row],[WATTS]]<200,VLOOKUP(200,$BS$14:$BT$22,2,FALSE), IF(Tabla1[[#This Row],[WATTS]]<350,VLOOKUP(350,$BS$14:$BT$22,2,FALSE), IF(Tabla1[[#This Row],[WATTS]]<=400,VLOOKUP(450,$BS$14:$BT$22,2,FALSE), "2 FP 350 watts - 24v MEAN WELL"))))))))) -> FALSE | X17: =+VLOOKUP(Tabla1[[#This Row],[led 1]],$BE$15:$BI$26,AA17,FALSE)*Tabla1[[#This Row],[luces 1 x caja]]+VLOOKUP(Tabla1[[#This Row],[led 2]],$BE$15:$BI$26,AA17,FALSE)*Tabla1[[#This Row],[luces 2 x caja]] -> #N/A | Y17: =IF(C17="","",IF(ISNUMBER(FIND("6",C17)),"PERFIL 60 MM",IF(ISNUMBER(FIND("8",C17)),"PERFIL 80 MM", IF(ISNUMBER(FIND("10",C17)),IF(ISNUMBER(FIND("doble",C17)), "PERFIL 100 MM DOBLE", "PERFIL 100 MM SIMPLE"), "PERFIL 120 MM SIMPLE")))) | Z17: =Tabla1[[#This Row],[mts lineales x caja]]*Tabla1[[#This Row],[Cantidad]] -> 0 | AA17: 4 | AB17: 7 | AC17: =+E17*F17/2 -> 0 | AD17: =VLOOKUP(W17,$BT$14:$BW$22,$T27,FALSE)/X17 -> #N/A | AE17: =+D17*1 -> 0 | AF17: =1.5*D17 -> 0 | AG17: =VLOOKUP(H17,$BE$15:$BK$23,AB17,FALSE) -> #N/A | AH17: =VLOOKUP(L17,$BE$15:$BK$23,AC17,FALSE) -> #VALUE! | AQ17: fuente 24 v 100 watts | BA17: caja frameless 8 simple | BD17: M12 | BE17: Led Lateral Actilum M12 -6k, 90 cms max 1000mm | BF17: 0.6 | BG17: =+BJ17*1.4 -> 25488.4 | BH17: 21 | BI17: 1 | BJ17: 18206 | BK17: M12 | BL17: ARMADO COMPLEJO | BM17: armado complejo 6 > 8 ml | BN17: 5000 | BS17: 200 | BT17: FP 200 watts- 24v MEAN WELL | BU17: =+BV17*1.8 -> 32295.6 | BV17: 17942 | BW17: 200
A18: C | D18: ='Nota de venta'!G12 -> 0 | E18: =IF('Nota de venta'!F12>'Nota de venta'!E12,'Nota de venta'!F12,'Nota de venta'!E12) -> 0 | F18: =IF('Nota de venta'!F12<'Nota de venta'!E12,'Nota de venta'!F12,'Nota de venta'!E12) -> 0 | H18: =IF(ISTEXT(Tabla1[[#This Row],[Producto nro]]),IF(OR(Tabla1[[#This Row],[Producto nro]]="PERFIL 60 MM",Tabla1[[#This Row],[lado + corto]]>1.4),"Malla Front Led 50x150 5k","Led Lateral Actilum M12 -6k, 90 cms max 1000mm"),"") | I18: =VLOOKUP(H18,$BE$15:$BG$29,$R28,FALSE) -> #N/A | J18: =TRUNC((E18-0.03)/I18) -> #N/A | K18: =E18-(J18*I18) -> #N/A | L18: =IF(Tabla1[[#This Row],[Producto nro]]="PERFIL 60 MM","sin luces","sin luces") -> sin luces | M18: =VLOOKUP(L18,$BE$15:$BG$29,$R28,FALSE) -> 0 | N18: =IF(M18=0,0,TRUNC(K18/M18)) -> 0 | O18: =IF(Tabla1[[#This Row],[Producto nro]]="PERFIL 60 MM",1, IF(Tabla1[[#This Row],[led 1]]="",0, IF(Tabla1[[#This Row],[led 1]]="Led Lateral Actilum M12 -6k, 90 cms max 1000mm", IF(Tabla1[[#This Row],[lado + corto]]<0.8,1, IF(Tabla1[[#This Row],[lado + corto]]<140,2,0)),1))) -> 0 | P18: =+$J18*$O18 -> #N/A | Q18: =+$N18*$O18 -> 0 | R18: =+P18*D18 -> #N/A | S18: =+Q18*D18 -> 0 | T18: =+E18*2+F18*2 -> 0 | U18: =IF(T18=0,"",IF(T18<1,"ARMADO MINIMO",IF(T18<=4,"ARMADO SIMPLE",IF(T18<=6,"ARMADO MEDIO",IF(T18<8,"ARMADO COMPLEJO","ARMADO JUMBO"))))) | V18: =IF(AND(Y18="",H18=""),"",IF(ISNUMBER(FIND("DOBLE",Y18)),"sin traseras",IF(OR(H18="Malla Front Led 50x150 5k",H18="malla front led 12v 6000 k"),"alucobond 122x244","trovicel 122"))) | W18: =IF(ISNUMBER(Tabla1[[#This Row],[WATTS]]), IF(Tabla1[[#This Row],[WATTS]]<35,VLOOKUP(35,$BS$14:$BT$22,2,FALSE), IF(Tabla1[[#This Row],[WATTS]]<50,VLOOKUP(50,$BS$14:$BT$22,2,FALSE), IF(Tabla1[[#This Row],[WATTS]]<75,VLOOKUP(75,$BS$14:$BT$22,2,FALSE), IF(Tabla1[[#This Row],[WATTS]]<100,VLOOKUP(100,$BS$14:$BT$22,2,FALSE), IF(Tabla1[[#This Row],[WATTS]]<150,VLOOKUP(150,$BS$14:$BT$22,2,FALSE), IF(Tabla1[[#This Row],[WATTS]]<200,VLOOKUP(200,$BS$14:$BT$22,2,FALSE), IF(Tabla1[[#This Row],[WATTS]]<350,VLOOKUP(350,$BS$14:$BT$22,2,FALSE), IF(Tabla1[[#This Row],[WATTS]]<=400,VLOOKUP(450,$BS$14:$BT$22,2,FALSE), "2 FP 350 watts - 24v MEAN WELL"))))))))) -> FALSE | X18: =+VLOOKUP(Tabla1[[#This Row],[led 1]],$BE$15:$BI$26,AA18,FALSE)*Tabla1[[#This Row],[luces 1 x caja]]+VLOOKUP(Tabla1[[#This Row],[led 2]],$BE$15:$BI$26,AA18,FALSE)*Tabla1[[#This Row],[luces 2 x caja]] -> #N/A | Y18: =IF(C18="","",IF(ISNUMBER(FIND("6",C18)),"PERFIL 60 MM",IF(ISNUMBER(FIND("8",C18)),"PERFIL 80 MM", IF(ISNUMBER(FIND("10",C18)),IF(ISNUMBER(FIND("doble",C18)), "PERFIL 100 MM DOBLE", "PERFIL 100 MM SIMPLE"), "PERFIL 120 MM SIMPLE")))) | Z18: =Tabla1[[#This Row],[mts lineales x caja]]*Tabla1[[#This Row],[Cantidad]] -> 0 | AA18: 4 | AB18: 7 | AC18: =+E18*F18/2 -> 0 | AD18: =VLOOKUP(W18,$BT$14:$BW$22,$T28,FALSE)/X18 -> #N/A | AE18: =+D18*1 -> 0 | AF18: =1.5*D18 -> 0 | AG18: =VLOOKUP(H18,$BE$15:$BK$23,AB18,FALSE) -> #N/A | AH18: =VLOOKUP(L18,$BE$15:$BK$23,AC18,FALSE) -> #VALUE! | AQ18: fuente 24v 150 watts | BA18: caja frameless 6 simple | BD18: M9 | BE18: Led Lateral Actilum M9 -6k, 52 cms max 700mm | BF18: 0.52 | BG18: =+BJ18*1.3 -> 23268.7 | BH18: 15 | BI18: 0.75 | BJ18: 17899 | BK18: M9 | BL18: ARMADO JUMBO | BM18: armado jumbo > 8 ml | BN18: 4500 | BP18: sin traseras | BQ18: 0 | BS18: 150 | BT18: FP 150 watts- 24v MEAN WELL | BU18: =+BV18*1.7 -> 29088.7 | BV18: 17111 | BW18: 150
A19: D | D19: ='Nota de venta'!G13 -> 0 | E19: =IF('Nota de venta'!F13>'Nota de venta'!E13,'Nota de venta'!F13,'Nota de venta'!E13) -> 0 | F19: =IF('Nota de venta'!F13<'Nota de venta'!E13,'Nota de venta'!F13,'Nota de venta'!E13) -> 0 | H19: =IF(ISTEXT(Tabla1[[#This Row],[Producto nro]]),IF(OR(Tabla1[[#This Row],[Producto nro]]="PERFIL 60 MM",Tabla1[[#This Row],[lado + corto]]>1.4),"Malla Front Led 50x150 5k","Led Lateral Actilum M12 -6k, 90 cms max 1000mm"),"") | I19: =VLOOKUP(H19,$BE$15:$BG$29,$R29,FALSE) -> #N/A | J19: =TRUNC((E19-0.03)/I19) -> #N/A | K19: =E19-(J19*I19) -> #N/A | L19: =IF(Tabla1[[#This Row],[Producto nro]]="PERFIL 60 MM","sin luces","sin luces") -> sin luces | M19: =VLOOKUP(L19,$BE$15:$BG$29,$R29,FALSE) -> 0 | N19: =IF(M19=0,0,TRUNC(K19/M19)) -> 0 | O19: =IF(Tabla1[[#This Row],[Producto nro]]="PERFIL 60 MM",1, IF(Tabla1[[#This Row],[led 1]]="",0, IF(Tabla1[[#This Row],[led 1]]="Led Lateral Actilum M12 -6k, 90 cms max 1000mm", IF(Tabla1[[#This Row],[lado + corto]]<0.8,1, IF(Tabla1[[#This Row],[lado + corto]]<140,2,0)),1))) -> 0 | P19: =+$J19*$O19 -> #N/A | Q19: =+$N19*$O19 -> 0 | R19: =+P19*D19 -> #N/A | S19: =+Q19*D19 -> 0 | T19: =+E19*2+F19*2 -> 0 | U19: =IF(T19=0,"",IF(T19<1,"ARMADO MINIMO",IF(T19<=4,"ARMADO SIMPLE",IF(T19<=6,"ARMADO MEDIO",IF(T19<8,"ARMADO COMPLEJO","ARMADO JUMBO"))))) | V19: =IF(AND(Y19="",H19=""),"",IF(ISNUMBER(FIND("DOBLE",Y19)),"sin traseras",IF(OR(H19="Malla Front Led 50x150 5k",H19="malla front led 12v 6000 k"),"alucobond 122x244","trovicel 122"))) | W19: =IF(ISNUMBER(Tabla1[[#This Row],[WATTS]]), IF(Tabla1[[#This Row],[WATTS]]<35,VLOOKUP(35,$BS$14:$BT$22,2,FALSE), IF(Tabla1[[#This Row],[WATTS]]<50,VLOOKUP(50,$BS$14:$BT$22,2,FALSE), IF(Tabla1[[#This Row],[WATTS]]<75,VLOOKUP(75,$BS$14:$BT$22,2,FALSE), IF(Tabla1[[#This Row],[WATTS]]<100,VLOOKUP(100,$BS$14:$BT$22,2,FALSE), IF(Tabla1[[#This Row],[WATTS]]<150,VLOOKUP(150,$BS$14:$BT$22,2,FALSE), IF(Tabla1[[#This Row],[WATTS]]<200,VLOOKUP(200,$BS$14:$BT$22,2,FALSE), IF(Tabla1[[#This Row],[WATTS]]<350,VLOOKUP(350,$BS$14:$BT$22,2,FALSE), IF(Tabla1[[#This Row],[WATTS]]<=400,VLOOKUP(450,$BS$14:$BT$22,2,FALSE), "2 FP 350 watts - 24v MEAN WELL"))))))))) -> FALSE | X19: =+VLOOKUP(Tabla1[[#This Row],[led 1]],$BE$15:$BI$26,AA19,FALSE)*Tabla1[[#This Row],[luces 1 x caja]]+VLOOKUP(Tabla1[[#This Row],[led 2]],$BE$15:$BI$26,AA19,FALSE)*Tabla1[[#This Row],[luces 2 x caja]] -> #N/A | Y19: =IF(C19="","",IF(ISNUMBER(FIND("6",C19)),"PERFIL 60 MM",IF(ISNUMBER(FIND("8",C19)),"PERFIL 80 MM", IF(ISNUMBER(FIND("10",C19)),IF(ISNUMBER(FIND("doble",C19)), "PERFIL 100 MM DOBLE", "PERFIL 100 MM SIMPLE"), "PERFIL 120 MM SIMPLE")))) | Z19: =Tabla1[[#This Row],[mts lineales x caja]]*Tabla1[[#This Row],[Cantidad]] -> 0 | AA19: 4 | AB19: 7 | AC19: =+E19*F19/2 -> 0 | AD19: =VLOOKUP(W19,$BT$14:$BW$22,$T29,FALSE)/X19 -> #N/A | AE19: =+D19*1 -> 0 | AF19: =1.5*D19 -> 0 | AG19: =VLOOKUP(H19,$BE$15:$BK$23,AB19,FALSE) -> #N/A | AH19: =VLOOKUP(L19,$BE$15:$BK$23,AC19,FALSE) -> #VALUE! | AQ19: fuente 24v 200 watts | BA19: fuente de poder | BD19: M6 | BE19: Led lateral Actilum M6 6k, 35 cms max 700mm | BF19: 0.35 | BG19: =+BJ19*1.3 -> 15512.9 | BH19: 10 | BI19: 0.75 | BJ19: 11933 | BK19: M6 | BM19: armado y electropintado mínimo <1 | BN19: 10000 | BS19: 100 | BT19: FP 100 watts- 24v MEAN WELL | BU19: =+BV19*1.7 -> 18793.5 | BV19: 11055 | BW19: 100
D20: ='Nota de venta'!G14 -> 0 | E20: =IF('Nota de venta'!F14>'Nota de venta'!E14,'Nota de venta'!F14,'Nota de venta'!E14) -> 0 | F20: =IF('Nota de venta'!F14<'Nota de venta'!E14,'Nota de venta'!F14,'Nota de venta'!E14) -> 0 | H20: =IF(ISTEXT(Tabla1[[#This Row],[Producto nro]]),IF(OR(Tabla1[[#This Row],[Producto nro]]="PERFIL 60 MM",Tabla1[[#This Row],[lado + corto]]>1.4),"Malla Front Led 50x150 5k","Led Lateral Actilum M12 -6k, 90 cms max 1000mm"),"") | I20: =VLOOKUP(H20,$BE$15:$BG$29,$R30,FALSE) -> #N/A | J20: =TRUNC((E20-0.03)/I20) -> #N/A | K20: =E20-(J20*I20) -> #N/A | L20: =IF(Tabla1[[#This Row],[Producto nro]]="PERFIL 60 MM","sin luces","sin luces") -> sin luces | M20: =VLOOKUP(L20,$BE$15:$BG$29,$R30,FALSE) -> 0 | N20: =IF(M20=0,0,TRUNC(K20/M20)) -> 0 | O20: =IF(Tabla1[[#This Row],[Producto nro]]="PERFIL 60 MM",1, IF(Tabla1[[#This Row],[led 1]]="",0, IF(Tabla1[[#This Row],[led 1]]="Led Lateral Actilum M12 -6k, 90 cms max 1000mm", IF(Tabla1[[#This Row],[lado + corto]]<0.8,1, IF(Tabla1[[#This Row],[lado + corto]]<140,2,0)),1))) -> 0 | P20: =+$J20*$O20 -> #N/A | Q20: =+$N20*$O20 -> 0 | R20: =+P20*D20 -> #N/A | S20: =+Q20*D20 -> 0 | T20: =+E20*2+F20*2 -> 0 | U20: =IF(T20=0,"",IF(T20<1,"ARMADO MINIMO",IF(T20<=4,"ARMADO SIMPLE",IF(T20<=6,"ARMADO MEDIO",IF(T20<8,"ARMADO COMPLEJO","ARMADO JUMBO"))))) | V20: =IF(AND(Y20="",H20=""),"",IF(ISNUMBER(FIND("DOBLE",Y20)),"sin traseras",IF(OR(H20="Malla Front Led 50x150 5k",H20="malla front led 12v 6000 k"),"alucobond 122x244","trovicel 122"))) | W20: =IF(ISNUMBER(Tabla1[[#This Row],[WATTS]]), IF(Tabla1[[#This Row],[WATTS]]<35,VLOOKUP(35,$BS$14:$BT$22,2,FALSE), IF(Tabla1[[#This Row],[WATTS]]<50,VLOOKUP(50,$BS$14:$BT$22,2,FALSE), IF(Tabla1[[#This Row],[WATTS]]<75,VLOOKUP(75,$BS$14:$BT$22,2,FALSE), IF(Tabla1[[#This Row],[WATTS]]<100,VLOOKUP(100,$BS$14:$BT$22,2,FALSE), IF(Tabla1[[#This Row],[WATTS]]<150,VLOOKUP(150,$BS$14:$BT$22,2,FALSE), IF(Tabla1[[#This Row],[WATTS]]<200,VLOOKUP(200,$BS$14:$BT$22,2,FALSE), IF(Tabla1[[#This Row],[WATTS]]<350,VLOOKUP(350,$BS$14:$BT$22,2,FALSE), IF(Tabla1[[#This Row],[WATTS]]<=400,VLOOKUP(450,$BS$14:$BT$22,2,FALSE), "2 FP 350 watts - 24v MEAN WELL"))))))))) -> FALSE | X20: =+VLOOKUP(Tabla1[[#This Row],[led 1]],$BE$15:$BI$26,AA20,FALSE)*Tabla1[[#This Row],[luces 1 x caja]]+VLOOKUP(Tabla1[[#This Row],[led 2]],$BE$15:$BI$26,AA20,FALSE)*Tabla1[[#This Row],[luces 2 x caja]] -> #N/A | Y20: =IF(C20="","",IF(ISNUMBER(FIND("6",C20)),"PERFIL 60 MM",IF(ISNUMBER(FIND("8",C20)),"PERFIL 80 MM", IF(ISNUMBER(FIND("10",C20)),IF(ISNUMBER(FIND("doble",C20)), "PERFIL 100 MM DOBLE", "PERFIL 100 MM SIMPLE"), "PERFIL 120 MM SIMPLE")))) | Z20: =Tabla1[[#This Row],[mts lineales x caja]]*Tabla1[[#This Row],[Cantidad]] -> 0 | AA20: 4 | AB20: 7 | AC20: =+E20*F20/2 -> 0 | AD20: =VLOOKUP(W20,$BT$14:$BW$22,$T30,FALSE)/X20 -> #N/A | AE20: =+D20*1 -> 0 | AF20: =1.5*D20 -> 0 | AG20: =VLOOKUP(H20,$BE$15:$BK$23,AB20,FALSE) -> #N/A | AH20: =VLOOKUP(L20,$BE$15:$BK$23,AC20,FALSE) -> #VALUE! | AQ20: fuente 24v 50 watts | BA20: iluminación | BD20: M3 | BE20: Led lateral Actilum M3 6k 19 cms. max700 mm | BF20: 0.19 | BG20: =+BJ20*1.3 -> 7755.8 | BH20: 5 | BI20: 0.75 | BJ20: 5966 | BK20: M3 | BM20: armado y electropintado simple 1>4 ml | BN20: 9500 | BS20: 75 | BT20: FP 75 watts- 24v MEAN WELL | BU20: =+BV20*1.5 -> 17628 | BV20: 11752 | BW20: 75
D21: ='Nota de venta'!G15 -> 0 | E21: =IF('Nota de venta'!F15>'Nota de venta'!E15,'Nota de venta'!F15,'Nota de venta'!E15) -> 0 | F21: =IF('Nota de venta'!F15<'Nota de venta'!E15,'Nota de venta'!F15,'Nota de venta'!E15) -> 0 | H21: =IF(ISTEXT(Tabla1[[#This Row],[Producto nro]]),IF(OR(Tabla1[[#This Row],[Producto nro]]="PERFIL 60 MM",Tabla1[[#This Row],[lado + corto]]>1.4),"Malla Front Led 50x150 5k","Led Lateral Actilum M12 -6k, 90 cms max 1000mm"),"") | I21: =VLOOKUP(H21,$BE$15:$BG$29,$R31,FALSE) -> #N/A | J21: =TRUNC((E21-0.03)/I21) -> #N/A | K21: =E21-(J21*I21) -> #N/A | L21: =IF(Tabla1[[#This Row],[Producto nro]]="PERFIL 60 MM","sin luces","sin luces") -> sin luces | M21: =VLOOKUP(L21,$BE$15:$BG$29,$R31,FALSE) -> 0 | N21: =IF(M21=0,0,TRUNC(K21/M21)) -> 0 | O21: =IF(Tabla1[[#This Row],[Producto nro]]="PERFIL 60 MM",1, IF(Tabla1[[#This Row],[led 1]]="",0, IF(Tabla1[[#This Row],[led 1]]="Led Lateral Actilum M12 -6k, 90 cms max 1000mm", IF(Tabla1[[#This Row],[lado + corto]]<0.8,1, IF(Tabla1[[#This Row],[lado + corto]]<140,2,0)),1))) -> 0 | P21: =+$J21*$O21 -> #N/A | Q21: =+$N21*$O21 -> 0 | R21: =+P21*D21 -> #N/A | S21: =+Q21*D21 -> 0 | T21: =+E21*2+F21*2 -> 0 | U21: =IF(T21=0,"",IF(T21<1,"ARMADO MINIMO",IF(T21<=4,"ARMADO SIMPLE",IF(T21<=6,"ARMADO MEDIO",IF(T21<8,"ARMADO COMPLEJO","ARMADO JUMBO"))))) | V21: =IF(AND(Y21="",H21=""),"",IF(ISNUMBER(FIND("DOBLE",Y21)),"sin traseras",IF(OR(H21="Malla Front Led 50x150 5k",H21="malla front led 12v 6000 k"),"alucobond 122x244","trovicel 122"))) | W21: =IF(ISNUMBER(Tabla1[[#This Row],[WATTS]]), IF(Tabla1[[#This Row],[WATTS]]<35,VLOOKUP(35,$BS$14:$BT$22,2,FALSE), IF(Tabla1[[#This Row],[WATTS]]<50,VLOOKUP(50,$BS$14:$BT$22,2,FALSE), IF(Tabla1[[#This Row],[WATTS]]<75,VLOOKUP(75,$BS$14:$BT$22,2,FALSE), IF(Tabla1[[#This Row],[WATTS]]<100,VLOOKUP(100,$BS$14:$BT$22,2,FALSE), IF(Tabla1[[#This Row],[WATTS]]<150,VLOOKUP(150,$BS$14:$BT$22,2,FALSE), IF(Tabla1[[#This Row],[WATTS]]<200,VLOOKUP(200,$BS$14:$BT$22,2,FALSE), IF(Tabla1[[#This Row],[WATTS]]<350,VLOOKUP(350,$BS$14:$BT$22,2,FALSE), IF(Tabla1[[#This Row],[WATTS]]<=400,VLOOKUP(450,$BS$14:$BT$22,2,FALSE), "2 FP 350 watts - 24v MEAN WELL"))))))))) -> FALSE | X21: =+VLOOKUP(Tabla1[[#This Row],[led 1]],$BE$15:$BI$26,AA21,FALSE)*Tabla1[[#This Row],[luces 1 x caja]]+VLOOKUP(Tabla1[[#This Row],[led 2]],$BE$15:$BI$26,AA21,FALSE)*Tabla1[[#This Row],[luces 2 x caja]] -> #N/A | Y21: =IF(C21="","",IF(ISNUMBER(FIND("6",C21)),"PERFIL 60 MM",IF(ISNUMBER(FIND("8",C21)),"PERFIL 80 MM", IF(ISNUMBER(FIND("10",C21)),IF(ISNUMBER(FIND("doble",C21)), "PERFIL 100 MM DOBLE", "PERFIL 100 MM SIMPLE"), "PERFIL 120 MM SIMPLE")))) | Z21: =Tabla1[[#This Row],[mts lineales x caja]]*Tabla1[[#This Row],[Cantidad]] -> 0 | AA21: 4 | AB21: 7 | AC21: =+E21*F21/2 -> 0 | AD21: =VLOOKUP(W21,$BT$14:$BW$22,$T31,FALSE)/X21 -> #N/A | AE21: =+D21*1 -> 0 | AF21: =1.5*D21 -> 0 | AG21: =VLOOKUP(H21,$BE$15:$BK$23,AB21,FALSE) -> #N/A | AH21: =VLOOKUP(L21,$BE$15:$BK$23,AC21,FALSE) -> #VALUE! | BA21: instalación | BD21: Malla 150 | BE21: Malla Front Led 50x150 5k | BF21: 0.3 | BG21: =+BJ21*1.5 -> 40128 | BH21: 60 | BI21: 1 | BJ21: 26752 | BK21: malla 150 | BM21: armado y electropintado medio 4 > 6 ml | BN21: 9000 | BS21: 50 | BT21: FP 50 watts- 24v MEAN WELL | BU21: =+BV21*1.5 -> 13680 | BV21: 9120 | BW21: 50
D22: ='Nota de venta'!G16 -> 0 | E22: =IF('Nota de venta'!F16>'Nota de venta'!E16,'Nota de venta'!F16,'Nota de venta'!E16) -> 0 | F22: =IF('Nota de venta'!F16<'Nota de venta'!E16,'Nota de venta'!F16,'Nota de venta'!E16) -> 0 | H22: =IF(ISTEXT(Tabla1[[#This Row],[Producto nro]]),IF(OR(Tabla1[[#This Row],[Producto nro]]="PERFIL 60 MM",Tabla1[[#This Row],[lado + corto]]>1.4),"Malla Front Led 50x150 5k","Led Lateral Actilum M12 -6k, 90 cms max 1000mm"),"") | I22: =VLOOKUP(H22,$BE$15:$BG$29,$R32,FALSE) -> #N/A | J22: =TRUNC((E22-0.03)/I22) -> #N/A | K22: =E22-(J22*I22) -> #N/A | L22: =IF(Tabla1[[#This Row],[Producto nro]]="PERFIL 60 MM","sin luces","sin luces") -> sin luces | M22: =VLOOKUP(L22,$BE$15:$BG$29,$R32,FALSE) -> 0 | N22: =IF(M22=0,0,TRUNC(K22/M22)) -> 0 | O22: =IF(Tabla1[[#This Row],[Producto nro]]="PERFIL 60 MM",1, IF(Tabla1[[#This Row],[led 1]]="",0, IF(Tabla1[[#This Row],[led 1]]="Led Lateral Actilum M12 -6k, 90 cms max 1000mm", IF(Tabla1[[#This Row],[lado + corto]]<0.8,1, IF(Tabla1[[#This Row],[lado + corto]]<140,2,0)),1))) -> 0 | P22: =+$J22*$O22 -> #N/A | Q22: =+$N22*$O22 -> 0 | R22: =+P22*D22 -> #N/A | S22: =+Q22*D22 -> 0 | T22: =+E22*2+F22*2 -> 0 | U22: =IF(T22=0,"",IF(T22<1,"ARMADO MINIMO",IF(T22<=4,"ARMADO SIMPLE",IF(T22<=6,"ARMADO MEDIO",IF(T22<8,"ARMADO COMPLEJO","ARMADO JUMBO"))))) | V22: =IF(AND(Y22="",H22=""),"",IF(ISNUMBER(FIND("DOBLE",Y22)),"sin traseras",IF(OR(H22="Malla Front Led 50x150 5k",H22="malla front led 12v 6000 k"),"alucobond 122x244","trovicel 122"))) | W22: =IF(ISNUMBER(Tabla1[[#This Row],[WATTS]]), IF(Tabla1[[#This Row],[WATTS]]<35,VLOOKUP(35,$BS$14:$BT$22,2,FALSE), IF(Tabla1[[#This Row],[WATTS]]<50,VLOOKUP(50,$BS$14:$BT$22,2,FALSE), IF(Tabla1[[#This Row],[WATTS]]<75,VLOOKUP(75,$BS$14:$BT$22,2,FALSE), IF(Tabla1[[#This Row],[WATTS]]<100,VLOOKUP(100,$BS$14:$BT$22,2,FALSE), IF(Tabla1[[#This Row],[WATTS]]<150,VLOOKUP(150,$BS$14:$BT$22,2,FALSE), IF(Tabla1[[#This Row],[WATTS]]<200,VLOOKUP(200,$BS$14:$BT$22,2,FALSE), IF(Tabla1[[#This Row],[WATTS]]<350,VLOOKUP(350,$BS$14:$BT$22,2,FALSE), IF(Tabla1[[#This Row],[WATTS]]<=400,VLOOKUP(450,$BS$14:$BT$22,2,FALSE), "2 FP 350 watts - 24v MEAN WELL"))))))))) -> FALSE | X22: =+VLOOKUP(Tabla1[[#This Row],[led 1]],$BE$15:$BI$26,AA22,FALSE)*Tabla1[[#This Row],[luces 1 x caja]]+VLOOKUP(Tabla1[[#This Row],[led 2]],$BE$15:$BI$26,AA22,FALSE)*Tabla1[[#This Row],[luces 2 x caja]] -> #N/A | Y22: =IF(C22="","",IF(ISNUMBER(FIND("6",C22)),"PERFIL 60 MM",IF(ISNUMBER(FIND("8",C22)),"PERFIL 80 MM", IF(ISNUMBER(FIND("10",C22)),IF(ISNUMBER(FIND("doble",C22)), "PERFIL 100 MM DOBLE", "PERFIL 100 MM SIMPLE"), "PERFIL 120 MM SIMPLE")))) | Z22: =Tabla1[[#This Row],[mts lineales x caja]]*Tabla1[[#This Row],[Cantidad]] -> 0 | AA22: 4 | AB22: 7 | AC22: =+E22*F22/2 -> 0 | AD22: =VLOOKUP(W22,$BT$14:$BW$22,$T32,FALSE)/X22 -> #N/A | AE22: =+D22*1 -> 0 | AF22: =1.5*D22 -> 0 | AG22: =VLOOKUP(H22,$BE$15:$BK$23,AB22,FALSE) -> #N/A | AH22: =VLOOKUP(L22,$BE$15:$BK$23,AC22,FALSE) -> #VALUE! | BA22: perfil 6 | BD22: Malla 12v | BE22: Malla front led 12v 6000 k | BF22: 0.3 | BG22: 25000 | BK22: malla 12v | BM22: armado y electropintado complejo 6 > 8 ml | BN22: 8500 | BS22: 35 | BT22: FP 35 watts- 24v MEAN WELL | BU22: =+BV22*1.5 -> 13992 | BV22: 9328 | BW22: 35
A23: E | D23: ='Nota de venta'!G17 -> 0 | E23: =IF('Nota de venta'!F17>'Nota de venta'!E17,'Nota de venta'!F17,'Nota de venta'!E17) -> 0 | F23: =IF('Nota de venta'!F17<'Nota de venta'!E17,'Nota de venta'!F17,'Nota de venta'!E17) -> 0 | H23: =IF(ISTEXT(Tabla1[[#This Row],[Producto nro]]),IF(OR(Tabla1[[#This Row],[Producto nro]]="PERFIL 60 MM",Tabla1[[#This Row],[lado + corto]]>1.4),"Malla Front Led 50x150 5k","Led Lateral Actilum M12 -6k, 90 cms max 1000mm"),"") | I23: =VLOOKUP(H23,$BE$15:$BG$29,$R33,FALSE) -> #N/A | J23: =TRUNC((E23-0.03)/I23) -> #N/A | K23: =E23-(J23*I23) -> #N/A | L23: =IF(Tabla1[[#This Row],[Producto nro]]="PERFIL 60 MM","sin luces","sin luces") -> sin luces | M23: =VLOOKUP(L23,$BE$15:$BG$29,$R33,FALSE) -> 0 | N23: =IF(M23=0,0,TRUNC(K23/M23)) -> 0 | O23: =IF(Tabla1[[#This Row],[Producto nro]]="PERFIL 60 MM",1, IF(Tabla1[[#This Row],[led 1]]="",0, IF(Tabla1[[#This Row],[led 1]]="Led Lateral Actilum M12 -6k, 90 cms max 1000mm", IF(Tabla1[[#This Row],[lado + corto]]<0.8,1, IF(Tabla1[[#This Row],[lado + corto]]<140,2,0)),1))) -> 0 | P23: =+$J23*$O23 -> #N/A | Q23: =+$N23*$O23 -> 0 | R23: =+P23*D23 -> #N/A | S23: =+Q23*D23 -> 0 | T23: =+E23*2+F23*2 -> 0 | U23: =IF(T23=0,"",IF(T23<1,"ARMADO MINIMO",IF(T23<=4,"ARMADO SIMPLE",IF(T23<=6,"ARMADO MEDIO",IF(T23<8,"ARMADO COMPLEJO","ARMADO JUMBO"))))) | V23: =IF(AND(Y23="",H23=""),"",IF(ISNUMBER(FIND("DOBLE",Y23)),"sin traseras",IF(OR(H23="Malla Front Led 50x150 5k",H23="malla front led 12v 6000 k"),"alucobond 122x244","trovicel 122"))) | W23: =IF(ISNUMBER(Tabla1[[#This Row],[WATTS]]), IF(Tabla1[[#This Row],[WATTS]]<35,VLOOKUP(35,$BS$14:$BT$22,2,FALSE), IF(Tabla1[[#This Row],[WATTS]]<50,VLOOKUP(50,$BS$14:$BT$22,2,FALSE), IF(Tabla1[[#This Row],[WATTS]]<75,VLOOKUP(75,$BS$14:$BT$22,2,FALSE), IF(Tabla1[[#This Row],[WATTS]]<100,VLOOKUP(100,$BS$14:$BT$22,2,FALSE), IF(Tabla1[[#This Row],[WATTS]]<150,VLOOKUP(150,$BS$14:$BT$22,2,FALSE), IF(Tabla1[[#This Row],[WATTS]]<200,VLOOKUP(200,$BS$14:$BT$22,2,FALSE), IF(Tabla1[[#This Row],[WATTS]]<350,VLOOKUP(350,$BS$14:$BT$22,2,FALSE), IF(Tabla1[[#This Row],[WATTS]]<=400,VLOOKUP(450,$BS$14:$BT$22,2,FALSE), "2 FP 350 watts - 24v MEAN WELL"))))))))) -> FALSE | X23: =+VLOOKUP(Tabla1[[#This Row],[led 1]],$BE$15:$BI$26,AA23,FALSE)*Tabla1[[#This Row],[luces 1 x caja]]+VLOOKUP(Tabla1[[#This Row],[led 2]],$BE$15:$BI$26,AA23,FALSE)*Tabla1[[#This Row],[luces 2 x caja]] -> #N/A | Y23: =IF(C23="","",IF(ISNUMBER(FIND("6",C23)),"PERFIL 60 MM",IF(ISNUMBER(FIND("8",C23)),"PERFIL 80 MM", IF(ISNUMBER(FIND("10",C23)),IF(ISNUMBER(FIND("doble",C23)), "PERFIL 100 MM DOBLE", "PERFIL 100 MM SIMPLE"), "PERFIL 120 MM SIMPLE")))) | Z23: =Tabla1[[#This Row],[mts lineales x caja]]*Tabla1[[#This Row],[Cantidad]] -> 0 | AA23: 4 | AB23: 7 | AC23: =+E23*F23/2 -> 0 | AD23: =VLOOKUP(W23,$BT$14:$BW$22,$T30,FALSE)/X23 -> #N/A | AE23: =+D23*1 -> 0 | AF23: =1.5*D23 -> 0 | AG23: =VLOOKUP(H23,$BE$15:$BK$23,AB23,FALSE) -> #N/A | AH23: =VLOOKUP(L23,$BE$15:$BK$23,AC23,FALSE) -> #VALUE! | BA23: perfil 8 | BD23: sin luces | BE23: sin luces | BF23: 0 | BG23: 0 | BM23: armado y electropintado jumbo > 8 ml | BN23: 8000 | BT23: 2 FP 350 watts - 24v MEAN WELL | BU23: =BU16*2 -> 80748 | BV23: =BV16*2 -> 44860
A24: F | D24: =SUM(D16:D23) -> 0 | R24: =SUM(R16:R23) -> #N/A | S24: =SUM(S16:S23) -> 0 | BA24: Perfil 10 | BD24: basic 9 focos | BE24: Basic led lateral 9F, 6K, 45 cms 21 watts | BF24: 0.45 | BG24: =BJ24*1.5 -> 24366 | BH24: 21 | BI24: 0.48 | BJ24: 16244 | BK24: 9f 6k | BM24: armado y electropintado exagonal | BN24: 20000
A25: G | D25: valores unitarios | K25: 4000 | BA25: perfil 12 | BM25: armado sin luz minimo <1 | BN25: 25000
A26: H | D26: ILUMINACIÓN | E26: TRASERAS | F26: ARMADO | H26: FP | I26: PERFIL | J26: OTROS UNIT | K26: Pintura ml | L26: Valor Unitario | M26: Valor total neto | R26: 2 | S26: 3 | T26: 4 | BA26: pernos | BM26: armado NO RECTO | BN26: 10000
A27: I | C27: =C16 -> 0 | D27: =VLOOKUP(H16,$BE$15:$BG$29,$S26,FALSE)*P16+VLOOKUP(L16,$BE$15:$BG$29,$S26,FALSE)*Q16 -> #N/A | E27: =VLOOKUP($V16,$BP$14:$BQ$36,$R26,FALSE)*E16*F16 -> #N/A | F27: =VLOOKUP($U16,$BL$14:$BN$66,$S26,FALSE)*T16 -> #N/A | H27: =(VLOOKUP($W16,$BT$14:$BW$23,$R26,FALSE)) -> #N/A | I27: =(VLOOKUP($Y16,$BT$28:$BV$32,$R26,FALSE))*T16 -> #N/A | K27: =+T16*$K$25 -> 0 | L27: =+D27+E27+F27+H27+I27+K27+J27 -> #N/A | M27: =+L27*D16 -> #N/A | R27: 2 | S27: 3 | T27: 4 | Z27: =SUM(Z16:Z26) -> 0 | BA27: esquineros
A28: J | C28: =C17 -> 0 | D28: =VLOOKUP(H17,$BE$15:$BG$29,$S27,FALSE)*P17+VLOOKUP(L17,$BE$15:$BG$29,$S27,FALSE)*Q17 -> #N/A | E28: =VLOOKUP($V17,$BP$14:$BQ$36,$R27,FALSE)*E17*F17 -> #N/A | F28: =VLOOKUP($U17,$BL$14:$BN$66,$S27,FALSE)*T17 -> #N/A | H28: =(VLOOKUP($W17,$BT$14:$BW$23,$R27,FALSE)) -> #N/A | I28: =(VLOOKUP($Y17,$BT$28:$BV$32,$R27,FALSE))*T17 -> #N/A | K28: =+T17*$K$25 -> 0 | L28: =+D28+E28+F28+H28+I28+K28+J28 -> #N/A | M28: =+L28*D17 -> #N/A | R28: 2 | S28: 3 | T28: 4 | BA28: caja frameless 10 exhibidor | BT28: PERFIL 60 MM | BU28: =+BV28*4.5 -> 6973.5 | BV28: 1549.6667
C29: =C18 -> 0 | D29: =VLOOKUP(H18,$BE$15:$BG$29,$S28,FALSE)*P18+VLOOKUP(L18,$BE$15:$BG$29,$S28,FALSE)*Q18 -> #N/A | E29: =VLOOKUP($V18,$BP$14:$BQ$36,$R28,FALSE)*E18*F18 -> #N/A | F29: =VLOOKUP($U18,$BL$14:$BN$66,$S28,FALSE)*T18 -> #N/A | H29: =(VLOOKUP($W18,$BT$14:$BW$23,$R28,FALSE)) -> #N/A | I29: =(VLOOKUP($Y18,$BT$28:$BV$32,$R28,FALSE))*T18 -> #N/A | K29: =+T18*$K$25 -> 0 | L29: =+D29+E29+F29+H29+I29+K29+J29 -> #N/A | M29: =+L29*D18 -> #N/A | R29: 2 | S29: 3 | T29: 4 | BT29: PERFIL 80 MM | BU29: =+BV29*1.7 -> 7995.1 | BV29: 4703
C30: =C19 -> 0 | D30: =VLOOKUP(H19,$BE$15:$BG$29,$S29,FALSE)*P19+VLOOKUP(L19,$BE$15:$BG$29,$S29,FALSE)*Q19 -> #N/A | E30: =VLOOKUP($V19,$BP$14:$BQ$36,$R29,FALSE)*E19*F19 -> #N/A | F30: =VLOOKUP($U19,$BL$14:$BN$66,$S29,FALSE)*T19 -> #N/A | H30: =(VLOOKUP($W19,$BT$14:$BW$23,$R29,FALSE)) -> #N/A | I30: =(VLOOKUP($Y19,$BT$28:$BV$32,$R29,FALSE))*T19 -> #N/A | K30: =+T19*$K$25 -> 0 | L30: =+D30+E30+F30+H30+I30+K30+J30 -> #N/A | M30: =+L30*D19 -> #N/A | R30: 2 | S30: 3 | T30: 4 | BT30: PERFIL 100 MM SIMPLE | BU30: =+BV30*2.3 -> 9830.2 | BV30: 4274
C31: =C20 -> 0 | D31: =VLOOKUP(H20,$BE$15:$BG$29,$S30,FALSE)*P20+VLOOKUP(L20,$BE$15:$BG$29,$S30,FALSE)*Q20 -> #N/A | E31: =VLOOKUP($V20,$BP$14:$BQ$36,$R30,FALSE)*E20*F20 -> #N/A | F31: =VLOOKUP($U20,$BL$14:$BN$66,$S30,FALSE)*T20 -> #N/A | H31: =(VLOOKUP($W20,$BT$14:$BW$23,$R30,FALSE)) -> #N/A | I31: =(VLOOKUP($Y20,$BT$28:$BV$32,$R30,FALSE))*T20 -> #N/A | K31: =+T20*$K$25 -> 0 | L31: =+D31+E31+F31+H31+I31+K31+J31 -> #N/A | M31: =+L31*D20 -> #N/A | R31: 2 | S31: 3 | T31: 4 | BT31: PERFIL 100 MM DOBLE | BU31: =+BV31*2.5 -> 11484.583 | BV31: 4593.8333
C32: =C21 -> 0 | D32: =VLOOKUP(H21,$BE$15:$BG$29,$S31,FALSE)*P21+VLOOKUP(L21,$BE$15:$BG$29,$S31,FALSE)*Q21 -> #N/A | E32: =VLOOKUP($V21,$BP$14:$BQ$36,$R31,FALSE)*E21*F21 -> #N/A | F32: =VLOOKUP($U21,$BL$14:$BN$66,$S31,FALSE)*T21 -> #N/A | H32: =(VLOOKUP($W21,$BT$14:$BW$23,$R31,FALSE)) -> #N/A | I32: =(VLOOKUP($Y21,$BT$28:$BV$32,$R31,FALSE))*T21 -> #N/A | K32: =+T21*$K$25 -> 0 | L32: =+D32+E32+F32+H32+I32+K32+J32 -> #N/A | M32: =+L32*D21 -> #N/A | R32: 2 | S32: 3 | T32: 4 | BT32: PERFIL 120MM DOBLE | BU32: 14000 | BV32: =1550*2 -> 3100
C33: =C22 -> 0 | D33: =VLOOKUP(H22,$BE$15:$BG$29,$S32,FALSE)*P22+VLOOKUP(L22,$BE$15:$BG$29,$S32,FALSE)*Q22 -> #N/A | E33: =VLOOKUP($V22,$BP$14:$BQ$36,$R32,FALSE)*E22*F22 -> #N/A | F33: =VLOOKUP($U22,$BL$14:$BN$66,$S32,FALSE)*T22 -> #N/A | H33: =(VLOOKUP($W22,$BT$14:$BW$23,$R32,FALSE)) -> #N/A | I33: =(VLOOKUP($Y22,$BT$28:$BV$32,$R32,FALSE))*T22 -> #N/A | K33: =+T22*$K$25 -> 0 | L33: =+D33+E33+F33+H33+I33+K33+J33 -> #N/A | M33: =+L33*D22 -> #N/A | R33: 2 | S33: 3 | T33: 4
A34: A | C34: =C23 -> 0 | D34: =VLOOKUP(H23,$BE$15:$BG$29,$S33,FALSE)*P23+VLOOKUP(L23,$BE$15:$BG$29,$S33,FALSE)*Q23 -> #N/A | E34: =VLOOKUP($V23,$BP$14:$BQ$36,$R33,FALSE)*E23*F23 -> #N/A | F34: =VLOOKUP($U23,$BL$14:$BN$66,$S33,FALSE)*T23 -> #N/A | H34: =(VLOOKUP($W23,$BT$14:$BW$23,$R33,FALSE)) -> #N/A | I34: =(VLOOKUP($Y23,$BT$28:$BV$32,$R33,FALSE))*T23 -> #N/A | K34: =+T23*$K$25 -> 0 | L34: =+D34+E34+F34+H34+I34+K34+J34 -> #N/A | M34: =+L34*D23 -> #N/A | R34: 2 | S34: 3 | T34: 4 | AI34: Detalles para el cliente
A35: B | AI35: Caja frameles, tiro y retiro, perfil 12 cms incluye: luces led bajo consumo, textil backlight incluído con terminaciones, fuente de poder.
A36: C | AI36: Caja frameles, tiro y retiro, perfil 10 cms incluye: luces led bajo consumo, textil backlight incluído con terminaciones, fuente de poder.
A37: D | AI37: Caja frameles simple, perfil 10 cms incluye: luces led bajo consumo, textil backlight incluído con terminaciones, fuente de poder.
A38: E | AI38: Caja frameles simple, perfil 8 cms incluye: luces led bajo consumo, textil backlight incluído con terminaciones, fuente de poder.
A39: F | AI39: Caja frameles simple, perfil 6 cms incluye: luces led bajo consumo, textil backlight incluído con terminaciones, fuente de poder.
A40: G | AI40: textil backlight con terminaciones para instalación en perfil frameless
A41: H | AI41: Instalación en un punto
A42: I | AI42: Bastidor 60mm
A43: J | AI43: Bastidor 80mm
AI44: Bastidor 100mm
AI45: Bastidor 120mm
AI46: luces led

Sheet Productos
A1: productos | B1: medida ancho cms | C1: medida alto cms | D1: texto confección | E1: texto producción | F1: confección unit | G1: estructura 1 unit | H1: estructura 2 unit
A2: Asta fibra de vidrio vela 2 mts | G2: 17000
A3: Asta fibra de vidrio vela 3 mts | G3: 19000
A4: Bandera 2,3x1,5 | B4: 234 | C4: 154 | D4: bastas 2 cms doble costura, cinta nylon con 3 pasadores reforzados para argolla media caña | E4: dar 2 cms peimetrales | F4: 5200
A5: Bandera 3x2 | B5: 304 | C5: 204 | D5: bastas 2 cms doble costura, cinta nylon con 4 pasadores reforzados para argolla media caña | E5: dar 2 cms peimetrales | F5: 10300
A6: Bandera 1,5x1 | B6: 154 | C6: 105 | D6: bastas 2 cms doble costura, cinta nylon con 2 pasadores reforzados para argolla media caña | E6: dar 2 cms peimetrales | F6: 4000
A7: Base auto | D7: solo estructura | E7: solo estructura | G7: 11000
A8: Base suelo metal más accesorio para rellenar | D8: solo estructura | E8: solo estructura | G8: 18000
A9: Base suelo plástico para rellenar | D9: solo estructura | E9: solo estructura | G9: 16000
A10: Bolso de transporte con ruedas 1 estructura panel araña | D10: sin confección | E10: solo estructura | F10: 0 | G10: 40000 | H10: 0
A11: Bolso de transporte con ruedas 2 estructuras panel araña | D11: sin confección | E11: solo estructura | F11: 0 | G11: 70000 | H11: 0
A12: Cosmetiquero 20x30 cms 1 cara | B12: 22 | C12: 66 | D12: reverso, cierre y forro al tono, con fuelle 4 cms | E12: solo estructura | F12: 4100 | G12: 0 | H12: 0
A13: Cosmetiquero 20x30 cms tiro y retiro | B13: 22 | C13: 35 | D13: cierre y forro al tono, con fuelle 4 cms | E13: 1 cms laterales, 2 cms arriba. Tiro y retiro unidos abajo dar 2 cms a la unión | F13: 3700 | G13: 0 | H13: 0
A14: Cubre alarma | D14: costuras con recta perimetral y basta simple abajo | E14: 1 cms laterales, 2 cms abajo y 3 cms arriba | F14: 7000 | G14: 0 | H14: 0
A15: Estaca | D15: solo estructura | E15: solo estructura | G15: 10000
A16: Estuche 18x23 cms 1 cara | B16: 20 | C16: 50 | D16: reverso, cierre y forro al tono, sin fuelle | E16: 1 cms laterales, 1 cms abajo y 2 cms arriba | F16: 3300 | G16: 0 | H16: 0
A17: Estuche 18x23 cms tiro y retiro | B17: 20 | C17: 26 | D17: cierre y forro al tono, sin fuelle | E17: 1 cms laterales, 2 cms arriba. Tiro y retiro unidos abajo | F17: 3000 | G17: 0 | H17: 0
A18: Estuche lapicero 5x20 cms | B18: 20 | C18: 25 | D18: cierre y forro al tono, con fuelle 4 cms | E18: 1 pieza de | F18: 3000 | G18: 0 | H18: 0
A19: Estuches lentes 22x12 cms tiro y retiro | B19: 26 | C19: 26 | D19: basta de 2 cms terminada, sin forro. Tira elástica para cerrar. | E19: 1 cms laterales y abajo. Arriba 3 cms para basta | F19: 3000 | G19: 0 | H19: 0
A20: Forro textil soporte muro 2,3x2,3 mts tiro y retiro | B20: 232 | C20: 232 | D20: costuras con overlock y basta simple abajo | E20: dar 1 cms perimetral y coser con trasera mismo tamaño estrcuturas | F20: 8000 | G20: 0 | H20: 0
A21: Funda Almohada 50x70 cms 1 cara , reverso con cruce | B21: 52 | C21: 72 | D21: reverso en tela al tono, con cruce de 10 cms, overlock perimetral | E21: dar 1 cms perimetral | F21: 4500 | G21: 0 | H21: 0
A22: Funda Almohada 50x70 cms tiro y retiro cierre lateral | B22: 52 | C22: 73 | D22: overlock, cierre lateral con pestaña | E22: 1 cms arriba y abajo. Lado derecho con 2 cms para cierre. | F22: 3500 | G22: 0 | H22: 0
A23: Funda Almohada 50x90 cms 1 cara , reverso con cruce | B23: 52 | C23: 92 | D23: reverso en tela al tono, con cruce de 10 cms, overlock perimetral | E23: dar 1 cms perimetral | F23: 5500 | G23: 0 | H23: 0
A24: Funda Almohada 50x90 cms tiro y retiro cierre lateral | B24: 52 | C24: 93 | D24: cierre abajo, overlock | E24: dar 1 cms perimetral laterales y arriba, abajo 2 cms para cierre | F24: 4000 | G24: 0 | H24: 0
A25: Funda Cojín 40x40 cms 1 cara, cierre abajo | B25: 43 | C25: 42 | D25: reverso en tela al tono, cierre abajo, overlock perimetral | E25: dar 1 cms perimetral | F25: 3500 | G25: 0 | H25: 0
A26: Funda Cojín 40x40 cms tiro y retiro, cierre abajo | B26: 43 | C26: 42 | D26: cierre abajo, overlock | E26: dar 1 cms perimetral laterales y arriba, abajo 2 cms para cierre | F26: 3800 | G26: 0 | H26: 0
A27: Funda Cojín 50x50 cms 1 cara, cierre abajo | B27: 53 | C27: 52 | D27: cierre abajo, overlock | E27: dar 1 cms perimetral laterales y arriba, abajo 2 cms para cierre | F27: 4000 | G27: 0 | H27: 0
A28: Funda Cojín 50x50 cms tiro y retiro, cierre abajo | B28: 53 | C28: 52 | D28: cierre abajo, overlock | E28: dar 1 cms perimetral laterales y arriba, abajo 2 cms para cierre | F28: 4200 | G28: 0 | H28: 0
A29: Lienzo con uniones con calce con basta | D29: basta perimetral | E29: dar 2 cms perimetrales para basta, traslape de 2 cms para calce | F29: 20000
A30: Lienzo con uniones con calce con ojetillos perimetrales | D30: basta ancha de 3 cms para ojetillos de 2 cms | E30: dar 4 cms perimetrales para ojetillos reforzados. Traslape de 2 cms para calce | F30: 25000
A31: Lienzo con uniones con calce, bolsillos, fleje plástico arriba y abajo con hilos para colgar transparente | D31: basta lateral y bolsillo de 5 cms terminado arriba y abajo | E31: traslape de paños de 2 cms, 2 cms en los laterales para bastas y 7 cms arriba y abajo para bolsillos de 5 cms terminado | F31: 23000 | G31: 7500 | H31: 4000
A32: Lienzo con uniones con calce, basta o bolsillo SIN estructuras | D32: basta lateral y bolsillo de 5 cms terminado arriba y abajo | E32: traslape de paños de 2 cms, 2 cms en los laterales para bastas y 7 cms arriba y abajo para bolsillos de 5 cms terminado | F32: 23000 | G32: 0 | H32: 0
A33: Lienzo con uniones con calce, bolsillos, madera exterior ambas caras arriba y abajo con cáncamos y cable para colgar | D33: basta lateral y bolsillo de 5 cms terminado arriba y abajo | E33: traslape de paños de 2 cms, 2 cms en los laterales para bastas y 7 cms arriba y abajo para bolsillos de 5 cms terminado | F33: 23000 | G33: 15000 | H33: 4000
A34: Lienzo con uniones con calce, bolsillos, tubo metálico arriba y pletina metálica abajo con cable y candados | D34: basta lateral y bolsillo de 5 cms terminado arriba y abajo | E34: traslape de paños de 2 cms, 2 cms en los laterales para bastas y 7 cms arriba y abajo para bolsillos de 5 cms terminado | F34: 23000 | G34: 12000 | H34: 4000
A35: Lienzo simple con basta o bolsillo SIN estructuras hasta 150cms de ancho | D35: basta lateral y bolsillo de 5 cms terminado arriba y abajo | E35: dar 2 cms en los laterales para bastas y 7 cms arriba y abajo para bolsillos | F35: 10000 | G35: 0 | H35: 0
A36: Lienzo simple con bolsillos hasta 150 cms de ancho, fleje plástico arriba y abajo con hilos para colgar transparente | D36: basta lateral y bolsillo de 5 cms terminado arriba y abajo | E36: dar 2 cms en los laterales para bastas y 7 cms arriba y abajo para bolsillos | F36: 10000 | G36: 7500 | H36: 4000
A37: Lienzo simple con bolsillos hasta 150 cms de ancho, madera exterior ambas caras arriba y abajo con cáncamos y cable para colgar | D37: basta lateral y bolsillo de 5 cms terminado arriba y abajo | E37: dar 2 cms en los laterales para bastas y 7 cms arriba y abajo para bolsillos | F37: 10000 | G37: 15000 | H37: 4000
A38: Lienzo simple con bolsillos hasta 150 cms de ancho, tubo metálico arriba y pletina metálica abajo con cable y candados | D38: basta lateral y bolsillo de 5 cms terminado arriba y abajo | E38: dar 2 cms en los laterales para bastas y 7 cms arriba y abajo para bolsillos | F38: 10000 | G38: 12000 | H38: 4000
A39: Lienzo simple con ojetillos perimetrales reforzados cada 30 cms | D39: basta lateral y bolsillo de 5 cms terminado arriba y abajo | E39: dar 4 cms perimetrales y refuerzo para ojetillos | F39: 15000 | G39: 0 | H39: 0
A40: Lienzo simple con ojetillos perimetrales reforzados cada 50 cms | D40: basta lateral y bolsillo de 5 cms terminado arriba y abajo | E40: dar 4 cms perimetrales y refuerzo para ojetillos | F40: 16000 | G40: 0 | H40: 0
A41: Lienzo simple con ojetillos reforzados 4 esquinas | D41: basta lateral y bolsillo de 5 cms terminado arriba y abajo | E41: excedente 2 cms para basta y refuerzo en las puntas con tela firme | F41: 12000 | G41: 0 | H41: 0
A42: Lienzo tiro y retiro con basta o bolsillos SIN estructuras | D42: basta lateral y bolsillo de 5 cms terminado arriba y abajo | E42: dar 2 cms perimetrales para confección | F42: 18000 | G42: 0 | H42: 0
A43: Lienzo tiro y retiro con uniones con calce sin estructutas | D43: basta lateral y bolsillo de 5 cms terminado arriba y abajo | E43: dar 2 cms en los laterales para bastas y 7 cms arriba y abajo para bolsillos/basta, traslape de 2 cms para calce | F43: 23000
A44: Lienzo tiro y retiro con uniones con calce, bolsillo tubo metálico arriba y pletina metálica abajo con cable y candados | D44: basta lateral y bolsillo de 5 cms terminado arriba y abajo | E44: dar 2 cms en los laterales para bastas y 7 cms arriba y abajo para bolsillos/basta, traslape de 2 cms para calce | F44: 45000 | G44: 15000 | H44: 4000
A45: Lienzo tiro y retiro, madera exterior ambas caras arriba y abajo con cáncamos y cable para colgar | D45: basta lateral y bolsillo de 5 cms terminado arriba y abajo | E45: dar 2 cms en los laterales para bastas y 7 cms arriba y abajo para bolsillos | F45: 18000 | G45: 15000 | H45: 7000
A46: Lienzo tiro y retiro, tubo metálico arriba y pletina metálica abajo con cable y candados | D46: basta lateral y bolsillo de 5 cms terminado arriba y abajo | E46: dar 2 cms perimetrales para confección | F46: 18000 | G46: 12000 | H46: 5000
A47: Mantel basta perimetral 150x150 | B47: 150 | C47: 150 | D47: basta perimetral | E47: dar 2 cms perimetrales para confección | F47: 4000 | G47: 0 | H47: 0
A48: Mantel con calce y basta 210x300 | B48: 212 | C48: 3.02 | D48: calce y basta perimetral | E48: calce con traslape de 2 cms, 2 cms perimetrales para basta | F48: 7000 | G48: 0 | H48: 0
A49: Panel araña 1 cuerpo (228 cms alto x 75 cms de ancho) con textil | B49: 232 | C49: 79 | D49: velcro perimetral | E49: 2 cms perimetral para velcro | F49: 10000 | G49: 85000 | H49: 0
A50: Panel araña 1 cuerpo (228 cms alto x 75 cms de ancho) solo estructura | D50: velcro perimetral | E50: solo soporte | F50: 0 | G50: 85000 | H50: 0
A51: Panel araña 2 cuerpos (228 cms alto x 150 cms de ancho) con textil | B51: 232 | C51: 254 | D51: velcro perimetral | E51: 2 cms perimetral para velcro | F51: 15000 | G51: 120000 | H51: 0
A52: Panel araña 2 cuerpos (228 cms alto x 150 cms de ancho) solo estructura | D52: velcro perimetral | E52: solo soporte | G52: 12000 | H52: 0
A53: Panel araña 3 cuerpos (228 cms alto x 230 cms de ancho) con textil | B53: 232 | C53: 234 | D53: velcro perimetral | E53: 2 cms perimetral para velcro | F53: 18000 | G53: 140000 | H53: 0
A54: Panel araña 3 cuerpos (228 cms alto x 230 cms de ancho) solo estructura | D54: velcro perimetral | E54: solo soporte | F54: 0 | G54: 140000 | H54: 0
A55: Panel araña 4 cuerpos (228 cms alto x 300 cms de ancho) con textil | B55: 232 | C55: 304 | D55: velcro perimetral | E55: 2 cms perimetral para velcro | F55: 20000 | G55: 170000 | H55: 0
A56: Panel araña 4 cuerpos (228 cms alto x 300 cms de ancho) solo estructura | D56: velcro perimetral | E56: solo soporte | F56: 0 | G56: 170000 | H56: 0
A57: Panel araña 5 cuerpos (228 cms alto x 375 cms de ancho) con textil | B57: 232 | C57: 379 | D57: velcro perimetral | E57: 2 cms perimetral para velcro | F57: 23000 | G57: 205000 | H57: 0
A58: Panel araña 5 cuerpos (228 cms alto x 375 cms de ancho) solo estructura | D58: velcro perimetral | E58: solo soporte | F58: 0 | G58: 205000 | H58: 0
A59: Panel araña 6 cuerpos (228 cms alto x 450 cms de ancho) con textil | B59: 232 | C59: 454 | D59: velcro perimetral | E59: 2 cms perimetral para velcro | F59: 25000 | G59: 245000 | H59: 0
A60: Panel araña 6 cuerpos (228 cms alto x 450 cms de ancho) solo estructura | D60: velcro perimetral | E60: solo soporte | F60: 0 | G60: 245000 | H60: 0
A61: Pañuelo 100x100 cms | B61: 104 | C61: 104 | D61: basta perimetra fina | E61: dar 2 cms perimetrales para confección | F61: 5000 | G61: 0 | H61: 0
A62: Pañuelo 50x50 cms | B62: 54 | C62: 54 | D62: basta perimetra fina | E62: dar 2 cms perimetrales para confección | F62: 2000 | G62: 0 | H62: 0
A63: Pañuelo 70x70 cms | B63: 74 | C63: 74 | D63: basta perimetra fina | E63: dar 2 cms perimetrales para confección | F63: 3000 | G63: 0 | H63: 0
A64: Pañuelo 90x90 cms | B64: 94 | C64: 94 | D64: basta perimetra fina | E64: dar 2 cms perimetrales para confección | F64: 4000 | G64: 0 | H64: 0
A65: Pareo 140x140 cms | B65: 144 | C65: 144 | D65: basta perimetra fina | E65: dar 2 cms perimetrales para confección | F65: 6000 | G65: 0 | H65: 0
A66: Pechera adulto con boslillo | B66: 62 | C66: 92 | D66: bolsillo con sesgo y costura al medio | E66: dar 1 cms perimetral | F66: 6000 | G66: 0 | H66: 0
A67: Pechera adulto simple | B67: 62 | C67: 67 | D67: sesgo perimetral | E67: dar 1 cms perimetral | F67: 4000 | G67: 0 | H67: 0
A68: Pechera niño con bolsillo | B68: 42 | C68: 66 | D68: bolsillo con sesgo y costura al medio | E68: dar 1 cms perimetral | F68: 4500 | G68: 0 | H68: 0
A69: Pechera niño simple | B69: 42 | C69: 47 | D69: sesgo perimetral | E69: dar 1 cms perimetral | F69: 3000 | G69: 0 | H69: 0
A70: Piecera 2plazas con basta | B70: 45 | C70: 202 | D70: basta perimetral | E70: 2 cms laterales y 3 cms arriba y abajo para embolsar | F70: 6000 | G70: 0 | H70: 0
A71: Piecera 2plazas con forro | B71: 45 | C71: 202 | D71: forro embolsado de popelina de color | E71: 2 cms laterales y 3 cms arriba y abajo para embolsar | F71: 8000 | G71: 0 | H71: 0
A72: Piecera king con basta | B72: 57 | C72: 242 | D72: basta perimetral | E72: 2 cms laterales y 3 cms arriba y abajo para embolsar | F72: 7000 | G72: 0 | H72: 0
A73: Piecera king con forro | B73: 57 | C73: 242 | D73: forro embolsado de popelina de color | E73: 2 cms laterales y 3 cms arriba y abajo para embolsar | F73: 10000 | G73: 0 | H73: 0
A74: Soporte muro textil tubo aluminio 2.3x2.3 mts | D74: sin confección | E74: solo soporte | F74: 0 | G74: 96000 | H74: 0
A75: Soporte muro textil tubo aluminio 2.3x2.3 mts + forro textil tiro y retiro | B75: 232 | C75: 232 | D75: costuras con overlock y basta simple abajo | E75: dar 1 cms perimetral y coser con trasera mismo tamaño estrcuturas | F75: 8000 | G75: 96000 | H75: 0
A76: Textil panel araña 1 cuerpo (228 cms alto x 75 cms de ancho) sin estructura | B76: 232 | C76: 79 | D76: velcro perimetral | E76: 2 cms perimetral para velcro | F76: 10000 | G76: 0 | H76: 0
A77: Textil panel araña 2 cuerpos (228 cms alto x 150 cms de ancho) sin estructura | B77: 232 | C77: 254 | D77: velcro perimetral | E77: 2 cms perimetral para velcro | F77: 15000 | G77: 0 | H77: 0
A78: Textil panel araña 3 cuerpos (228 cms alto x 230 cms de ancho) sin estructura | B78: 232 | C78: 234 | D78: velcro perimetral | E78: 2 cms perimetral para velcro | F78: 18000 | G78: 0 | H78: 0
A79: Textil panel araña 4 cuerpos (228 cms alto x 300 cms de ancho) sin estructura | B79: 232 | C79: 304 | D79: velcro perimetral | E79: 2 cms perimetral para velcro | F79: 20000 | G79: 0 | H79: 0
A80: Textil panel araña 5 cuerpos (228 cms alto x 375 cms de ancho) sin estructura | B80: 232 | C80: 379 | D80: velcro perimetral | E80: 2 cms perimetral para velcro | F80: 23000 | G80: 0 | H80: 0
A81: Textil panel araña 6 cuerpos (228 cms alto x 450 cms de ancho) sin estructura | B81: 232 | C81: 454 | D81: velcro perimetral | E81: 2 cms perimetral para velcro | F81: 25000 | G81: 0 | H81: 0
A82: Totebag 30x40 1 cara sin fuelle | B82: 32 | C82: 51 | D82: tirantes misma tela , costura overlock con seguridad, refuerzo X en manillas, basta arriba doble de 5 cms terminada | E82: dar 1 cms laterales y abajo, arriba dejar 11 cms para basta reforzada | F82: 4000 | G82: 0 | H82: 0
A83: Totebag 30x40 tiro y retiro sin fuelle | B83: 32 | C83: 100 | D83: tirantes misma tela , costura overlock con seguridad, refuerzo X en manillas, basta arriba doble de 5 cms terminada | E83: 1 cms laterales, 11 cms arriba. Tiro y retiro unidos abajo | F83: 4000 | G83: 0 | H83: 0
A84: Vela 70x200 con asta de fibra de vidrio y base metálica suelo | B84: 74 | C84: 204 | D84: elastico lateral, basta simple abajo y lado recto | E84: dar 2 cms perimetrales para confección | F84: 6000 | G84: 17000 | H84: 21000
A85: Vela 70x200 con asta de fibra de vidrio y base plástica suelo | B85: 74 | C85: 204 | D85: elastico lateral, basta simple abajo y lado recto | E85: dar 2 cms perimetrales para confección | F85: 6000 | G85: 17000 | H85: 18000
A86: Vela 70x200 con asta de fibra de vidrio y estaca | B86: 74 | C86: 204 | D86: elastico lateral, basta simple abajo y lado recto | E86: dar 2 cms perimetrales para confección | F86: 6000 | G86: 17000 | H86: 10000
... A98: Vela 90x300 solo con asta de fibra de vidrio | B98: 94 | C98: 304 | D98: elastico lateral, basta simple abajo y lado recto | E98: dar 2 cms perimetrales para confección | F98: 8000 | G98: 19000 | H98: 0
A99: Textil Backlight | F99: 0 | G99: 0 | H99: 0
A100: Caja + Backlight | F100: 0 | G100: 0 | H100: 0
